Workbook

Sheet 畅想结算中心
A1: 发票号码 | B1: 财务期间 | C1: 客户编号 | D1: 渠道类型 | E1: 畅想部门 | F1: 畅想组别 | G1: 销品公司 | H1: 分公司 | I1: 销品小组 | J1: 一级目录 | K1: 二级目录 | L1: 三级目录 | M1: SPU | N1: 产品编号 | O1: 产品经理 | P1: 开发类型 | Q1: 外销币种 | R1: USD汇率 | S1: 应收货款 | T1: 应收货款（美元） | U1: 信保费用 | V1: 银行费用 | W1: 佣金 | X1: 采购金额（含税销售） | Y1: 减：退税额 | Z1: 出运包干费 | AA1: 单证费 | AB1: 海运及保险费 | AC1: 国内其他费用 | AD1: 仓储费 | AE1: 验货费 | AF1: 包装设计费 | AG1: 毛利
A2: HSA25J004-A | B2: 46047 | C2: 波兰749 | D2: 渠道商 | E2: 昊特赛八公司 | F2: 办公室 | H2: 市场七一司 | I2: 业务办公室 | J2: 露营和远足 | K2: 户外家具 | L2: 庭院吊篮 | N2: PO-OF5001-002 | O2: 王柯飞 | P2: 外部引进 | Q2: USD | R2: 6.96 | S2: 5140.8 | T2: 5140.8 | U2: 35.99 | V2: 50 | W2: 0 | X2: 34272 | Y2: 3942.8 | Z2: 2909.65 | AA2: 0 | AB2: 0 | AC2: 0 | AD2: 0 | AE2: 0 | AF2: 0 | AG2: =(T2-U2-V2-W2)*R2-X2+Y2-Z2-AA2-AB2-AC2-AD2-AE2-AF2 -> 1942.6276 | AH2: =IF(ISNUMBER(MATCH(A2,'畅想出运数据（核算明细导出）'!$C$2:$C$484,0)),"有","无") -> 有
A3: HSA25J007-2 | B3: 46047 | C3: 波兰749 | D3: 渠道商 | E3: 昊特赛三公司 | F3: 办公室 | H3: 市场七一司 | I3: 业务办公室 | J3: 户外骑行和滑板 | K3: 自行车 | L3: 自行车铃铛 | N3: PO-CS3001-004 | O3: 王柯飞 | P3: 外部引进 | Q3: USD | R3: 6.96 | S3: 0 | T3: 0 | U3: 0 | V3: 0 | W3: 0 | X3: 3526.4 | Y3: 405.69 | Z3: 495.98 | AA3: 0 | AB3: 0 | AC3: 0 | AD3: 0 | AE3: 0 | AF3: 0 | AG3: =(T3-U3-V3-W3)*R3-X3+Y3-Z3-AA3-AB3-AC3-AD3-AE3-AF3 -> -3616.69 | AH3: =IF(ISNUMBER(MATCH(A3,'畅想出运数据（核算明细导出）'!$C$2:$C$484,0)),"有","无") -> 有
A4: HSA25J007-2 | B4: 46047 | C4: 波兰749 | D4: 渠道商 | E4: 昊特赛三公司 | F4: 办公室 | H4: 市场七一司 | I4: 业务办公室 | J4: 园林装饰 | K4: 喷泉及其他园林装饰品 | L4: 风车 | N4: PO-CS3001-001 | O4: 王柯飞 | P4: 外部引进 | Q4: USD | R4: 6.96 | S4: 1216 | T4: 1216 | U4: 8.51 | V4: 50 | W4: 0 | X4: 4803.2 | Y4: 552.58 | Z4: 638.26 | AA4: 0 | AB4: 0 | AC4: 0 | AD4: 0 | AE4: 0 | AF4: 0 | AG4: =(T4-U4-V4-W4)*R4-X4+Y4-Z4-AA4-AB4-AC4-AD4-AE4-AF4 -> 3167.2504 | AH4: =IF(ISNUMBER(MATCH(A4,'畅想出运数据（核算明细导出）'!$C$2:$C$484,0)),"有","无") -> 有
A5: HSA25Y007-1 | B5: 46047 | C5: 波兰749 | D5: 渠道商 | E5: 昊特赛一公司 | F5: 客户第一组 | H5: 市场七一司 | I5: 客户第二组 | J5: DIY玩具 | K5: 其他DIY玩具 | L5: 其他常规DIY玩具 | M5: 0C003 | N5: OC003-MQ-brown | O5: 原柯冬浩 | P5: 外部引进 | Q5: USD | R5: 6.98 | S5: 1108.8 | T5: 1108.8 | U5: 7.76 | V5: 50 | W5: 0 | X5: 7358.4 | Y5: 846.54 | Z5: 1829.26 | AA5: 0 | AB5: 0 | AC5: 0 | AD5: 0 | AE5: 0 | AF5: 0 | AG5: =(T5-U5-V5-W5)*R5-X5+Y5-Z5-AA5-AB5-AC5-AD5-AE5-AF5 -> -1004.8608 | AH5: =IF(ISNUMBER(MATCH(A5,'畅想出运数据（核算明细导出）'!$C$2:$C$484,0)),"有","无") -> 有
A6: HSA25D001-2,HSA25D006-2 | B6: 46047 | C6: 波兰749 | D6: 渠道商 | E6: 昊特赛一公司 | F6: 客户第一组 | H6: 市场七一司 | I6: 客户第二组 | J6: 工艺陶瓷 | K6: 陶瓷工艺品 | L6: 常规陶瓷工艺品 | N6: GD-PC200-1023 | O6: 钟 琪 | P6: 外部引进 | Q6: USD | R6: 6.97 | S6: 1900.8 | T6: 1900.8 | U6: 13.31 | V6: 41.27 | W6: 0 | X6: 12960 | Y6: 1032.21 | Z6: 1162.05 | AA6: 0 | AB6: 0 | AC6: 0 | AD6: 0 | AE6: 0 | AF6: 0 | AG6: =(T6-U6-V6-W6)*R6-X6+Y6-Z6-AA6-AB6-AC6-AD6-AE6-AF6 -> -221.6866 | AH6: =IF(ISNUMBER(MATCH(A6,'畅想出运数据（核算明细导出）'!$C$2:$C$484,0)),"有","无") -> 有
A7: HSA25D001-2,HSA25D006-2 | B7: 46047 | C7: 波兰749 | D7: 渠道商 | E7: 昊特赛一公司 | F7: 客户第一组 | H7: 市场七一司 | I7: 客户第二组 | J7: 工艺陶瓷 | K7: 陶瓷工艺品 | L7: 常规陶瓷工艺品 | N7: GD-PC100-1001 | O7: 钟 琪 | P7: 外部引进 | Q7: USD | R7: 6.97 | S7: 402 | T7: 402 | U7: 2.81 | V7: 8.73 | W7: 0 | X7: 2640 | Y7: 210.27 | Z7: 497.16 | AA7: 0 | AB7: 0 | AC7: 0 | AD7: 0 | AE7: 0 | AF7: 0 | AG7: =(T7-U7-V7-W7)*R7-X7+Y7-Z7-AA7-AB7-AC7-AD7-AE7-AF7 -> -205.3838 | AH7: =IF(ISNUMBER(MATCH(A7,'畅想出运数据（核算明细导出）'!$C$2:$C$484,0)),"有","无") -> 有
A8: HSA25J006 | B8: 46047 | C8: 波兰749 | D8: 渠道商 | E8: 昊特赛一公司 | F8: 客户第二组 | H8: 市场七一司 | I8: 客户第二组 | J8: 专用材料 | K8: 隔热材料 | L8: 常规隔热材料 | N8: BF-SM3001-002 | O8: 王柯飞 | P8: 外部引进 | Q8: USD | R8: 6.98 | S8: 485 | T8: 485 | U8: 3.39 | V8: 24.04 | W8: 0 | X8: 2500 | Y8: 287.61 | Z8: 504.89 | AA8: 0 | AB8: 0 | AC8: 0 | AD8: 0 | AE8: 0 | AF8: 0 | AG8: =(T8-U8-V8-W8)*R8-X8+Y8-Z8-AA8-AB8-AC8-AD8-AE8-AF8 -> 476.5586 | AH8: =IF(ISNUMBER(MATCH(A8,'畅想出运数据（核算明细导出）'!$C$2:$C$484,0)),"有","无") -> 有
A9: HSA25J006 | B9: 46047 | C9: 波兰749 | D9: 渠道商 | E9: 昊特赛一公司 | F9: 客户第二组 | H9: 市场七一司 | I9: 客户第二组 | J9: 专用材料 | K9: 隔热材料 | L9: 常规隔热材料 | N9: BF-SM3001-001 | O9: 王柯飞 | P9: 外部引进 | Q9: USD | R9: 6.98 | S9: 523.8 | T9: 523.8 | U9: 3.67 | V9: 25.96 | W9: 0 | X9: 2700 | Y9: 310.62 | Z9: 605.86 | AA9: 0 | AB9: 0 | AC9: 0 | AD9: 0 | AE9: 0 | AF9: 0 | AG9: =(T9-U9-V9-W9)*R9-X9+Y9-Z9-AA9-AB9-AC9-AD9-AE9-AF9 -> 454.0666 | AH9: =IF(ISNUMBER(MATCH(A9,'畅想出运数据（核算明细导出）'!$C$2:$C$484,0)),"有","无") -> 有
A10: HSA25J010-1 | B10: 46047 | C10: 波兰749 | D10: 渠道商 | E10: 昊特赛一公司 | F10: 客户第二组 | H10: 市场七一司 | I10: 客户第二组 | J10: 家庭收纳 | K10: 收纳容器 | L10: 收纳盒 | N10: HS-HO100-1001 | O10: 钟 琪 | P10: 外部引进 | Q10: USD | R10: 6.96 | S10: 1229.76 | T10: 1229.76 | U10: 8.61 | V10: 50 | W10: 0 | X10: 8064 | Y10: 927.72 | Z10: 672.98 | AA10: 0 | AB10: 0 | AC10: 0 | AD10: 0 | AE10: 0 | AF10: 0 | AG10: =(T10-U10-V10-W10)*R10-X10+Y10-Z10-AA10-AB10-AC10-AD10-AE10-AF10 -> 341.944 | AH10: =IF(ISNUMBER(MATCH(A10,'畅想出运数据（核算明细导出）'!$C$2:$C$484,0)),"有","无") -> 有
A11: HSC25X010-1 | B11: 46047 | C11: 美国5529 | D11: 渠道商 | E11: 昊特赛三公司 | F11: 客户第一组 | H11: 市场七三司 | I11: 客户第一组 | J11: 备菜工具 | K11: 刀具及配件 | L11: 水果刀 | N11: 99270 | O11: 黄家辉 | P11: 外部引进 | Q11: USD | R11: 6.95 | S11: 1434 | T11: 1434 | U11: 10.04 | V11: 8.14 | W11: 0 | X11: 8400 | Y11: 966.37 | Z11: 261.82 | AA11: 0 | AB11: 0 | AC11: 0 | AD11: 0 | AE11: 0 | AF11: 0 | AG11: =(T11-U11-V11-W11)*R11-X11+Y11-Z11-AA11-AB11-AC11-AD11-AE11-AF11 -> 2144.499 | AH11: =IF(ISNUMBER(MATCH(A11,'畅想出运数据（核算明细导出）'!$C$2:$C$484,0)),"有","无") -> 有
A12: HSC25X010-1 | B12: 46047 | C12: 美国5529 | D12: 渠道商 | E12: 昊特赛三公司 | F12: 客户第一组 | H12: 市场七三司 | I12: 客户第一组 | J12: 备菜工具 | K12: 刀具及配件 | L12: 切菜刀 | N12: 99272 | O12: 黄家辉 | P12: 自主研发 | Q12: USD | R12: 6.95 | S12: 1434 | T12: 1434 | U12: 10.04 | V12: 8.14 | W12: 0 | X12: 8700 | Y12: 1000.88 | Z12: 261.82 | AA12: 0 | AB12: 0 | AC12: 0 | AD12: 0 | AE12: 0 | AF12: 0 | AG12: =(T12-U12-V12-W12)*R12-X12+Y12-Z12-AA12-AB12-AC12-AD12-AE12-AF12 -> 1879.009 | AH12: =IF(ISNUMBER(MATCH(A12,'畅想出运数据（核算明细导出）'!$C$2:$C$484,0)),"有","无") -> 有
A13: HSC25X001-X002 | B13: 46047 | C13: 加拿大925 | D13: 渠道商 | E13: 昊特赛三公司 | F13: 客户第一组 | H13: 市场七三司 | I13: 客户第一组 | J13: 备菜工具 | K13: 洗菜及沥水篮 | L13: 沥水篮 | N13: 03-3104145 | O13: 黄家辉 | P13: 外部引进 | Q13: USD | R13: 6.96 | S13: 4230 | T13: 4230 | U13: 29.61 | V13: 33.1 | W13: 0 | X13: 28800 | Y13: 3313.27 | Z13: 2175.85 | AA13: 0 | AB13: 0 | AC13: 0 | AD13: 0 | AE13: 0 | AF13: 0 | AG13: =(T13-U13-V13-W13)*R13-X13+Y13-Z13-AA13-AB13-AC13-AD13-AE13-AF13 -> 1341.7584 | AH13: =IF(ISNUMBER(MATCH(A13,'畅想出运数据（核算明细导出）'!$C$2:$C$484,0)),"有","无") -> 有
A14: HSC25X010-1 | B14: 46047 | C14: 美国5529 | D14: 渠道商 | E14: 昊特赛三公司 | F14: 客户第一组 | H14: 市场七三司 | I14: 客户第一组 | J14: 备菜工具 | K14: 刀具及配件 | L14: 刀具套装 | N14: 99278 | O14: 黄家辉 | P14: 自主研发 | Q14: USD | R14: 6.95 | S14: 1995 | T14: 1995 | U14: 13.97 | V14: 11.32 | W14: 0 | X14: 12180 | Y14: 1401.24 | Z14: 320 | AA14: 0 | AB14: 0 | AC14: 0 | AD14: 0 | AE14: 0 | AF14: 0 | AG14: =(T14-U14-V14-W14)*R14-X14+Y14-Z14-AA14-AB14-AC14-AD14-AE14-AF14 -> 2590.7245 | AH14: =IF(ISNUMBER(MATCH(A14,'畅想出运数据（核算明细导出）'!$C$2:$C$484,0)),"有","无") -> 有
A15: HSC25X015-1 | B15: 46047 | C15: 以色列383 | D15: 品牌商 | E15: 昊特赛三公司 | F15: 客户第一组 | H15: 市场七三司 | I15: 客户第一组 | J15: 厨房清洁 | K15: 清洁工具 | L15: 厨房清洁海绵 | N15: 2376 | O15: 黄家辉 | P15: 外部引进 | Q15: USD | R15: 6.96 | S15: 5940 | T15: 5940 | U15: 41.58 | V15: 50 | W15: 0 | X15: 33480 | Y15: 3851.68 | Z15: 1900 | AA15: 0 | AB15: 0 | AC15: 0 | AD15: 0 | AE15: 0 | AF15: 0 | AG15: =(T15-U15-V15-W15)*R15-X15+Y15-Z15-AA15-AB15-AC15-AD15-AE15-AF15 -> 9176.6832 | AH15: =IF(ISNUMBER(MATCH(A15,'畅想出运数据（核算明细导出）'!$C$2:$C$484,0)),"有","无") -> 有
A16: HSC25X010-1 | B16: 46047 | C16: 美国5529 | D16: 渠道商 | E16: 昊特赛三公司 | F16: 客户第一组 | H16: 市场七三司 | I16: 客户第一组 | J16: 备菜工具 | K16: 刀具及配件 | L16: 切骨刀 | N16: 99276 | O16: 黄家辉 | P16: 自主研发 | Q16: USD | R16: 6.95 | S16: 1974 | T16: 1974 | U16: 13.82 | V16: 11.2 | W16: 0 | X16: 11790 | Y16: 1356.37 | Z16: 378.18 | AA16: 0 | AB16: 0 | AC16: 0 | AD16: 0 | AE16: 0 | AF16: 0 | AG16: =(T16-U16-V16-W16)*R16-X16+Y16-Z16-AA16-AB16-AC16-AD16-AE16-AF16 -> 2733.601 | AH16: =IF(ISNUMBER(MATCH(A16,'畅想出运数据（核算明细导出）'!$C$2:$C$484,0)),"有","无") -> 有
A17: HSC25X001-X002 | B17: 46047 | C17: 加拿大925 | D17: 渠道商 | E17: 昊特赛三公司 | F17: 客户第一组 | H17: 市场七三司 | I17: 客户第一组 | J17: 备菜工具 | K17: 洗菜及沥水篮 | L17: 沥水篮 | N17: 03-3092760 | O17: 黄家辉 | P17: 外部引进 | Q17: USD | R17: 6.96 | S17: 2160 | T17: 2160 | U17: 15.12 | V17: 16.9 | W17: 0 | X17: 13992 | Y17: 1609.7 | Z17: 857.15 | AA17: 0 | AB17: 0 | AC17: 0 | AD17: 0 | AE17: 0 | AF17: 0 | AG17: =(T17-U17-V17-W17)*R17-X17+Y17-Z17-AA17-AB17-AC17-AD17-AE17-AF17 -> 1571.2908 | AH17: =IF(ISNUMBER(MATCH(A17,'畅想出运数据（核算明细导出）'!$C$2:$C$484,0)),"有","无") -> 有
A18: HSC25X010-1 | B18: 46047 | C18: 美国5529 | D18: 渠道商 | E18: 昊特赛三公司 | F18: 客户第一组 | H18: 市场七三司 | I18: 客户第一组 | J18: 备菜工具 | K18: 刀具及配件 | L18: 切菜刀 | N18: 99274 | O18: 黄家辉 | P18: 自主研发 | Q18: USD | R18: 6.95 | S18: 1974 | T18: 1974 | U18: 13.82 | V18: 11.2 | W18: 0 | X18: 11790 | Y18: 1356.37 | Z18: 378.18 | AA18: 0 | AB18: 0 | AC18: 0 | AD18: 0 | AE18: 0 | AF18: 0 | AG18: =(T18-U18-V18-W18)*R18-X18+Y18-Z18-AA18-AB18-AC18-AD18-AE18-AF18 -> 2733.601 | AH18: =IF(ISNUMBER(MATCH(A18,'畅想出运数据（核算明细导出）'!$C$2:$C$484,0)),"有","无") -> 有
A19: HSB25M024-8 | B19: 46047 | C19: 英国2962 | D19: 渠道商 | E19: 昊特赛二公司 | F19: 办公室 | H19: 市场七二司 | I19: 业务办公室 | J19: 装扮玩具 | K19: 其他装扮玩具 | L19: 其他常规装扮玩具 | M19: 0D322 | N19: 0D322-PS001 | O19: 丁迎全 | P19: 外部引进 | Q19: USD | R19: 6.95 | S19: 376.32 | T19: 376.32 | U19: 2.63 | V19: 3.69 | W19: 11.29 | X19: 2916.48 | Y19: 335.52 | Z19: 0 | AA19: 0 | AB19: 0 | AC19: 0 | AD19: 0 | AE19: 0 | AF19: 0 | AG19: =(T19-U19-V19-W19)*R19-X19+Y19-Z19-AA19-AB19-AC19-AD19-AE19-AF19 -> -87.9255 | AH19: =IF(ISNUMBER(MATCH(A19,'畅想出运数据（核算明细导出）'!$C$2:$C$484,0)),"有","无") -> 有
A20: HSB25M024-11 | B20: 46047 | C20: 英国2962 | D20: 渠道商 | E20: 昊特赛二公司 | F20: 办公室 | H20: 市场七二司 | I20: 业务办公室 | J20: 装扮玩具 | K20: 其他装扮玩具 | L20: 其他常规装扮玩具 | M20: 0D322 | N20: 0D322-PS001 | O20: 丁迎全 | P20: 外部引进 | Q20: USD | R20: 6.96 | S20: 384 | T20: 384 | U20: 2.69 | V20: 3.79 | W20: 11.52 | X20: 2976 | Y20: 342.37 | Z20: 119.48 | AA20: 0 | AB20: 0 | AC20: 0 | AD20: 0 | AE20: 0 | AF20: 0 | AG20: =(T20-U20-V20-W20)*R20-X20+Y20-Z20-AA20-AB20-AC20-AD20-AE20-AF20 -> -205.75 | AH20: =IF(ISNUMBER(MATCH(A20,'畅想出运数据（核算明细导出）'!$C$2:$C$484,0)),"有","无") -> 有
A21: HSB25M024-10 | B21: 46047 | C21: 英国2962 | D21: 渠道商 | E21: 昊特赛二公司 | F21: 办公室 | H21: 市场七二司 | I21: 业务办公室 | J21: 装扮玩具 | K21: 其他装扮玩具 | L21: 其他常规装扮玩具 | M21: 0D322 | N21: 0D322-PS001 | O21: 丁迎全 | P21: 外部引进 | Q21: USD | R21: 6.96 | S21: 376.32 | T21: 376.32 | U21: 2.63 | V21: 3.61 | W21: 7.53 | X21: 2916.48 | Y21: 335.52 | Z21: 98.54 | AA21: 0 | AB21: 0 | AC21: 0 | AD21: 0 | AE21: 0 | AF21: 0 | AG21: =(T21-U21-V21-W21)*R21-X21+Y21-Z21-AA21-AB21-AC21-AD21-AE21-AF21 -> -156.152 | AH21: =IF(ISNUMBER(MATCH(A21,'畅想出运数据（核算明细导出）'!$C$2:$C$484,0)),"有","无") -> 有
A22: HSB25M024-8 | B22: 46047 | C22: 英国2962 | D22: 渠道商 | E22: 昊特赛二公司 | F22: 办公室 | H22: 市场七二司 | I22: 业务办公室 | J22: 运动休闲包 | K22: 沙滩包 | L22: 常规沙滩包 | M22: BB001 | N22: BB001-STB-1 | O22: 原柯冬浩 | P22: 外部引进 | Q22: USD | R22: 6.95 | S22: 4719.6 | T22: 4719.6 | U22: 33.04 | V22: 46.31 | W22: 141.59 | X22: 31050 | Y22: 3572.12 | Z22: 0 | AA22: 0 | AB22: 0 | AC22: 0 | AD22: 0 | AE22: 0 | AF22: 0 | AG22: =(T22-U22-V22-W22)*R22-X22+Y22-Z22-AA22-AB22-AC22-AD22-AE22-AF22 -> 3787.807 | AH22: =IF(ISNUMBER(MATCH(A22,'畅想出运数据（核算明细导出）'!$C$2:$C$484,0)),"有","无") -> 有
A23: HSB25M024-11 | B23: 46047 | C23: 英国2962 | D23: 渠道商 | E23: 昊特赛二公司 | F23: 办公室 | H23: 市场七二司 | I23: 业务办公室 | J23: 运动休闲包 | K23: 沙滩包 | L23: 常规沙滩包 | M23: BB001 | N23: BB001-STB-1 | O23: 原柯冬浩 | P23: 外部引进 | Q23: USD | R23: 6.96 | S23: 4681.6 | T23: 4681.6 | U23: 32.77 | V23: 46.21 | W23: 140.45 | X23: 30800 | Y23: 3543.36 | Z23: 2880.52 | AA23: 0 | AB23: 0 | AC23: 0 | AD23: 0 | AE23: 0 | AF23: 0 | AG23: =(T23-U23-V23-W23)*R23-X23+Y23-Z23-AA23-AB23-AC23-AD23-AE23-AF23 -> 919.5432 | AH23: =IF(ISNUMBER(MATCH(A23,'畅想出运数据（核算明细导出）'!$C$2:$C$484,0)),"有","无") -> 有
A24: HSB25M024-10 | B24: 46047 | C24: 英国2962 | D24: 渠道商 | E24: 昊特赛二公司 | F24: 办公室 | H24: 市场七二司 | I24: 业务办公室 | J24: 运动休闲包 | K24: 沙滩包 | L24: 常规沙滩包 | M24: BB001 | N24: BB001-STB-1 | O24: 原柯冬浩 | P24: 外部引进 | Q24: USD | R24: 6.96 | S24: 4833.6 | T24: 4833.6 | U24: 33.84 | V24: 46.39 | W24: 96.67 | X24: 31800 | Y24: 3658.41 | Z24: 2501.46 | AA24: 0 | AB24: 0 | AC24: 0 | AD24: 0 | AE24: 0 | AF24: 0 | AG24: =(T24-U24-V24-W24)*R24-X24+Y24-Z24-AA24-AB24-AC24-AD24-AE24-AF24 -> 1767.582 | AH24: =IF(ISNUMBER(MATCH(A24,'畅想出运数据（核算明细导出）'!$C$2:$C$484,0)),"有","无") -> 有
A25: HSB25M024-7 | B25: 46047 | C25: 英国2962 | D25: 渠道商 | E25: 昊特赛二公司 | F25: 办公室 | H25: 市场七二司 | I25: 业务办公室 | J25: 装扮玩具 | K25: 工具玩具 | L25: 常规工具玩具 | M25: TT003 | N25: TT003-FJWJ001 | O25: 丁迎全 | P25: 外部引进 | Q25: USD | R25: 6.94 | S25: 1725.89 | T25: 1725.89 | U25: 12.08 | V25: 10.02 | W25: 51.78 | X25: 10564.4 | Y25: 1215.37 | Z25: 1235.92 | AA25: 0 | AB25: 0 | AC25: 0 | AD25: 0 | AE25: 0 | AF25: 0 | AG25: =(T25-U25-V25-W25)*R25-X25+Y25-Z25-AA25-AB25-AC25-AD25-AE25-AF25 -> 879.9994 | AH25: =IF(ISNUMBER(MATCH(A25,'畅想出运数据（核算明细导出）'!$C$2:$C$484,0)),"有","无") -> 有
A26: HSB25M024-5 | B26: 46047 | C26: 英国2962 | D26: 渠道商 | E26: 昊特赛二公司 | F26: 办公室 | H26: 市场七二司 | I26: 业务办公室 | J26: 装扮玩具 | K26: 工具玩具 | L26: 常规工具玩具 | M26: TT003 | N26: TT003-FJWJ001 | O26: 丁迎全 | P26: 外部引进 | Q26: USD | R26: 6.96 | S26: 1689.6 | T26: 1689.6 | U26: 11.83 | V26: 12.38 | W26: 50.69 | X26: 10348.8 | Y26: 1190.57 | Z26: 1302.29 | AA26: 0 | AB26: 0 | AC26: 0 | AD26: 0 | AE26: 0 | AF26: 0 | AG26: =(T26-U26-V26-W26)*R26-X26+Y26-Z26-AA26-AB26-AC26-AD26-AE26-AF26 -> 777.792 | AH26: =IF(ISNUMBER(MATCH(A26,'畅想出运数据（核算明细导出）'!$C$2:$C$484,0)),"有","无") -> 有
A27: HSB25M024-2 | B27: 46047 | C27: 英国2962 | D27: 渠道商 | E27: 昊特赛二公司 | F27: 办公室 | H27: 市场七二司 | I27: 业务办公室 | J27: 装扮玩具 | K27: 工具玩具 | L27: 常规工具玩具 | M27: TT003 | N27: TT003-FJWJ001 | O27: 丁迎全 | P27: 外部引进 | Q27: USD | R27: 6.97 | S27: 1616 | T27: 1616 | U27: 11.31 | V27: 9.42 | W27: 0 | X27: 9898 | Y27: 1138.71 | Z27: 1090.17 | AA27: 0 | AB27: 0 | AC27: 0 | AD27: 0 | AE27: 0 | AF27: 0 | AG27: =(T27-U27-V27-W27)*R27-X27+Y27-Z27-AA27-AB27-AC27-AD27-AE27-AF27 -> 1269.5719 | AH27: =IF(ISNUMBER(MATCH(A27,'畅想出运数据（核算明细导出）'!$C$2:$C$484,0)),"有","无") -> 有
A28: HSB25M024-7 | B28: 46047 | C28: 英国2962 | D28: 渠道商 | E28: 昊特赛二公司 | F28: 办公室 | H28: 市场七二司 | I28: 业务办公室 | J28: 游泳装备 | K28: 游泳训练器材 | L28: 游泳圈 | M28: ST047 | N28: ST047-YQ-1 | O28: 丁迎全 | P28: 外部引进 | Q28: USD | R28: 6.94 | S28: 1664.26 | T28: 1664.26 | U28: 11.65 | V28: 9.67 | W28: 49.93 | X28: 9504 | Y28: 1093.38 | Z28: 266.02 | AA28: 0 | AB28: 0 | AC28: 0 | AD28: 0 | AE28: 0 | AF28: 0 | AG28: =(T28-U28-V28-W28)*R28-X28+Y28-Z28-AA28-AB28-AC28-AD28-AE28-AF28 -> 2378.8494 | AH28: =IF(ISNUMBER(MATCH(A28,'畅想出运数据（核算明细导出）'!$C$2:$C$484,0)),"有","无") -> 有
A29: HSB25M024-7 | B29: 46047 | C29: 英国2962 | D29: 渠道商 | E29: 昊特赛二公司 | F29: 办公室 | H29: 市场七二司 | I29: 业务办公室 | J29: 游泳装备 | K29: 游泳训练器材 | L29: 游泳圈 | M29: ST047 | N29: ST047-YQ-1 | O29: 丁迎全 | P29: 外部引进 | Q29: USD | R29: 6.94 | S29: 33.62 | T29: 33.62 | U29: 0.24 | V29: 0.2 | W29: 1.01 | X29: 192 | Y29: 22.09 | Z29: 5.37 | AA29: 0 | AB29: 0 | AC29: 0 | AD29: 0 | AE29: 0 | AF29: 0 | AG29: =(T29-U29-V29-W29)*R29-X29+Y29-Z29-AA29-AB29-AC29-AD29-AE29-AF29 -> 47.9798 | AH29: =IF(ISNUMBER(MATCH(A29,'畅想出运数据（核算明细导出）'!$C$2:$C$484,0)),"有","无") -> 有
A30: HSB25M024-4 | B30: 46047 | C30: 英国2962 | D30: 渠道商 | E30: 昊特赛二公司 | F30: 办公室 | H30: 市场七二司 | I30: 业务办公室 | J30: 游泳装备 | K30: 游泳训练器材 | L30: 游泳圈 | M30: ST047 | N30: ST047-YQ-1 | O30: 丁迎全 | P30: 外部引进 | Q30: USD | R30: 6.95 | S30: 1680 | T30: 1680 | U30: 11.76 | V30: 50 | W30: 0 | X30: 9600 | Y30: 1104.42 | Z30: 1035.34 | AA30: 0 | AB30: 0 | AC30: 0 | AD30: 0 | AE30: 0 | AF30: 0 | AG30: =(T30-U30-V30-W30)*R30-X30+Y30-Z30-AA30-AB30-AC30-AD30-AE30-AF30 -> 1715.848 | AH30: =IF(ISNUMBER(MATCH(A30,'畅想出运数据（核算明细导出）'!$C$2:$C$484,0)),"有","无") -> 有
... A49: HSB25E023-6 | B49: 46047 | C49: 英国2962 | D49: 渠道商 | E49: 昊特赛二公司 | F49: 客户第一组 | H49: 市场七二司 | I49: 客户第一组 | J49: 手工艺品及DIY玩具 | K49: 创意类及材料包 | L49: 其他常规DIY玩具 | M49: OD273 | N49: OD273-CN001 | O49: 丁迎全 | P49: 外部引进 | Q49: USD | R49: 6.96 | S49: 4180.8 | T49: 4180.8 | U49: 29.27 | V49: 50 | W49: 0 | X49: 26757.12 | Y49: 3078.25 | Z49: 0 | AA49: 0 | AB49: 0 | AC49: 0 | AD49: 0 | AE49: 0 | AF49: 0 | AG49: =(T49-U49-V49-W49)*R49-X49+Y49-Z49-AA49-AB49-AC49-AD49-AE49-AF49 -> 4867.7788 | AH49: =IF(ISNUMBER(MATCH(A49,'畅想出运数据（核算明细导出）'!$C$2:$C$484,0)),"有","无") -> 有
A50: Y25D0904-1 | B50: 46047 | C50: 美国0830 | D50: 品牌商 | E50: 昊特赛十公司 | F50: 办公室 | H50: 市场八十司 | I50: 业务办公室 | J50: 露营和远足 | K50: 户外家具 | L50: 户外折叠椅 | N50: HTS-W-8001 | O50: 王 进 | P50: 外部引进 | Q50: USD | R50: 6.97 | S50: 22368 | T50: 22368 | U50: 156.58 | V50: 50 | W50: 0 | X50: 97680 | Y50: 11237.52 | Z50: 49724.8 | AA50: 0 | AB50: 0 | AC50: 0 | AD50: 0 | AE50: 0 | AF50: 0 | AG50: =(T50-U50-V50-W50)*R50-X50+Y50-Z50-AA50-AB50-AC50-AD50-AE50-AF50 -> 18297.817 | AH50: =IF(ISNUMBER(MATCH(A50,'畅想出运数据（核算明细导出）'!$C$2:$C$484,0)),"有","无") -> 有
A51: HSJ25R005-2 | B51: 46047 | C51: 美国0830 | D51: 品牌商 | E51: 昊特赛十公司 | F51: 办公室 | H51: 市场八十司 | I51: 业务办公室 | J51: 露营和远足 | K51: 户外家具 | L51: 户外折叠椅 | N51: HTS-W-8001 | O51: 王 进 | P51: 外部引进 | Q51: USD | R51: 6.95 | S51: 3197.7 | T51: 3197.7 | U51: 22.38 | V51: 50 | W51: 0 | X51: 21374.1 | Y51: 2458.97 | Z51: 0 | AA51: 0 | AB51: 0 | AC51: 0 | AD51: 0 | AE51: 0 | AF51: 0 | AG51: =(T51-U51-V51-W51)*R51-X51+Y51-Z51-AA51-AB51-AC51-AD51-AE51-AF51 -> 2805.844 | AH51: =IF(ISNUMBER(MATCH(A51,'畅想出运数据（核算明细导出）'!$C$2:$C$484,0)),"有","无") -> 有
A52: Y25D0903 | B52: 46047 | C52: 美国0830 | D52: 品牌商 | E52: 昊特赛十公司 | F52: 办公室 | H52: 市场八十司 | I52: 业务办公室 | J52: 功能照明 | K52: 头灯及野营灯 | L52: 头灯 | N52: F-YNT-头灯 | O52: 郭红勇 | P52: 外部引进 | Q52: USD | R52: 6.95 | S52: 8709.12 | T52: 8709.12 | U52: 60.96 | V52: 50 | W52: 0 | X52: 63110.88 | Y52: 7260.54 | Z52: 2607 | AA52: 0 | AB52: 0 | AC52: 0 | AD52: 0 | AE52: 0 | AF52: 0 | AG52: =(T52-U52-V52-W52)*R52-X52+Y52-Z52-AA52-AB52-AC52-AD52-AE52-AF52 -> 1299.872 | AH52: =IF(ISNUMBER(MATCH(A52,'畅想出运数据（核算明细导出）'!$C$2:$C$484,0)),"有","无") -> 有
A53: HSA25D010-2 | B53: 46078 | C53: 波兰749 | D53: 渠道商 | E53: 昊特赛一公司 | F53: 客户第一组 | H53: 市场七一司 | I53: 客户第二组 | J53: 工艺陶瓷 | K53: 陶瓷工艺品 | L53: 常规陶瓷工艺品 | N53: GD-PC200-1024 | O53: 钟 琪 | P53: 外部引进 | Q53: USD | R53: 6.9 | S53: 957.6 | T53: 957.6 | U53: 6.7 | V53: 50 | W53: 0 | X53: 4636.8 | Y53: 369.3 | Z53: 1400.34 | AA53: 0 | AB53: 0 | AC53: 0 | AD53: 0 | AE53: 0 | AF53: 0 | AG53: =(T53-U53-V53-W53)*R53-X53+Y53-Z53-AA53-AB53-AC53-AD53-AE53-AF53 -> 548.37 | AH53: =IF(ISNUMBER(MATCH(A53,'畅想出运数据（核算明细导出）'!$C$2:$C$484,0)),"有","无") -> 有
A54: HSA25D005-1 | B54: 46078 | C54: 波兰749 | D54: 渠道商 | E54: 昊特赛一公司 | F54: 客户第一组 | H54: 市场七一司 | I54: 客户第二组 | J54: 家居装饰品 | K54: 人造绿植 | L54: 常规人造绿植 | N54: GD-HD200-1006 | O54: 钟 琪 | P54: 外部引进 | Q54: USD | R54: 6.92 | S54: 1689.6 | T54: 1689.6 | U54: 11.83 | V54: 50 | W54: 0 | X54: 10936.32 | Y54: 1258.16 | Z54: 281.77 | AA54: 0 | AB54: 0 | AC54: 0 | AD54: 0 | AE54: 0 | AF54: 0 | AG54: =(T54-U54-V54-W54)*R54-X54+Y54-Z54-AA54-AB54-AC54-AD54-AE54-AF54 -> 1304.2384 | AH54: =IF(ISNUMBER(MATCH(A54,'畅想出运数据（核算明细导出）'!$C$2:$C$484,0)),"有","无") -> 有
A55: HSA25J009-1 | B55: 46078 | C55: 波兰749 | D55: 渠道商 | E55: 昊特赛一公司 | F55: 客户第一组 | H55: 市场七一司 | I55: 客户第二组 | J55: 工艺陶瓷 | K55: 陶瓷工艺品 | L55: 常规陶瓷工艺品 | N55: GD-PC200-1026 | O55: 钟 琪 | P55: 外部引进 | Q55: USD | R55: 6.92 | S55: 1229.76 | T55: 1229.76 | U55: 8.61 | V55: 50 | W55: 0 | X55: 8064 | Y55: 642.27 | Z55: 1587.22 | AA55: 0 | AB55: 0 | AC55: 0 | AD55: 0 | AE55: 0 | AF55: 0 | AG55: =(T55-U55-V55-W55)*R55-X55+Y55-Z55-AA55-AB55-AC55-AD55-AE55-AF55 -> -904.592 | AH55: =IF(ISNUMBER(MATCH(A55,'畅想出运数据（核算明细导出）'!$C$2:$C$484,0)),"有","无") -> 有
A56: HSA25D003-11 | B56: 46078 | C56: 波兰749 | D56: 渠道商 | E56: 昊特赛一公司 | F56: 客户第一组 | H56: 市场七一司 | I56: 客户第二组 | J56: 家居装饰品 | K56: 人造绿植 | L56: 常规人造绿植 | N56: GD-HD200-1005 | O56: 钟 琪 | P56: 外部引进 | Q56: USD | R56: 6.9 | S56: 726 | T56: 726 | U56: 5.09 | V56: 42.31 | W56: 0 | X56: 4443.12 | Y56: 511.16 | Z56: 0 | AA56: 0 | AB56: 0 | AC56: 0 | AD56: 0 | AE56: 0 | AF56: 0 | AG56: =(T56-U56-V56-W56)*R56-X56+Y56-Z56-AA56-AB56-AC56-AD56-AE56-AF56 -> 750.38 | AH56: =IF(ISNUMBER(MATCH(A56,'畅想出运数据（核算明细导出）'!$C$2:$C$484,0)),"有","无") -> 有
A57: HSA25D003-11 | B57: 46078 | C57: 波兰749 | D57: 渠道商 | E57: 昊特赛一公司 | F57: 客户第一组 | H57: 市场七一司 | I57: 客户第二组 | J57: 家居装饰品 | K57: 人造绿植 | L57: 常规人造绿植 | N57: GD-HD200-1005 | O57: 钟 琪 | P57: 外部引进 | Q57: USD | R57: 6.9 | S57: 132 | T57: 132 | U57: 0.92 | V57: 7.69 | W57: 0 | X57: 807.84 | Y57: 92.94 | Z57: 0 | AA57: 0 | AB57: 0 | AC57: 0 | AD57: 0 | AE57: 0 | AF57: 0 | AG57: =(T57-U57-V57-W57)*R57-X57+Y57-Z57-AA57-AB57-AC57-AD57-AE57-AF57 -> 136.491 | AH57: =IF(ISNUMBER(MATCH(A57,'畅想出运数据（核算明细导出）'!$C$2:$C$484,0)),"有","无") -> 有
A58: HSA25D003-4 | B58: 46078 | C58: 波兰749 | D58: 渠道商 | E58: 昊特赛一公司 | F58: 客户第一组 | H58: 市场七一司 | I58: 客户第二组 | J58: 厨房收纳 | K58: 厨房置物架 | L58: 纸巾架 | N58: KW-KS600-1001 | O58: 钟 琪 | P58: 外部引进 | Q58: USD | R58: 6.92 | S58: 628.32 | T58: 628.32 | U58: 4.4 | V58: 17.83 | W58: 0 | X58: 4161.6 | Y58: 478.77 | Z58: 0 | AA58: 0 | AB58: 0 | AC58: 0 | AD58: 0 | AE58: 0 | AF58: 0 | AG58: =(T58-U58-V58-W58)*R58-X58+Y58-Z58-AA58-AB58-AC58-AD58-AE58-AF58 -> 511.3128 | AH58: =IF(ISNUMBER(MATCH(A58,'畅想出运数据（核算明细导出）'!$C$2:$C$484,0)),"有","无") -> 有
A59: HSA25D004-3 | B59: 46078 | C59: 波兰749 | D59: 渠道商 | E59: 昊特赛一公司 | F59: 客户第一组 | H59: 市场七一司 | I59: 客户第二组 | J59: 工艺陶瓷 | K59: 陶瓷工艺品 | L59: 常规陶瓷工艺品 | N59: GD-PC200-1021 | O59: 钟 琪 | P59: 外部引进 | Q59: USD | R59: 6.89 | S59: 835.2 | T59: 835.2 | U59: 5.85 | V59: 23.02 | W59: 0 | X59: 4872 | Y59: 388.04 | Z59: 795.03 | AA59: 0 | AB59: 0 | AC59: 0 | AD59: 0 | AE59: 0 | AF59: 0 | AG59: =(T59-U59-V59-W59)*R59-X59+Y59-Z59-AA59-AB59-AC59-AD59-AE59-AF59 -> 276.6237 | AH59: =IF(ISNUMBER(MATCH(A59,'畅想出运数据（核算明细导出）'!$C$2:$C$484,0)),"有","无") -> 有
A60: HSA25D004-3 | B60: 46078 | C60: 波兰749 | D60: 渠道商 | E60: 昊特赛一公司 | F60: 客户第一组 | H60: 市场七一司 | I60: 客户第二组 | J60: 工艺陶瓷 | K60: 陶瓷工艺品 | L60: 常规陶瓷工艺品 | N60: GD-PC200-1021 | O60: 钟 琪 | P60: 外部引进 | Q60: USD | R60: 6.89 | S60: 201.6 | T60: 201.6 | U60: 1.41 | V60: 5.56 | W60: 0 | X60: 1176 | Y60: 93.66 | Z60: 191.9 | AA60: 0 | AB60: 0 | AC60: 0 | AD60: 0 | AE60: 0 | AF60: 0 | AG60: =(T60-U60-V60-W60)*R60-X60+Y60-Z60-AA60-AB60-AC60-AD60-AE60-AF60 -> 66.7607 | AH60: =IF(ISNUMBER(MATCH(A60,'畅想出运数据（核算明细导出）'!$C$2:$C$484,0)),"有","无") -> 有
A61: HSA25D003-4 | B61: 46078 | C61: 波兰749 | D61: 渠道商 | E61: 昊特赛一公司 | F61: 客户第一组 | H61: 市场七一司 | I61: 客户第二组 | J61: 家居装饰品 | K61: 人造绿植 | L61: 常规人造绿植 | N61: GD-HD200-1007 | O61: 钟 琪 | P61: 外部引进 | Q61: USD | R61: 6.92 | S61: 1134 | T61: 1134 | U61: 7.94 | V61: 32.17 | W61: 0 | X61: 7741.44 | Y61: 890.61 | Z61: 0 | AA61: 0 | AB61: 0 | AC61: 0 | AD61: 0 | AE61: 0 | AF61: 0 | AG61: =(T61-U61-V61-W61)*R61-X61+Y61-Z61-AA61-AB61-AC61-AD61-AE61-AF61 -> 718.8888 | AH61: =IF(ISNUMBER(MATCH(A61,'畅想出运数据（核算明细导出）'!$C$2:$C$484,0)),"有","无") -> 有
... A76: HSC25X012-1 | B76: 46078 | C76: 加拿大925 | D76: 渠道商 | E76: 昊特赛三公司 | F76: 客户第一组 | H76: 市场七三司 | I76: 客户第一组 | J76: 餐具及摆盘 | K76: 刀叉勺 | L76: 勺子 | N76: 03-0301953 | O76: 黄家辉 | P76: 外部引进 | Q76: USD | R76: 6.94 | S76: 8640 | T76: 8640 | U76: 60.48 | V76: 50 | W76: 0 | X76: 64800 | Y76: 7454.87 | Z76: 0 | AA76: 0 | AB76: 0 | AC76: 0 | AD76: 0 | AE76: 0 | AF76: 0 | AG76: =(T76-U76-V76-W76)*R76-X76+Y76-Z76-AA76-AB76-AC76-AD76-AE76-AF76 -> 1849.7388 | AH76: =IF(ISNUMBER(MATCH(A76,'畅想出运数据（核算明细导出）'!$C$2:$C$484,0)),"有","无") -> 有
A77: HSA25J011 | B77: 46078 | C77: 波兰749 | D77: 渠道商 | E77: 昊特赛八公司 | F77: 办公室 | H77: 市场七九司 | J77: 经典玩具 | K77: 其他经典玩具 | L77: 其他常规经典玩具 | N77: KB-CT600-1011 | O77: 钟 琪 | P77: 外部引进 | Q77: USD | R77: 6.87 | S77: 846 | T77: 846 | U77: 5.92 | V77: 12.26 | W77: 0 | X77: 5085 | Y77: 585 | Z77: 955.61 | AA77: 0 | AB77: 0 | AC77: 0 | AD77: 0 | AE77: 0 | AF77: 0 | AG77: =(T77-U77-V77-W77)*R77-X77+Y77-Z77-AA77-AB77-AC77-AD77-AE77-AF77 -> 231.5134 | AH77: =IF(ISNUMBER(MATCH(A77,'畅想出运数据（核算明细导出）'!$C$2:$C$484,0)),"有","无") -> 有
A78: HSA25J011 | B78: 46078 | C78: 波兰749 | D78: 渠道商 | E78: 昊特赛八公司 | F78: 办公室 | H78: 市场七九司 | J78: 经典玩具 | K78: 其他经典玩具 | L78: 其他常规经典玩具 | N78: KB-CT600-1017 | O78: 钟 琪 | P78: 外部引进 | Q78: USD | R78: 6.87 | S78: 1800 | T78: 1800 | U78: 12.6 | V78: 26.08 | W78: 0 | X78: 8100 | Y78: 931.86 | Z78: 732.25 | AA78: 0 | AB78: 0 | AC78: 0 | AD78: 0 | AE78: 0 | AF78: 0 | AG78: =(T78-U78-V78-W78)*R78-X78+Y78-Z78-AA78-AB78-AC78-AD78-AE78-AF78 -> 4199.8784 | AH78: =IF(ISNUMBER(MATCH(A78,'畅想出运数据（核算明细导出）'!$C$2:$C$484,0)),"有","无") -> 有
A79: HSA25J011-1 | B79: 46078 | C79: 波兰749 | D79: 渠道商 | E79: 昊特赛八公司 | F79: 办公室 | H79: 市场七九司 | J79: 经典玩具 | K79: 其他经典玩具 | L79: 其他常规经典玩具 | N79: KB-CT600-1018 | O79: 钟 琪 | P79: 外部引进 | Q79: USD | R79: 6.9 | S79: 927 | T79: 927 | U79: 6.49 | V79: 50 | W79: 0 | X79: 7650 | Y79: 880.09 | Z79: 1719.18 | AA79: 0 | AB79: 0 | AC79: 0 | AD79: 0 | AE79: 0 | AF79: 0 | AG79: =(T79-U79-V79-W79)*R79-X79+Y79-Z79-AA79-AB79-AC79-AD79-AE79-AF79 -> -2482.571 | AH79: =IF(ISNUMBER(MATCH(A79,'畅想出运数据（核算明细导出）'!$C$2:$C$484,0)),"有","无") -> 有
A80: HSA25J011 | B80: 46078 | C80: 波兰749 | D80: 渠道商 | E80: 昊特赛八公司 | F80: 办公室 | H80: 市场七九司 | J80: 经典玩具 | K80: 其他经典玩具 | L80: 其他常规经典玩具 | N80: KB-CT600-1013 | O80: 钟 琪 | P80: 外部引进 | Q80: USD | R80: 6.87 | S80: 804.96 | T80: 804.96 | U80: 5.64 | V80: 11.66 | W80: 0 | X80: 3837.6 | Y80: 441.49 | Z80: 395.14 | AA80: 0 | AB80: 0 | AC80: 0 | AD80: 0 | AE80: 0 | AF80: 0 | AG80: =(T80-U80-V80-W80)*R80-X80+Y80-Z80-AA80-AB80-AC80-AD80-AE80-AF80 -> 1619.9742 | AH80: =IF(ISNUMBER(MATCH(A80,'畅想出运数据（核算明细导出）'!$C$2:$C$484,0)),"有","无") -> 有
A81: HSA25Y013-1 | B81: 46078 | C81: 波兰749 | D81: 渠道商 | E81: 昊特赛一公司 | F81: 客户第一组 | H81: 市场七九司 | I81: 客户第一组 | J81: 经典玩具 | K81: 其他经典玩具 | L81: 其他常规经典玩具 | N81: KB-CT600-1008 | O81: 钟 琪 | P81: 外部引进 | Q81: USD | R81: 6.92 | S81: 4452.8 | T81: 4452.8 | U81: 31.17 | V81: 40.64 | W81: 0 | X81: 23377.2 | Y81: 2689.41 | Z81: 932.65 | AA81: 0 | AB81: 0 | AC81: 0 | AD81: 0 | AE81: 0 | AF81: 0 | AG81: =(T81-U81-V81-W81)*R81-X81+Y81-Z81-AA81-AB81-AC81-AD81-AE81-AF81 -> 8696.0108 | AH81: =IF(ISNUMBER(MATCH(A81,'畅想出运数据（核算明细导出）'!$C$2:$C$484,0)),"有","无") -> 有
A82: HSA25Y013-1 | B82: 46078 | C82: 波兰749 | D82: 渠道商 | E82: 昊特赛一公司 | F82: 客户第一组 | H82: 市场七九司 | I82: 客户第一组 | J82: 经典玩具 | K82: 其他经典玩具 | L82: 其他常规经典玩具 | N82: KB-CT600-104 | O82: 钟 琪 | P82: 外部引进 | Q82: USD | R82: 6.92 | S82: 1026 | T82: 1026 | U82: 7.18 | V82: 9.36 | W82: 0 | X82: 7387.2 | Y82: 849.85 | Z82: 295.76 | AA82: 0 | AB82: 0 | AC82: 0 | AD82: 0 | AE82: 0 | AF82: 0 | AG82: =(T82-U82-V82-W82)*R82-X82+Y82-Z82-AA82-AB82-AC82-AD82-AE82-AF82 -> 152.3532 | AH82: =IF(ISNUMBER(MATCH(A82,'畅想出运数据（核算明细导出）'!$C$2:$C$484,0)),"有","无") -> 有
A83: HSI25L003-1 | B83: 46078 | C83: 波兰749 | D83: 渠道商 | E83: 昊特赛一公司 | F83: 客户第一组 | H83: 市场七九司 | I83: 客户第一组 | J83: 感官玩具及游戏 | K83: 运动游戏 | L83: 运动玩具 | N83: 062KR | O83: 李雅婷 | P83: 外部引进 | Q83: USD | R83: 6.89 | S83: 4000 | T83: 4000 | U83: 28 | V83: 50 | W83: 0 | X83: 26200 | Y83: 3014.16 | Z83: 0 | AA83: 0 | AB83: 0 | AC83: 0 | AD83: 0 | AE83: 0 | AF83: 0 | AG83: =(T83-U83-V83-W83)*R83-X83+Y83-Z83-AA83-AB83-AC83-AD83-AE83-AF83 -> 3836.74 | AH83: =IF(ISNUMBER(MATCH(A83,'畅想出运数据（核算明细导出）'!$C$2:$C$484,0)),"有","无") -> 有
A84: HSA25Y002-4 | B84: 46078 | C84: 波兰749 | D84: 渠道商 | E84: 昊特赛一公司 | F84: 客户第一组 | H84: 市场七九司 | I84: 客户第一组 | J84: 玩偶玩具 | K84: 布艺玩偶 | L84: 常规布艺玩偶 | N84: KB-DL200-122 | O84: 钟 琪 | P84: 外部引进 | Q84: USD | R84: 6.92 | S84: 1814.4 | T84: 1814.4 | U84: 12.7 | V84: 50 | W84: 0 | X84: 12821.76 | Y84: 1475.07 | Z84: 1836.76 | AA84: 0 | AB84: 0 | AC84: 0 | AD84: 0 | AE84: 0 | AF84: 0 | AG84: =(T84-U84-V84-W84)*R84-X84+Y84-Z84-AA84-AB84-AC84-AD84-AE84-AF84 -> -1061.686 | AH84: =IF(ISNUMBER(MATCH(A84,'畅想出运数据（核算明细导出）'!$C$2:$C$484,0)),"有","无") -> 有
A85: HSA25J004-2 | B85: 46078 | C85: 波兰749 | D85: 渠道商 | E85: 昊特赛八公司 | F85: 办公室 | H85: 市场七八司 | I85: 业务办公室 | J85: 商务礼品 | K85: 工艺品 | L85: 水晶工艺品 | N85: CR037 | O85: 蔡载君 | P85: 外部引进 | Q85: USD | R85: 6.85 | S85: 860 | T85: 860 | U85: 6.02 | V85: 11.07 | W85: 0 | X85: 6103 | Y85: 486.08 | Z85: 8.21 | AA85: 0 | AB85: 0 | AC85: 0 | AD85: 0 | AE85: 0 | AF85: 0 | AG85: =(T85-U85-V85-W85)*R85-X85+Y85-Z85-AA85-AB85-AC85-AD85-AE85-AF85 -> 148.8035 | AH85: =IF(ISNUMBER(MATCH(A85,'畅想出运数据（核算明细导出）'!$C$2:$C$484,0)),"有","无") -> 有
A86: HSA25J004-2 | B86: 46078 | C86: 波兰749 | D86: 渠道商 | E86: 昊特赛八公司 | F86: 办公室 | H86: 市场七八司 | I86: 业务办公室 | J86: 露营和远足 | K86: 户外家具 | L86: 庭院吊篮 | N86: PO-OF5001-001 | O86: 王柯飞 | P86: 外部引进 | Q86: USD | R86: 6.85 | S86: 3024 | T86: 3024 | U86: 21.17 | V86: 38.93 | W86: 0 | X86: 18144 | Y86: 2087.36 | Z86: 757.83 | AA86: 0 | AB86: 0 | AC86: 0 | AD86: 0 | AE86: 0 | AF86: 0 | AG86: =(T86-U86-V86-W86)*R86-X86+Y86-Z86-AA86-AB86-AC86-AD86-AE86-AF86 -> 3488.245 | AH86: =IF(ISNUMBER(MATCH(A86,'畅想出运数据（核算明细导出）'!$C$2:$C$484,0)),"有","无") -> 有
A87: HSA25J012-1 | B87: 46078 | C87: 波兰749 | D87: 渠道商 | E87: 昊特赛八公司 | F87: 办公室 | H87: 市场七八司 | I87: 业务办公室 | J87: 露营和远足 | K87: 户外家具 | L87: 户外折叠椅 | N87: PO-CH100-1001 | O87: 钟 琪 | P87: 外部引进 | Q87: USD | R87: 6.92 | S87: 1764 | T87: 1764 | U87: 12.35 | V87: 6.4 | W87: 0 | X87: 13980 | Y87: 1608.32 | Z87: 198.14 | AA87: 0 | AB87: 0 | AC87: 0 | AD87: 0 | AE87: 0 | AF87: 0 | AG87: =(T87-U87-V87-W87)*R87-X87+Y87-Z87-AA87-AB87-AC87-AD87-AE87-AF87 -> -492.69 | AH87: =IF(ISNUMBER(MATCH(A87,'畅想出运数据（核算明细导出）'!$C$2:$C$484,0)),"有","无") -> 有
A88: HSA25J012-2 | B88: 46078 | C88: 波兰749 | D88: 渠道商 | E88: 昊特赛八公司 | F88: 办公室 | H88: 市场七八司 | I88: 业务办公室 | J88: 露营和远足 | K88: 户外家具 | L88: 户外折叠椅 | N88: PO-CH100-1001 | O88: 钟 琪 | P88: 外部引进 | Q88: USD | R88: 6.9 | S88: 1159.59 | T88: 1159.59 | U88: 8.12 | V88: 4.75 | W88: 0 | X88: 9436.5 | Y88: 1085.62 | Z88: 0 | AA88: 0 | AB88: 0 | AC88: 0 | AD88: 0 | AE88: 0 | AF88: 0 | AG88: =(T88-U88-V88-W88)*R88-X88+Y88-Z88-AA88-AB88-AC88-AD88-AE88-AF88 -> -438.512 | AH88: =IF(ISNUMBER(MATCH(A88,'畅想出运数据（核算明细导出）'!$C$2:$C$484,0)),"有","无") -> 有
A89: HSA25J001-3 | B89: 46078 | C89: 波兰749 | D89: 渠道商 | E89: 昊特赛八公司 | F89: 办公室 | H89: 市场七八司 | I89: 业务办公室 | J89: 瑜伽和普拉提 | K89: 瑜伽垫 | L89: 常规瑜伽垫 | N89: PO-YP1001-002 | O89: 李 宁2 | P89: 外部引进 | Q89: USD | R89: 6.89 | S89: 716.8 | T89: 716.8 | U89: 5.02 | V89: 4.25 | W89: 0 | X89: 4710.4 | Y89: 541.9 | Z89: 0 | AA89: 0 | AB89: 0 | AC89: 0 | AD89: 0 | AE89: 0 | AF89: 0 | AG89: =(T89-U89-V89-W89)*R89-X89+Y89-Z89-AA89-AB89-AC89-AD89-AE89-AF89 -> 706.3817 | AH89: =IF(ISNUMBER(MATCH(A89,'畅想出运数据（核算明细导出）'!$C$2:$C$484,0)),"有","无") -> 有
A90: HSA25J001-1 | B90: 46078 | C90: 波兰749 | D90: 渠道商 | E90: 昊特赛八公司 | F90: 办公室 | H90: 市场七八司 | I90: 业务办公室 | J90: 其他运动用品 | K90: 伸展训练 | L90: 弹力带 | N90: PO-OSP2001-001 | O90: 李 宁2 | P90: 外部引进 | Q90: USD | R90: 6.89 | S90: 594.72 | T90: 594.72 | U90: 4.16 | V90: 50 | W90: 0 | X90: 3729.6 | Y90: 429.07 | Z90: 0 | AA90: 0 | AB90: 0 | AC90: 0 | AD90: 0 | AE90: 0 | AF90: 0 | AG90: =(T90-U90-V90-W90)*R90-X90+Y90-Z90-AA90-AB90-AC90-AD90-AE90-AF90 -> 423.9284 | AH90: =IF(ISNUMBER(MATCH(A90,'畅想出运数据（核算明细导出）'!$C$2:$C$484,0)),"有","无") -> 有
A91: HSA25J012-2 | B91: 46078 | C91: 波兰749 | D91: 渠道商 | E91: 昊特赛八公司 | F91: 办公室 | H91: 市场七八司 | I91: 业务办公室 | J91: 露营和远足 | K91: 户外家具 | L91: 户外折叠椅 | N91: PO-CH100-1002 | O91: 钟 琪 | P91: 外部引进 | Q91: USD | R91: 6.9 | S91: 429.48 | T91: 429.48 | U91: 3.01 | V91: 1.76 | W91: 0 | X91: 3495 | Y91: 402.08 | Z91: 0 | AA91: 0 | AB91: 0 | AC91: 0 | AD91: 0 | AE91: 0 | AF91: 0 | AG91: =(T91-U91-V91-W91)*R91-X91+Y91-Z91-AA91-AB91-AC91-AD91-AE91-AF91 -> -162.421 | AH91: =IF(ISNUMBER(MATCH(A91,'畅想出运数据（核算明细导出）'!$C$2:$C$484,0)),"有","无") -> 有
A92: HSA25J001-3 | B92: 46078 | C92: 波兰749 | D92: 渠道商 | E92: 昊特赛八公司 | F92: 办公室 | H92: 市场七八司 | I92: 业务办公室 | J92: 力量训练 | K92: 哑铃及哑铃凳 | L92: 哑铃 | N92: PO-ST3001-002 | O92: 李 宁2 | P92: 外部引进 | Q92: USD | R92: 6.89 | S92: 1939.2 | T92: 1939.2 | U92: 13.57 | V92: 11.5 | W92: 0 | X92: 13938 | Y92: 1603.49 | Z92: 0 | AA92: 0 | AB92: 0 | AC92: 0 | AD92: 0 | AE92: 0 | AF92: 0 | AG92: =(T92-U92-V92-W92)*R92-X92+Y92-Z92-AA92-AB92-AC92-AD92-AE92-AF92 -> 853.8457 | AH92: =IF(ISNUMBER(MATCH(A92,'畅想出运数据（核算明细导出）'!$C$2:$C$484,0)),"有","无") -> 有
... A121: HSA25J010-3，HSA25D002-1 | B121: 46106 | C121: 波兰749 | D121: 渠道商 | E121: 昊特赛一公司 | F121: 客户第一组 | H121: 市场七一司 | I121: 客户第二组 | J121: 家居装饰品 | K121: 桌上装饰用品 | L121: 装饰托盘 | N121: GD-HD300-1004 | O121: 钟 琪 | P121: 外部引进 | Q121: USD | R121: 6.9 | S121: 960.48 | T121: 960.48 | U121: 6.72 | V121: 14.12 | W121: 0 | X121: 6624 | Y121: 762.05 | Z121: 249.41 | AA121: 0 | AB121: 0 | AC121: 0 | AD121: 0 | AE121: 0 | AF121: 0 | AG121: =(T121-U121-V121-W121)*R121-X121+Y121-Z121-AA121-AB121-AC121-AD121-AE121-AF121 -> 372.156 | AH121: =IF(ISNUMBER(MATCH(A121,'畅想出运数据（核算明细导出）'!$C$2:$C$484,0)),"有","无") -> 有
A122: HSA25Y007-2 | B122: 46106 | C122: 波兰749 | D122: 渠道商 | E122: 昊特赛一公司 | F122: 客户第一组 | H122: 市场七一司 | I122: 客户第二组 | J122: DIY玩具 | K122: 其他DIY玩具 | L122: 其他常规DIY玩具 | M122: 0C003 | N122: OC003-MQ-brown | O122: 原柯冬浩 | P122: 外部引进 | Q122: USD | R122: 6.87 | S122: 1108.8 | T122: 1108.8 | U122: 7.76 | V122: 50 | W122: 0 | X122: 7358.4 | Y122: 846.54 | Z122: 1820.06 | AA122: 0 | AB122: 0 | AC122: 0 | AD122: 0 | AE122: 0 | AF122: 0 | AG122: =(T122-U122-V122-W122)*R122-X122+Y122-Z122-AA122-AB122-AC122-AD122-AE122-AF122 -> -1111.2752 | AH122: =IF(ISNUMBER(MATCH(A122,'畅想出运数据（核算明细导出）'!$C$2:$C$484,0)),"有","无") -> 有
A123: HSA25D010-4 | B123: 46106 | C123: 波兰749 | D123: 渠道商 | E123: 昊特赛一公司 | F123: 客户第一组 | H123: 市场七一司 | I123: 客户第二组 | J123: 家居装饰品 | K123: 桌上装饰用品 | L123: 装饰蜡烛及烛台 | N123: GD-HD300-1003 | O123: 钟 琪 | P123: 外部引进 | Q123: USD | R123: 6.89 | S123: 1236 | T123: 1236 | U123: 8.65 | V123: 50 | W123: 0 | X123: 7200 | Y123: 573.45 | Z123: 1519.7 | AA123: 0 | AB123: 0 | AC123: 0 | AD123: 0 | AE123: 0 | AF123: 0 | AG123: =(T123-U123-V123-W123)*R123-X123+Y123-Z123-AA123-AB123-AC123-AD123-AE123-AF123 -> -34.3085 | AH123: =IF(ISNUMBER(MATCH(A123,'畅想出运数据（核算明细导出）'!$C$2:$C$484,0)),"有","无") -> 有
A124: HSA25D010-3，HSA25D001 | B124: 46106 | C124: 波兰749 | D124: 渠道商 | E124: 昊特赛一公司 | F124: 客户第一组 | H124: 市场七一司 | I124: 客户第二组 | J124: 家居装饰品 | K124: 桌上装饰用品 | L124: 装饰蜡烛及烛台 | N124: GD-HD300-1002 | O124: 钟 琪 | P124: 外部引进 | Q124: USD | R124: 6.85 | S124: 943.92 | T124: 943.92 | U124: 6.6 | V124: 29.15 | W124: 0 | X124: 5643 | Y124: 449.44 | Z124: 663.91 | AA124: 0 | AB124: 0 | AC124: 0 | AD124: 0 | AE124: 0 | AF124: 0 | AG124: =(T124-U124-V124-W124)*R124-X124+Y124-Z124-AA124-AB124-AC124-AD124-AE124-AF124 -> 363.4945 | AH124: =IF(ISNUMBER(MATCH(A124,'畅想出运数据（核算明细导出）'!$C$2:$C$484,0)),"有","无") -> 有
A125: HSA25J010-3，HSA25D002-1 | B125: 46106 | C125: 波兰749 | D125: 渠道商 | E125: 昊特赛一公司 | F125: 客户第一组 | H125: 市场七一司 | I125: 客户第二组 | J125: 家庭收纳 | K125: 收纳容器 | L125: 收纳盒 | N125: HS-HO100-1001 | O125: 钟 琪 | P125: 外部引进 | Q125: USD | R125: 6.9 | S125: 2440 | T125: 2440 | U125: 17.08 | V125: 35.88 | W125: 0 | X125: 16000 | Y125: 1840.71 | Z125: 1548.68 | AA125: 0 | AB125: 0 | AC125: 0 | AD125: 0 | AE125: 0 | AF125: 0 | AG125: =(T125-U125-V125-W125)*R125-X125+Y125-Z125-AA125-AB125-AC125-AD125-AE125-AF125 -> 762.606 | AH125: =IF(ISNUMBER(MATCH(A125,'畅想出运数据（核算明细导出）'!$C$2:$C$484,0)),"有","无") -> 有
A126: HSA25D010-3，HSA25D001 | B126: 46106 | C126: 波兰749 | D126: 渠道商 | E126: 昊特赛一公司 | F126: 客户第一组 | H126: 市场七一司 | I126: 客户第二组 | J126: 工艺陶瓷 | K126: 陶瓷工艺品 | L126: 常规陶瓷工艺品 | N126: GD-PC100-1001 | O126: 钟 琪 | P126: 外部引进 | Q126: USD | R126: 6.85 | S126: 675.36 | T126: 675.36 | U126: 4.73 | V126: 20.85 | W126: 0 | X126: 4435.2 | Y126: 353.25 | Z126: 959.07 | AA126: 0 | AB126: 0 | AC126: 0 | AD126: 0 | AE126: 0 | AF126: 0 | AG126: =(T126-U126-V126-W126)*R126-X126+Y126-Z126-AA126-AB126-AC126-AD126-AE126-AF126 -> -590.027 | AH126: =IF(ISNUMBER(MATCH(A126,'畅想出运数据（核算明细导出）'!$C$2:$C$484,0)),"有","无") -> 有
A127: HSC26H001-2 | B127: 46106 | C127: 波兰749 | D127: 渠道商 | E127: 昊特赛三公司 | F127: 办公室 | H127: 市场七三司 | I127: 业务办公室 | J127: 鞋服收纳 | K127: 挂衣架及挂衣钩 | L127: 挂衣架 | N127: 571GQ-08X-ONE | O127: 黄家辉 | P127: 自主研发 | Q127: USD | R127: 6.87 | S127: 1250 | T127: 1250 | U127: 8.75 | V127: 50 | W127: 0 | X127: 9750 | Y127: 1121.68 | Z127: 91.45 | AA127: 0 | AB127: 0 | AC127: 0 | AD127: 0 | AE127: 0 | AF127: 0 | AG127: =(T127-U127-V127-W127)*R127-X127+Y127-Z127-AA127-AB127-AC127-AD127-AE127-AF127 -> -535.8825 | AH127: =IF(ISNUMBER(MATCH(A127,'畅想出运数据（核算明细导出）'!$C$2:$C$484,0)),"有","无") -> 有
A128: HSB25M024-9 | B128: 46106 | C128: 英国2962 | D128: 渠道商 | E128: 昊特赛二公司 | F128: 办公室 | H128: 市场七九司 | J128: 装扮玩具 | K128: 其他装扮玩具 | L128: 其他常规装扮玩具 | M128: 0D322 | N128: 0D322-PS001 | O128: 丁迎全 | P128: 外部引进 | Q128: USD | R128: 6.94 | S128: 391.68 | T128: 391.68 | U128: 2.74 | V128: 3.79 | W128: 7.83 | X128: 3035.52 | Y128: 349.22 | Z128: 0 | AA128: 0 | AB128: 0 | AC128: 0 | AD128: 0 | AE128: 0 | AF128: 0 | AG128: =(T128-U128-V128-W128)*R128-X128+Y128-Z128-AA128-AB128-AC128-AD128-AE128-AF128 -> -67.6992 | AH128: =IF(ISNUMBER(MATCH(A128,'畅想出运数据（核算明细导出）'!$C$2:$C$484,0)),"有","无") -> 有
A129: HSB25M027-5 | B129: 46106 | C129: 英国2962 | D129: 渠道商 | E129: 昊特赛九公司 | F129: 办公室 | H129: 市场七九司 | J129: 装扮玩具 | K129: 其他装扮玩具 | L129: 其他常规装扮玩具 | M129: 0D322 | N129: 0D322-PS001 | O129: 丁迎全 | P129: 外部引进 | Q129: USD | R129: 6.87 | S129: 295.68 | T129: 295.68 | U129: 2.07 | V129: 3.65 | W129: 5.91 | X129: 2291.52 | Y129: 263.63 | Z129: 76.62 | AA129: 0 | AB129: 0 | AC129: 0 | AD129: 0 | AE129: 0 | AF129: 0 | AG129: =(T129-U129-V129-W129)*R129-X129+Y129-Z129-AA129-AB129-AC129-AD129-AE129-AF129 -> -153.0865 | AH129: =IF(ISNUMBER(MATCH(A129,'畅想出运数据（核算明细导出）'!$C$2:$C$484,0)),"有","无") -> 有
A130: HSB25M027-9 | B130: 46106 | C130: 英国2962 | D130: 渠道商 | E130: 昊特赛九公司 | F130: 办公室 | H130: 市场七九司 | J130: 装扮玩具 | K130: 其他装扮玩具 | L130: 其他常规装扮玩具 | M130: 0D322 | N130: 0D322-PS001 | O130: 丁迎全 | P130: 外部引进 | Q130: USD | R130: 6.87 | S130: 399.36 | T130: 399.36 | U130: 2.8 | V130: 3.63 | W130: 7.99 | X130: 3095.04 | Y130: 356.07 | Z130: 98.93 | AA130: 0 | AB130: 0 | AC130: 0 | AD130: 0 | AE130: 0 | AF130: 0 | AG130: =(T130-U130-V130-W130)*R130-X130+Y130-Z130-AA130-AB130-AC130-AD130-AE130-AF130 -> -193.3622 | AH130: =IF(ISNUMBER(MATCH(A130,'畅想出运数据（核算明细导出）'!$C$2:$C$484,0)),"有","无") -> 有
A131: HSB25M026-3 | B131: 46106 | C131: 英国2962 | D131: 渠道商 | E131: 昊特赛二公司 | F131: 办公室 | H131: 市场七九司 | J131: 装扮玩具 | K131: 其他装扮玩具 | L131: 其他常规装扮玩具 | M131: 0D322 | N131: 0D322-PS001 | O131: 丁迎全 | P131: 外部引进 | Q131: USD | R131: 6.89 | S131: 276.48 | T131: 276.48 | U131: 1.94 | V131: 3.61 | W131: 5.53 | X131: 2142.72 | Y131: 246.51 | Z131: 0 | AA131: 0 | AB131: 0 | AC131: 0 | AD131: 0 | AE131: 0 | AF131: 0 | AG131: =(T131-U131-V131-W131)*R131-X131+Y131-Z131-AA131-AB131-AC131-AD131-AE131-AF131 -> -67.604 | AH131: =IF(ISNUMBER(MATCH(A131,'畅想出运数据（核算明细导出）'!$C$2:$C$484,0)),"有","无") -> 有
A132: HSB25M026-1 | B132: 46106 | C132: 英国2962 | D132: 渠道商 | E132: 昊特赛二公司 | F132: 办公室 | H132: 市场七九司 | J132: 装扮玩具 | K132: 其他装扮玩具 | L132: 其他常规装扮玩具 | M132: 0D322 | N132: 0D322-PS001 | O132: 丁迎全 | P132: 外部引进 | Q132: USD | R132: 6.93 | S132: 407.04 | T132: 407.04 | U132: 2.85 | V132: 3.66 | W132: 8.14 | X132: 3154.56 | Y132: 362.91 | Z132: 0 | AA132: 0 | AB132: 0 | AC132: 0 | AD132: 0 | AE132: 0 | AF132: 0 | AG132: =(T132-U132-V132-W132)*R132-X132+Y132-Z132-AA132-AB132-AC132-AD132-AE132-AF132 -> -72.3873 | AH132: =IF(ISNUMBER(MATCH(A132,'畅想出运数据（核算明细导出）'!$C$2:$C$484,0)),"有","无") -> 有
A133: HSB25M026-2 | B133: 46106 | C133: 英国2962 | D133: 渠道商 | E133: 昊特赛二公司 | F133: 办公室 | H133: 市场七九司 | J133: 装扮玩具 | K133: 其他装扮玩具 | L133: 其他常规装扮玩具 | M133: 0D322 | N133: 0D322-PS001 | O133: 丁迎全 | P133: 外部引进 | Q133: USD | R133: 6.94 | S133: 399.36 | T133: 399.36 | U133: 2.8 | V133: 3.62 | W133: 7.99 | X133: 3095.04 | Y133: 356.07 | Z133: 0 | AA133: 0 | AB133: 0 | AC133: 0 | AD133: 0 | AE133: 0 | AF133: 0 | AG133: =(T133-U133-V133-W133)*R133-X133+Y133-Z133-AA133-AB133-AC133-AD133-AE133-AF133 -> -67.417 | AH133: =IF(ISNUMBER(MATCH(A133,'畅想出运数据（核算明细导出）'!$C$2:$C$484,0)),"有","无") -> 有
A134: HSB25M027-10 | B134: 46106 | C134: 英国2962 | D134: 渠道商 | E134: 昊特赛九公司 | F134: 办公室 | H134: 市场七九司 | J134: 装扮玩具 | K134: 其他装扮玩具 | L134: 其他常规装扮玩具 | M134: 0D322 | N134: 0D322-PS001 | O134: 丁迎全 | P134: 外部引进 | Q134: USD | R134: 6.87 | S134: 403.2 | T134: 403.2 | U134: 2.82 | V134: 3.63 | W134: 8.06 | X134: 3124.8 | Y134: 359.49 | Z134: 99.17 | AA134: 0 | AB134: 0 | AC134: 0 | AD134: 0 | AE134: 0 | AF134: 0 | AG134: =(T134-U134-V134-W134)*R134-X134+Y134-Z134-AA134-AB134-AC134-AD134-AE134-AF134 -> -194.1797 | AH134: =IF(ISNUMBER(MATCH(A134,'畅想出运数据（核算明细导出）'!$C$2:$C$484,0)),"有","无") -> 有
A135: HSB25M027-1 | B135: 46106 | C135: 英国2962 | D135: 渠道商 | E135: 昊特赛九公司 | F135: 办公室 | H135: 市场七九司 | J135: 装扮玩具 | K135: 其他装扮玩具 | L135: 其他常规装扮玩具 | M135: 0D322 | N135: 0D322-PS001 | O135: 丁迎全 | P135: 外部引进 | Q135: USD | R135: 6.87 | S135: 1025.28 | T135: 1025.28 | U135: 7.18 | V135: 3.55 | W135: 20.51 | X135: 7945.92 | Y135: 914.13 | Z135: 179.65 | AA135: 0 | AB135: 0 | AC135: 0 | AD135: 0 | AE135: 0 | AF135: 0 | AG135: =(T135-U135-V135-W135)*R135-X135+Y135-Z135-AA135-AB135-AC135-AD135-AE135-AF135 -> -382.3852 | AH135: =IF(ISNUMBER(MATCH(A135,'畅想出运数据（核算明细导出）'!$C$2:$C$484,0)),"有","无") -> 有
A136: HSB25M024-9 | B136: 46106 | C136: 英国2962 | D136: 渠道商 | E136: 昊特赛二公司 | F136: 办公室 | H136: 市场七九司 | J136: 运动休闲包 | K136: 沙滩包 | L136: 常规沙滩包 | M136: BB001 | N136: BB001-STB-1 | O136: 原柯冬浩 | P136: 外部引进 | Q136: USD | R136: 6.94 | S136: 4780.4 | T136: 4780.4 | U136: 33.46 | V136: 46.21 | W136: 95.61 | X136: 31450 | Y136: 3618.14 | Z136: 0 | AA136: 0 | AB136: 0 | AC136: 0 | AD136: 0 | AE136: 0 | AF136: 0 | AG136: =(T136-U136-V136-W136)*R136-X136+Y136-Z136-AA136-AB136-AC136-AD136-AE136-AF136 -> 4127.6728 | AH136: =IF(ISNUMBER(MATCH(A136,'畅想出运数据（核算明细导出）'!$C$2:$C$484,0)),"有","无") -> 有
A137: HSB25M027-5 | B137: 46106 | C137: 英国2962 | D137: 渠道商 | E137: 昊特赛九公司 | F137: 办公室 | H137: 市场七九司 | J137: 运动休闲包 | K137: 沙滩包 | L137: 常规沙滩包 | M137: BB001 | N137: BB001-STB-1 | O137: 原柯冬浩 | P137: 外部引进 | Q137: USD | R137: 6.87 | S137: 3754.4 | T137: 3754.4 | U137: 26.28 | V137: 46.35 | W137: 75.09 | X137: 24700 | Y137: 2841.59 | Z137: 1923.38 | AA137: 0 | AB137: 0 | AC137: 0 | AD137: 0 | AE137: 0 | AF137: 0 | AG137: =(T137-U137-V137-W137)*R137-X137+Y137-Z137-AA137-AB137-AC137-AD137-AE137-AF137 -> 996.1016 | AH137: =IF(ISNUMBER(MATCH(A137,'畅想出运数据（核算明细导出）'!$C$2:$C$484,0)),"有","无") -> 有
A138: HSB25M026-2 | B138: 46106 | C138: 英国2962 | D138: 渠道商 | E138: 昊特赛二公司 | F138: 办公室 | H138: 市场七九司 | J138: 运动休闲包 | K138: 沙滩包 | L138: 常规沙滩包 | M138: BB001 | N138: BB001-STB-1 | O138: 原柯冬浩 | P138: 外部引进 | Q138: USD | R138: 6.94 | S138: 5122.4 | T138: 5122.4 | U138: 35.85 | V138: 46.38 | W138: 102.45 | X138: 33700 | Y138: 3876.99 | Z138: 0 | AA138: 0 | AB138: 0 | AC138: 0 | AD138: 0 | AE138: 0 | AF138: 0 | AG138: =(T138-U138-V138-W138)*R138-X138+Y138-Z138-AA138-AB138-AC138-AD138-AE138-AF138 -> 4444.7668 | AH138: =IF(ISNUMBER(MATCH(A138,'畅想出运数据（核算明细导出）'!$C$2:$C$484,0)),"有","无") -> 有
A139: HSB25M026-3 | B139: 46106 | C139: 英国2962 | D139: 渠道商 | E139: 昊特赛二公司 | F139: 办公室 | H139: 市场七九司 | J139: 运动休闲包 | K139: 沙滩包 | L139: 常规沙滩包 | M139: BB001 | N139: BB001-STB-1 | O139: 原柯冬浩 | P139: 外部引进 | Q139: USD | R139: 6.89 | S139: 3556.8 | T139: 3556.8 | U139: 24.89 | V139: 46.39 | W139: 71.13 | X139: 23400 | Y139: 2692.04 | Z139: 0 | AA139: 0 | AB139: 0 | AC139: 0 | AD139: 0 | AE139: 0 | AF139: 0 | AG139: =(T139-U139-V139-W139)*R139-X139+Y139-Z139-AA139-AB139-AC139-AD139-AE139-AF139 -> 2817.1871 | AH139: =IF(ISNUMBER(MATCH(A139,'畅想出运数据（核算明细导出）'!$C$2:$C$484,0)),"有","无") -> 有
... A180: HSB25M027-4 | B180: 46106 | C180: 英国2962 | D180: 渠道商 | E180: 昊特赛九公司 | F180: 办公室 | H180: 市场七九司 | J180: 游泳装备 | K180: 游泳训练器材 | L180: 游泳圈 | M180: ST048 | N180: ST048-SC-1 | O180: 丁迎全 | P180: 外部引进 | Q180: USD | R180: 6.89 | S180: 2218.5 | T180: 2218.5 | U180: 15.53 | V180: 17.49 | W180: 44.37 | X180: 14094 | Y180: 1621.43 | Z180: 238.02 | AA180: 0 | AB180: 0 | AC180: 0 | AD180: 0 | AE180: 0 | AF180: 0 | AG180: =(T180-U180-V180-W180)*R180-X180+Y180-Z180-AA180-AB180-AC180-AD180-AE180-AF180 -> 2041.6579 | AH180: =IF(ISNUMBER(MATCH(A180,'畅想出运数据（核算明细导出）'!$C$2:$C$484,0)),"有","无") -> 有
A181: HSA25Y002-5 | B181: 46106 | C181: 波兰749 | D181: 渠道商 | E181: 昊特赛一公司 | F181: 客户第一组 | H181: 市场七九司 | I181: 客户第一组 | J181: 玩偶玩具 | K181: 布艺玩偶 | L181: 常规布艺玩偶 | N181: KB-DL200-122 | O181: 钟 琪 | P181: 外部引进 | Q181: USD | R181: 6.87 | S181: 1792.8 | T181: 1792.8 | U181: 12.55 | V181: 50 | W181: 0 | X181: 12669.12 | Y181: 1457.51 | Z181: 1452.14 | AA181: 0 | AB181: 0 | AC181: 0 | AD181: 0 | AE181: 0 | AF181: 0 | AG181: =(T181-U181-V181-W181)*R181-X181+Y181-Z181-AA181-AB181-AC181-AD181-AE181-AF181 -> -776.9325 | AH181: =IF(ISNUMBER(MATCH(A181,'畅想出运数据（核算明细导出）'!$C$2:$C$484,0)),"有","无") -> 有
A182: HSA25Y001-4 | B182: 46106 | C182: 波兰749 | D182: 渠道商 | E182: 昊特赛一公司 | F182: 客户第一组 | H182: 市场七九司 | I182: 客户第一组 | J182: DIY玩具 | K182: 其他DIY玩具 | L182: 其他常规DIY玩具 | M182: 0C003 | N182: OC003-MQ-brown | O182: 原柯冬浩 | P182: 外部引进 | Q182: USD | R182: 6.94 | S182: 1108.8 | T182: 1108.8 | U182: 7.76 | V182: 29.61 | W182: 0 | X182: 7358.4 | Y182: 846.54 | Z182: 769.07 | AA182: 0 | AB182: 0 | AC182: 0 | AD182: 0 | AE182: 0 | AF182: 0 | AG182: =(T182-U182-V182-W182)*R182-X182+Y182-Z182-AA182-AB182-AC182-AD182-AE182-AF182 -> 154.7942 | AH182: =IF(ISNUMBER(MATCH(A182,'畅想出运数据（核算明细导出）'!$C$2:$C$484,0)),"有","无") -> 有
A183: HSA25Y001-4 | B183: 46106 | C183: 波兰749 | D183: 渠道商 | E183: 昊特赛一公司 | F183: 客户第一组 | H183: 市场七九司 | I183: 客户第一组 | J183: DIY玩具 | K183: 其他DIY玩具 | L183: 其他常规DIY玩具 | M183: 0C001 | N183: OC001-QP-pink | O183: 原柯冬浩 | P183: 外部引进 | Q183: USD | R183: 6.94 | S183: 763.84 | T183: 763.84 | U183: 5.35 | V183: 20.39 | W183: 0 | X183: 6348.8 | Y183: 730.39 | Z183: 1510.32 | AA183: 0 | AB183: 0 | AC183: 0 | AD183: 0 | AE183: 0 | AF183: 0 | AG183: =(T183-U183-V183-W183)*R183-X183+Y183-Z183-AA183-AB183-AC183-AD183-AE183-AF183 -> -2006.316 | AH183: =IF(ISNUMBER(MATCH(A183,'畅想出运数据（核算明细导出）'!$C$2:$C$484,0)),"有","无") -> 有
A184: HSB25M022-1 | B184: 46106 | C184: 英国2962 | D184: 渠道商 | E184: 昊特赛二公司 | F184: 客户第一组 | H184: 市场七九司 | I184: 客户第一组 | J184: 手工艺品及DIY玩具 | K184: 创意类及材料包 | L184: 其他常规DIY玩具 | M184: OD270 | N184: OD270-SLM001 | O184: 敖 旭 | P184: 外部引进 | Q184: USD | R184: 6.96 | S184: 14313.6 | T184: 14313.6 | U184: 100.2 | V184: 50 | W184: 286.27 | X184: 95424 | Y184: 10977.98 | Z184: 5057.75 | AA184: 0 | AB184: 0 | AC184: 0 | AD184: 0 | AE184: 0 | AF184: 0 | AG184: =(T184-U184-V184-W184)*R184-X184+Y184-Z184-AA184-AB184-AC184-AD184-AE184-AF184 -> 7081.0548 | AH184: =IF(ISNUMBER(MATCH(A184,'畅想出运数据（核算明细导出）'!$C$2:$C$484,0)),"有","无") -> 有
A185: HSB25M022-5 | B185: 46106 | C185: 英国2962 | D185: 渠道商 | E185: 昊特赛二公司 | F185: 客户第一组 | H185: 市场七九司 | I185: 客户第一组 | J185: 手工艺品及DIY玩具 | K185: 创意类及材料包 | L185: 其他常规DIY玩具 | M185: OD270 | N185: OD270-SLM001 | O185: 敖 旭 | P185: 外部引进 | Q185: USD | R185: 6.96 | S185: 6465.6 | T185: 6465.6 | U185: 45.26 | V185: 50 | W185: 129.31 | X185: 43104 | Y185: 4958.87 | Z185: 5057.75 | AA185: 0 | AB185: 0 | AC185: 0 | AD185: 0 | AE185: 0 | AF185: 0 | AG185: =(T185-U185-V185-W185)*R185-X185+Y185-Z185-AA185-AB185-AC185-AD185-AE185-AF185 -> 234.6888 | AH185: =IF(ISNUMBER(MATCH(A185,'畅想出运数据（核算明细导出）'!$C$2:$C$484,0)),"有","无") -> 有
A186: HSB25M022-3 | B186: 46106 | C186: 英国2962 | D186: 渠道商 | E186: 昊特赛二公司 | F186: 客户第一组 | H186: 市场七九司 | I186: 客户第一组 | J186: 手工艺品及DIY玩具 | K186: 创意类及材料包 | L186: 其他常规DIY玩具 | M186: OD270 | N186: OD270-SLM001 | O186: 敖 旭 | P186: 外部引进 | Q186: USD | R186: 6.96 | S186: 7286.4 | T186: 7286.4 | U186: 51 | V186: 50 | W186: 145.73 | X186: 48576 | Y186: 5588.39 | Z186: 5057.75 | AA186: 0 | AB186: 0 | AC186: 0 | AD186: 0 | AE186: 0 | AF186: 0 | AG186: =(T186-U186-V186-W186)*R186-X186+Y186-Z186-AA186-AB186-AC186-AD186-AE186-AF186 -> 950.7432 | AH186: =IF(ISNUMBER(MATCH(A186,'畅想出运数据（核算明细导出）'!$C$2:$C$484,0)),"有","无") -> 有
A187: HSB25M022-2 | B187: 46106 | C187: 英国2962 | D187: 渠道商 | E187: 昊特赛二公司 | F187: 客户第一组 | H187: 市场七九司 | I187: 客户第一组 | J187: 手工艺品及DIY玩具 | K187: 创意类及材料包 | L187: 其他常规DIY玩具 | M187: OD270 | N187: OD270-SLM001 | O187: 敖 旭 | P187: 外部引进 | Q187: USD | R187: 6.96 | S187: 11073.6 | T187: 11073.6 | U187: 77.52 | V187: 50 | W187: 221.47 | X187: 73824 | Y187: 8493.03 | Z187: 5057.75 | AA187: 0 | AB187: 0 | AC187: 0 | AD187: 0 | AE187: 0 | AF187: 0 | AG187: =(T187-U187-V187-W187)*R187-X187+Y187-Z187-AA187-AB187-AC187-AD187-AE187-AF187 -> 4254.5656 | AH187: =IF(ISNUMBER(MATCH(A187,'畅想出运数据（核算明细导出）'!$C$2:$C$484,0)),"有","无") -> 有
A188: HSB25M022-4 | B188: 46106 | C188: 英国2962 | D188: 渠道商 | E188: 昊特赛二公司 | F188: 客户第一组 | H188: 市场七九司 | I188: 客户第一组 | J188: 手工艺品及DIY玩具 | K188: 创意类及材料包 | L188: 其他常规DIY玩具 | M188: OD270 | N188: OD270-SLM001 | O188: 敖 旭 | P188: 外部引进 | Q188: USD | R188: 6.96 | S188: 8870.4 | T188: 8870.4 | U188: 62.09 | V188: 50 | W188: 177.41 | X188: 59136 | Y188: 6803.26 | Z188: 5057.75 | AA188: 0 | AB188: 0 | AC188: 0 | AD188: 0 | AE188: 0 | AF188: 0 | AG188: =(T188-U188-V188-W188)*R188-X188+Y188-Z188-AA188-AB188-AC188-AD188-AE188-AF188 -> 2332.574 | AH188: =IF(ISNUMBER(MATCH(A188,'畅想出运数据（核算明细导出）'!$C$2:$C$484,0)),"有","无") -> 有
A189: HSA25J011-2 | B189: 46106 | C189: 波兰749 | D189: 渠道商 | E189: 昊特赛八公司 | F189: 办公室 | H189: 市场七八司 | I189: 业务办公室 | J189: 经典玩具 | K189: 其他经典玩具 | L189: 其他常规经典玩具 | N189: KB-CT600-1011 | O189: 钟 琪 | P189: 外部引进 | Q189: USD | R189: 6.87 | S189: 846 | T189: 846 | U189: 5.92 | V189: 23.86 | W189: 0 | X189: 5085 | Y189: 585 | Z189: 1157.33 | AA189: 0 | AB189: 0 | AC189: 0 | AD189: 0 | AE189: 0 | AF189: 0 | AG189: =(T189-U189-V189-W189)*R189-X189+Y189-Z189-AA189-AB189-AC189-AD189-AE189-AF189 -> -49.8986 | AH189: =IF(ISNUMBER(MATCH(A189,'畅想出运数据（核算明细导出）'!$C$2:$C$484,0)),"有","无") -> 有
A190: HSA25J008-2 | B190: 46106 | C190: 德国1433 | D190: 品牌商 | E190: 昊特赛八公司 | F190: 办公室 | H190: 市场七八司 | I190: 业务办公室 | J190: 露营和远足 | K190: 户外家具 | L190: 户外折叠椅 | N190: XY-118A1-1910-1 | O190: 王柯飞 | P190: 外部引进 | Q190: USD | R190: 6.88 | S190: 3382.5 | T190: 3382.5 | U190: 23.94 | V190: 19.64 | W190: 0 | X190: 19140 | Y190: 2201.95 | Z190: 1352.49 | AA190: 0 | AB190: 0 | AC190: 0 | AD190: 0 | AE190: 0 | AF190: 0 | AG190: =(T190-U190-V190-W190)*R190-X190+Y190-Z190-AA190-AB190-AC190-AD190-AE190-AF190 -> 4681.2296 | AH190: =IF(ISNUMBER(MATCH(A190,'畅想出运数据（核算明细导出）'!$C$2:$C$484,0)),"有","无") -> 有
A191: HSA25J008-2 | B191: 46106 | C191: 德国1433 | D191: 品牌商 | E191: 昊特赛八公司 | F191: 办公室 | H191: 市场七八司 | I191: 业务办公室 | J191: 露营和远足 | K191: 户外家具 | L191: 户外折叠椅 | N191: XY-118A1-1910-1 | O191: 王柯飞 | P191: 外部引进 | Q191: USD | R191: 6.88 | S191: 0 | T191: 0 | U191: 0 | V191: 0 | W191: 0 | X191: 290 | Y191: 33.36 | Z191: 20.49 | AA191: 0 | AB191: 0 | AC191: 0 | AD191: 0 | AE191: 0 | AF191: 0 | AG191: =(T191-U191-V191-W191)*R191-X191+Y191-Z191-AA191-AB191-AC191-AD191-AE191-AF191 -> -277.13 | AH191: =IF(ISNUMBER(MATCH(A191,'畅想出运数据（核算明细导出）'!$C$2:$C$484,0)),"有","无") -> 有
A192: HSA25J011-3 | B192: 46106 | C192: 波兰749 | D192: 渠道商 | E192: 昊特赛八公司 | F192: 办公室 | H192: 市场七八司 | I192: 业务办公室 | J192: 经典玩具 | K192: 其他经典玩具 | L192: 其他常规经典玩具 | N192: KB-CT600-1017 | O192: 钟 琪 | P192: 外部引进 | Q192: USD | R192: 6.87 | S192: 1800 | T192: 1800 | U192: 12.6 | V192: 20.58 | W192: 0 | X192: 8100 | Y192: 931.86 | Z192: 367.43 | AA192: 0 | AB192: 0 | AC192: 0 | AD192: 0 | AE192: 0 | AF192: 0 | AG192: =(T192-U192-V192-W192)*R192-X192+Y192-Z192-AA192-AB192-AC192-AD192-AE192-AF192 -> 4602.4834 | AH192: =IF(ISNUMBER(MATCH(A192,'畅想出运数据（核算明细导出）'!$C$2:$C$484,0)),"有","无") -> 有
A193: HSA25J011-2 | B193: 46106 | C193: 波兰749 | D193: 渠道商 | E193: 昊特赛八公司 | F193: 办公室 | H193: 市场七八司 | I193: 业务办公室 | J193: 经典玩具 | K193: 其他经典玩具 | L193: 其他常规经典玩具 | N193: KB-CT600-1018 | O193: 钟 琪 | P193: 外部引进 | Q193: USD | R193: 6.87 | S193: 927 | T193: 927 | U193: 6.49 | V193: 26.14 | W193: 0 | X193: 7650 | Y193: 880.09 | Z193: 766.91 | AA193: 0 | AB193: 0 | AC193: 0 | AD193: 0 | AE193: 0 | AF193: 0 | AG193: =(T193-U193-V193-W193)*R193-X193+Y193-Z193-AA193-AB193-AC193-AD193-AE193-AF193 -> -1392.4981 | AH193: =IF(ISNUMBER(MATCH(A193,'畅想出运数据（核算明细导出）'!$C$2:$C$484,0)),"有","无") -> 有
A194: HSA25J012-3 | B194: 46106 | C194: 波兰749 | D194: 渠道商 | E194: 昊特赛八公司 | F194: 办公室 | H194: 市场七八司 | I194: 业务办公室 | J194: 露营和远足 | K194: 户外家具 | L194: 户外折叠椅 | N194: PO-CH100-1002 | O194: 钟 琪 | P194: 外部引进 | Q194: USD | R194: 6.89 | S194: 1323 | T194: 1323 | U194: 9.26 | V194: 5.03 | W194: 0 | X194: 10485 | Y194: 1206.24 | Z194: 143.38 | AA194: 0 | AB194: 0 | AC194: 0 | AD194: 0 | AE194: 0 | AF194: 0 | AG194: =(T194-U194-V194-W194)*R194-X194+Y194-Z194-AA194-AB194-AC194-AD194-AE194-AF194 -> -405.1281 | AH194: =IF(ISNUMBER(MATCH(A194,'畅想出运数据（核算明细导出）'!$C$2:$C$484,0)),"有","无") -> 有
A195: HSA25J004-3 | B195: 46106 | C195: 波兰749 | D195: 渠道商 | E195: 昊特赛八公司 | F195: 办公室 | H195: 市场七八司 | I195: 业务办公室 | J195: 综合运动 | K195: 其他体育用品 | L195: 弹力带 | N195: PO-OSP2001-002 | O195: 李 宁2 | P195: 外部引进 | Q195: USD | R195: 6.89 | S195: 892.5 | T195: 892.5 | U195: 6.25 | V195: 5.77 | W195: 0 | X195: 5880 | Y195: 676.46 | Z195: 45.58 | AA195: 0 | AB195: 0 | AC195: 0 | AD195: 0 | AE195: 0 | AF195: 0 | AG195: =(T195-U195-V195-W195)*R195-X195+Y195-Z195-AA195-AB195-AC195-AD195-AE195-AF195 -> 817.3872 | AH195: =IF(ISNUMBER(MATCH(A195,'畅想出运数据（核算明细导出）'!$C$2:$C$484,0)),"有","无") -> 有
A196: HSA25J012-3 | B196: 46106 | C196: 波兰749 | D196: 渠道商 | E196: 昊特赛八公司 | F196: 办公室 | H196: 市场七八司 | I196: 业务办公室 | J196: 露营和远足 | K196: 户外家具 | L196: 户外折叠椅 | N196: PO-CH100-1004 | O196: 钟 琪 | P196: 外部引进 | Q196: USD | R196: 6.89 | S196: 1341 | T196: 1341 | U196: 9.39 | V196: 5.09 | W196: 0 | X196: 10800 | Y196: 1242.48 | Z196: 143.38 | AA196: 0 | AB196: 0 | AC196: 0 | AD196: 0 | AE196: 0 | AF196: 0 | AG196: =(T196-U196-V196-W196)*R196-X196+Y196-Z196-AA196-AB196-AC196-AD196-AE196-AF196 -> -561.1772 | AH196: =IF(ISNUMBER(MATCH(A196,'畅想出运数据（核算明细导出）'!$C$2:$C$484,0)),"有","无") -> 有
A197: HSA25J004-3 | B197: 46106 | C197: 波兰749 | D197: 渠道商 | E197: 昊特赛八公司 | F197: 办公室 | H197: 市场七八司 | I197: 业务办公室 | J197: 瑜伽和普拉提 | K197: 其他瑜伽和普拉提用品 | L197: 瑜伽负重袋 | N197: PO-YP6001-002 | O197: 李 宁2 | P197: 外部引进 | Q197: USD | R197: 6.89 | S197: 921.6 | T197: 921.6 | U197: 6.45 | V197: 5.96 | W197: 0 | X197: 6297.6 | Y197: 724.5 | Z197: 85.23 | AA197: 0 | AB197: 0 | AC197: 0 | AD197: 0 | AE197: 0 | AF197: 0 | AG197: =(T197-U197-V197-W197)*R197-X197+Y197-Z197-AA197-AB197-AC197-AD197-AE197-AF197 -> 605.9891 | AH197: =IF(ISNUMBER(MATCH(A197,'畅想出运数据（核算明细导出）'!$C$2:$C$484,0)),"有","无") -> 有
A198: HSA25J004-3 | B198: 46106 | C198: 波兰749 | D198: 渠道商 | E198: 昊特赛八公司 | F198: 办公室 | H198: 市场七八司 | I198: 业务办公室 | J198: 瑜伽和普拉提 | K198: 其他瑜伽和普拉提用品 | L198: 瑜伽负重袋 | N198: PO-YP6001-001 | O198: 李 宁2 | P198: 外部引进 | Q198: USD | R198: 6.89 | S198: 780 | T198: 780 | U198: 5.46 | V198: 5.04 | W198: 0 | X198: 5304 | Y198: 610.19 | Z198: 57.71 | AA198: 0 | AB198: 0 | AC198: 0 | AD198: 0 | AE198: 0 | AF198: 0 | AG198: =(T198-U198-V198-W198)*R198-X198+Y198-Z198-AA198-AB198-AC198-AD198-AE198-AF198 -> 550.335 | AH198: =IF(ISNUMBER(MATCH(A198,'畅想出运数据（核算明细导出）'!$C$2:$C$484,0)),"有","无") -> 有
A199: HSA25J004-3 | B199: 46106 | C199: 波兰749 | D199: 渠道商 | E199: 昊特赛八公司 | F199: 办公室 | H199: 市场七八司 | I199: 业务办公室 | J199: 露营和远足 | K199: 户外家具 | L199: 庭院吊篮 | N199: PO-OF5001-003 | O199: 王柯飞 | P199: 外部引进 | Q199: USD | R199: 6.89 | S199: 5140.8 | T199: 5140.8 | U199: 35.98 | V199: 33.23 | W199: 0 | X199: 34272 | Y199: 3942.8 | Z199: 1193.25 | AA199: 0 | AB199: 0 | AC199: 0 | AD199: 0 | AE199: 0 | AF199: 0 | AG199: =(T199-U199-V199-W199)*R199-X199+Y199-Z199-AA199-AB199-AC199-AD199-AE199-AF199 -> 3420.8051 | AH199: =IF(ISNUMBER(MATCH(A199,'畅想出运数据（核算明细导出）'!$C$2:$C$484,0)),"有","无") -> 有
A200: HSA25J011-3 | B200: 46106 | C200: 波兰749 | D200: 渠道商 | E200: 昊特赛八公司 | F200: 办公室 | H200: 市场七八司 | I200: 业务办公室 | J200: 经典玩具 | K200: 其他经典玩具 | L200: 其他常规经典玩具 | N200: KB-CT600-1016 | O200: 钟 琪 | P200: 外部引进 | Q200: USD | R200: 6.87 | S200: 882 | T200: 882 | U200: 6.17 | V200: 10.08 | W200: 0 | X200: 6300 | Y200: 724.78 | Z200: 1299.87 | AA200: 0 | AB200: 0 | AC200: 0 | AD200: 0 | AE200: 0 | AF200: 0 | AG200: =(T200-U200-V200-W200)*R200-X200+Y200-Z200-AA200-AB200-AC200-AD200-AE200-AF200 -> -927.3875 | AH200: =IF(ISNUMBER(MATCH(A200,'畅想出运数据（核算明细导出）'!$C$2:$C$484,0)),"有","无") -> 有
...

Sheet 畅想出运数据透视
A3: 外销合同 | B3: 求和项:FOB | C3: 求和项:出厂价_预计毛利 | D3: 毛利率
A4: HSA25D001-1 | B4: 649.78 | C4: -604.24 | D4: =TEXT(C4/B4/6.8,"0.00%") -> -13.68%
A5: HSA25D001-2 | B5: 390.46 | C5: -218.2 | D5: =TEXT(C5/B5/6.8,"0.00%") -> -8.22%
A6: HSA25D002-1 | B6: 2072.88 | C6: 579.65 | D6: =TEXT(C6/B6/6.8,"0.00%") -> 4.11%
A7: HSA25D003 | B7: 1772.5 | C7: 1225.91 | D7: =TEXT(C7/B7/6.8,"0.00%") -> 10.17%
A8: HSA25D004 | B8: 1431.95 | C8: 45.3 | D8: =TEXT(C8/B8/6.8,"0.00%") -> 0.47%
A9: HSA25D004-1 | B9: 319.75 | C9: 19.62 | D9: =TEXT(C9/B9/6.8,"0.00%") -> 0.90%
A10: HSA25D005 | B10: 2233.86 | C10: 1745.19 | D10: =TEXT(C10/B10/6.8,"0.00%") -> 11.49%
A11: HSA25D006 | B11: 1846.22 | C11: -284.64 | D11: =TEXT(C11/B11/6.8,"0.00%") -> -2.27%
A12: HSA25D010 | B12: 3887.32 | C12: 1265.43 | D12: =TEXT(C12/B12/6.8,"0.00%") -> 4.79%
A13: HSA25D011 | B13: 123.38 | C13: 131.97 | D13: =TEXT(C13/B13/6.8,"0.00%") -> 15.73%
A14: HSA25J001-1 | B14: 9565.26 | C14: 6741.38 | D14: =TEXT(C14/B14/6.8,"0.00%") -> 10.36%
A15: HSA25J002-1 | B15: 11169.1 | C15: 260.16 | D15: =TEXT(C15/B15/6.8,"0.00%") -> 0.34%
... A146: HSC25X013 | B146: 5894.97 | C146: 2224.72 | D146: =TEXT(C146/B146/6.8,"0.00%") -> 5.55%
A147: 总计 | B147: 2451451.8 | C147: 1070900.1

Sheet 畅想出运数据（核算明细导出）
A1: 业务员 | B1: 部门 | C1: 订单号 | D1: 外销合同 | E1: 客户 | F1: 客户来源 | G1: 签单日 | H1: 出运日 | I1: 出运月份 | J1: 核算月份 | K1: 交货期 | L1: PI交期 | M1: 出货数量 | N1: 一级目录 | O1: 中文品名 | P1: 采购跟单 | Q1: 采购员 | R1: 应收收汇 | S1: 收汇方式 | T1: 海运费+保费 | U1: 出口信保费用 | V1: 其他 | W1: 银行费 | X1: FOB | Y1: 收汇（USD） | Z1: 收汇（RMB） | AA1: 实际FOB | AB1: 内陆费 | AC1: 单证费 | AD1: 其他费 | AE1: 仓储费 | AF1: 验货费 | AG1: 包装设计费 | AH1: 实际FOB(RMB) | AI1: 出厂价_应付货款 | AJ1: 出厂价_退税款 | AK1: 出厂价_资金成本 | AL1: 出厂价_预计毛利 | AM1: 出厂价_毛利率 | AN1: 出厂价_实际毛利（收汇RMB） | AO1: 客户编号 | AP1: 产品编号 | AQ1: 操作月份 | AR1: 出厂价_预计毛利2 | AS1: 组别 | AT1: 二级目录 | AU1: 三级目录 | AV1: 对比畅想结算中心 | AW1: 对比外销合同
A2: 王柯飞 | B2: 昊特赛八公司 | C2: HSA25J001-1 | D2: HSA25J001-1 | E2: LPP | F2: 主动开发 | G2: 2025-08-04 | H2: 2026-02-17 | I2: 2 | J2: 202605 | K2: 197 | L2: 2025-09-20 | M2: 1008 | N2: 其他运动用品 | O2: 弹力带 | P2: 杜 娟 | R2: 594.72 | S2: OA 90 DAYS | T2: 0 | U2: 4.16 | V2: 0 | W2: 7.14 | X2: 533.42 | Y2: 0 | Z2: 0 | AA2: -11.3 | AB2: 0 | AC2: 0 | AD2: 0 | AE2: 0 | AF2: 0 | AG2: 0 | AH2: -77.91 | AI2: 3729.6 | AJ2: 429.07 | AK2: 18.65 | AL2: 358.59 | AM2: 0.0975 | AN2: -3347.86 | AO2: 波兰749 | AP2: PO-OSP2001-001 | AQ2: 202602 | AR2: 426.468 | AS2: 办公室 | AT2: 伸展训练 | AU2: 弹力带 | AV2: =IF(ISNUMBER(MATCH(C2,畅想结算中心!$A$2:$A$436,0)),"有","无") -> 有
A3: 王柯飞 | B3: 昊特赛八公司 | C3: HSA25J001-3 | D3: HSA25J001-1 | E3: LPP | F3: 主动开发 | G3: 2025-08-04 | H3: 2026-02-17 | I3: 2 | J3: 202605 | K3: 197 | L3: 2025-09-20 | M3: 1008 | N3: 瑜伽和普拉提 | O3: 常规瑜伽砖 | P3: 杜 娟 | R3: 786.24 | S3: OA 90 DAYS | T3: 0 | U3: 5.5 | V3: 0 | W3: 9.44 | X3: 766.64 | Y3: 0 | Z3: 0 | AA3: -14.94 | AB3: 0 | AC3: 0 | AD3: 0 | AE3: 0 | AF3: 0 | AG3: 0 | AH3: -103.01 | AI3: 5040 | AJ3: 579.82 | AK3: 25.2 | AL3: 800.38 | AM3: 0.1514 | AN3: -4523.32 | AO3: 波兰749 | AP3: PO-YP2001-002 | AQ3: 202602 | AR3: 890.6618 | AS3: 办公室 | AT3: 瑜伽砖 | AU3: 常规瑜伽砖 | AV3: =IF(ISNUMBER(MATCH(C3,畅想结算中心!$A$2:$A$436,0)),"有","无") -> 有
A4: 王柯飞 | B4: 昊特赛八公司 | C4: HSA25J001-3 | D4: HSA25J001-1 | E4: LPP | F4: 主动开发 | G4: 2025-08-04 | H4: 2026-02-17 | I4: 2 | J4: 202605 | K4: 197 | L4: 2025-09-20 | M4: 512 | N4: 瑜伽和普拉提 | O4: 常规瑜伽垫 | P4: 杜 娟 | R4: 716.8 | S4: OA 90 DAYS | T4: 0 | U4: 5.02 | V4: 0 | W4: 8.6 | X4: 698.93 | Y4: 0 | Z4: 0 | AA4: -13.62 | AB4: 0 | AC4: 0 | AD4: 0 | AE4: 0 | AF4: 0 | AG4: 0 | AH4: -93.91 | AI4: 4710.4 | AJ4: 541.9 | AK4: 23.55 | AL4: 626.87 | AM4: 0.1301 | AN4: -4226.64 | AO4: 波兰749 | AP4: PO-YP1001-001 | AQ4: 202602 | AR4: 709.7115 | AS4: 办公室 | AT4: 瑜伽垫 | AU4: 常规瑜伽垫 | AV4: =IF(ISNUMBER(MATCH(C4,畅想结算中心!$A$2:$A$436,0)),"有","无") -> 有
A5: 王柯飞 | B5: 昊特赛八公司 | C5: HSA25J001-3 | D5: HSA25J001-1 | E5: LPP | F5: 主动开发 | G5: 2025-08-04 | H5: 2026-02-17 | I5: 2 | J5: 202605 | K5: 197 | L5: 2025-09-20 | M5: 1010 | N5: 力量训练 | O5: 哑铃 | P5: 杜 娟 | R5: 1939.2 | S5: OA 90 DAYS | T5: 0 | U5: 13.57 | V5: 0 | W5: 23.27 | X5: 1890.86 | Y5: 0 | Z5: 0 | AA5: -36.85 | AB5: 0 | AC5: 0 | AD5: 0 | AE5: 0 | AF5: 0 | AG5: 0 | AH5: -254.07 | AI5: 13938 | AJ5: 1603.49 | AK5: 69.69 | AL5: 632.71 | AM5: 0.0485 | AN5: -12497.8 | AO5: 波兰749 | AP5: PO-ST3001-002 | AQ5: 202602 | AR5: 862.8388 | AS5: 办公室 | AT5: 哑铃及哑铃凳 | AU5: 哑铃 | AV5: =IF(ISNUMBER(MATCH(C5,畅想结算中心!$A$2:$A$436,0)),"有","无") -> 有
A6: 王柯飞 | B6: 昊特赛八公司 | C6: HSA25J001-3 | D6: HSA25J001-1 | E6: LPP | F6: 主动开发 | G6: 2025-08-04 | H6: 2026-02-17 | I6: 2 | J6: 202605 | K6: 197 | L6: 2025-09-20 | M6: 1008 | N6: 力量训练 | O6: 哑铃 | P6: 杜 娟 | R6: 1008 | S6: OA 90 DAYS | T6: 0 | U6: 7.06 | V6: 0 | W6: 12.1 | X6: 982.87 | Y6: 0 | Z6: 0 | AA6: -19.15 | AB6: 0 | AC6: 0 | AD6: 0 | AE6: 0 | AF6: 0 | AG6: 0 | AH6: -132.03 | AI6: 6955.2 | AJ6: 800.16 | AK6: 34.78 | AL6: 586.77 | AM6: 0.0866 | AN6: -6238.47 | AO6: 波兰749 | AP6: PO-ST3001-001 | AQ6: 202602 | AR6: 704.9755 | AS6: 办公室 | AT6: 哑铃及哑铃凳 | AU6: 哑铃 | AV6: =IF(ISNUMBER(MATCH(C6,畅想结算中心!$A$2:$A$436,0)),"有","无") -> 有
A7: 王柯飞 | B7: 昊特赛八公司 | C7: HSA25J001-3 | D7: HSA25J001-1 | E7: LPP | F7: 主动开发 | G7: 2025-08-04 | H7: 2026-02-17 | I7: 2 | J7: 202605 | K7: 197 | L7: 2025-09-20 | M7: 512 | N7: 瑜伽和普拉提 | O7: 常规瑜伽垫 | P7: 杜 娟 | R7: 716.8 | S7: OA 90 DAYS | T7: 0 | U7: 5.02 | V7: 0 | W7: 8.6 | X7: 698.93 | Y7: 0 | Z7: 0 | AA7: -13.62 | AB7: 0 | AC7: 0 | AD7: 0 | AE7: 0 | AF7: 0 | AG7: 0 | AH7: -93.91 | AI7: 4710.4 | AJ7: 541.9 | AK7: 23.55 | AL7: 626.87 | AM7: 0.1301 | AN7: -4226.64 | AO7: 波兰749 | AP7: PO-YP1001-003 | AQ7: 202602 | AR7: 709.7115 | AS7: 办公室 | AT7: 瑜伽垫 | AU7: 常规瑜伽垫 | AV7: =IF(ISNUMBER(MATCH(C7,畅想结算中心!$A$2:$A$436,0)),"有","无") -> 有
A8: 王柯飞 | B8: 昊特赛八公司 | C8: HSA25J001-3 | D8: HSA25J001-1 | E8: LPP | F8: 主动开发 | G8: 2025-08-04 | H8: 2026-02-17 | I8: 2 | J8: 202605 | K8: 197 | L8: 2025-09-20 | M8: 1008 | N8: 瑜伽和普拉提 | O8: 常规瑜伽砖 | P8: 杜 娟 | R8: 786.24 | S8: OA 90 DAYS | T8: 0 | U8: 5.5 | V8: 0 | W8: 9.44 | X8: 766.64 | Y8: 0 | Z8: 0 | AA8: -14.94 | AB8: 0 | AC8: 0 | AD8: 0 | AE8: 0 | AF8: 0 | AG8: 0 | AH8: -103.01 | AI8: 5040 | AJ8: 579.82 | AK8: 25.2 | AL8: 800.38 | AM8: 0.1514 | AN8: -4523.32 | AO8: 波兰749 | AP8: PO-YP2001-001 | AQ8: 202602 | AR8: 890.6618 | AS8: 办公室 | AT8: 瑜伽砖 | AU8: 常规瑜伽砖 | AV8: =IF(ISNUMBER(MATCH(C8,畅想结算中心!$A$2:$A$436,0)),"有","无") -> 有
A9: 王柯飞 | B9: 昊特赛八公司 | C9: HSA25J001-3 | D9: HSA25J001-1 | E9: LPP | F9: 主动开发 | G9: 2025-08-04 | H9: 2026-02-17 | I9: 2 | J9: 202605 | K9: 197 | L9: 2025-09-20 | M9: 512 | N9: 瑜伽和普拉提 | O9: 常规瑜伽垫 | P9: 杜 娟 | R9: 716.8 | S9: OA 90 DAYS | T9: 0 | U9: 5.02 | V9: 0 | W9: 8.6 | X9: 698.93 | Y9: 0 | Z9: 0 | AA9: -13.62 | AB9: 0 | AC9: 0 | AD9: 0 | AE9: 0 | AF9: 0 | AG9: 0 | AH9: -93.91 | AI9: 4710.4 | AJ9: 541.9 | AK9: 23.55 | AL9: 626.87 | AM9: 0.1301 | AN9: -4226.64 | AO9: 波兰749 | AP9: PO-YP1001-002 | AQ9: 202602 | AR9: 709.7115 | AS9: 办公室 | AT9: 瑜伽垫 | AU9: 常规瑜伽垫 | AV9: =IF(ISNUMBER(MATCH(C9,畅想结算中心!$A$2:$A$436,0)),"有","无") -> 有
A10: 王柯飞 | B10: 昊特赛八公司 | C10: HSA25J001-3 | D10: HSA25J013 | E10: LPP | F10: 主动开发 | G10: 2025-12-17 | H10: 2026-02-17 | I10: 2 | J10: 202605 | K10: 62 | L10: 2026-01-06 | M10: 1008 | N10: 装饰照明 | O10: 太阳能灯串 | P10: 杜 娟 | R10: 1764 | S10: OA 90 DAYS | T10: 0 | U10: 12.35 | V10: 0 | W10: 21.17 | X10: 1720.03 | Y10: 0 | Z10: 0 | AA10: -33.52 | AB10: 0 | AC10: 0 | AD10: 0 | AE10: 0 | AF10: 0 | AG10: 0 | AH10: -231.11 | AI10: 11088 | AJ10: 1275.61 | AK10: 110.88 | AL10: 1935.82 | AM10: 0.1632 | AN10: -10008.41 | AO10: 波兰749 | AP10: PO-GS1001-001 | AQ10: 202602 | AR10: 2192.5933 | AS10: 办公室 | AT10: 节日灯 | AU10: 太阳能灯串 | AV10: =IF(ISNUMBER(MATCH(C10,畅想结算中心!$A$2:$A$436,0)),"有","无") -> 有
A11: 王柯飞 | B11: 昊特赛八公司 | C11: HSA25J004-2 | D11: HSA25J004 | E11: LPP | F11: 主动开发 | G11: 2025-10-27 | H11: 2026-02-27 | I11: 3 | J11: 202605 | K11: 123 | L11: 2025-12-26 | M11: 1008 | N11: 餐厨及户外家具 | O11: 庭院吊篮 | P11: 杜 娟 | R11: 3024 | S11: OA 90 DAYS | T11: 0 | U11: 21.17 | V11: 0 | W11: 36.29 | X11: 2927.61 | Y11: 0 | Z11: 0 | AA11: -57.46 | AB11: 757.83 | AC11: 0 | AD11: 0 | AE11: 0 | AF11: 0 | AG11: 0 | AH11: -393.35 | AI11: 18144 | AJ11: 2087.36 | AK11: 90.72 | AL11: 3136.06 | AM11: 0.1565 | AN11: -17050.1 | AO11: 波兰749 | AP11: PO-OF5001-001 | AQ11: 202602 | AR11: 3475.2115 | AS11: 办公室 | AT11: 户外沙发及吊床 | AU11: 庭院吊篮 | AV11: =IF(ISNUMBER(MATCH(C11,畅想结算中心!$A$2:$A$436,0)),"有","无") -> 有
A12: 蔡载君 | B12: 昊特赛八公司 | C12: HSA25J004-2 | D12: HSG26E002 | E12: LPP | F12: 主动开发 | G12: 2026-01-23 | H12: 2026-02-27 | I12: 3 | J12: 202605 | K12: 35 | L12: 2026-02-23 | M12: 1000 | N12: 商务礼品 | O12: 水晶工艺品 | P12: 蔡载君 | R12: 860 | S12: OA 90 DAYS | T12: 0 | U12: 6.02 | V12: 0 | W12: 10.32 | X12: 832.59 | Y12: 0 | Z12: 0 | AA12: -16.34 | AB12: 8.21 | AC12: 0 | AD12: 0 | AE12: 0 | AF12: 0 | AG12: 0 | AH12: -111.86 | AI12: 6103 | AJ12: 486.08 | AK12: 122.06 | AL12: -47.62 | AM12: -0.0084 | AN12: -5788.41 | AO12: 波兰749 | AP12: CR037 | AQ12: 202602 | AR12: 145.0894 | AS12: 办公室 | AT12: 工艺品 | AU12: 水晶工艺品 | AV12: =IF(ISNUMBER(MATCH(C12,畅想结算中心!$A$2:$A$436,0)),"有","无") -> 有
A13: 王柯飞 | B13: 昊特赛八公司 | C13: HSA25J004-3 | D13: HSA25J001-1 | E13: LPP | F13: 主动开发 | G13: 2025-08-04 | H13: 2026-03-07 | I13: 3 | J13: 202606 | K13: 215 | L13: 2025-09-20 | M13: 1050 | N13: 其他运动用品 | O13: 弹力带 | P13: 杜 娟 | R13: 892.5 | S13: OA 90 DAYS | T13: 0 | U13: 6.25 | V13: 0 | W13: 10.71 | X13: 869.77 | Y13: 0 | Z13: 0 | AA13: -16.96 | AB13: 45.58 | AC13: 0 | AD13: 0 | AE13: 0 | AF13: 0 | AG13: 0 | AH13: -116.92 | AI13: 5880 | AJ13: 676.46 | AK13: 29.4 | AL13: 717.68 | AM13: 0.1197 | AN13: -5321.58 | AO13: 波兰749 | AP13: PO-OSP2001-002 | AQ13: 202603 | AR13: 820.9137 | AS13: 办公室 | AT13: 伸展训练 | AU13: 弹力带 | AV13: =IF(ISNUMBER(MATCH(C13,畅想结算中心!$A$2:$A$436,0)),"有","无") -> 有
... A55: 蔡载君 | B55: 昊特赛八公司 | C55: HSG26E004-2 | D55: HSG26E004 | E55: LPP | F55: 主动开发 | G55: 2026-03-26 | H55: 2026-05-23 | I55: 5 | J55: 202606 | K55: 58 | L55: 2026-11-02 | M55: 800 | N55: 综合运动 | O55: 哑铃 | P55: 陈依萍 | R55: 768 | S55: OA 90 DAYS | T55: 0 | U55: 5.38 | V55: 0 | W55: 9.22 | X55: 742.7 | Y55: 0 | Z55: 0 | AA55: -14.59 | AB55: 120.89 | AC55: 0 | AD55: 0 | AE55: 0 | AF55: 0 | AG55: 0 | AH55: -99.04 | AI55: 5040 | AJ55: 579.82 | AK55: 100.8 | AL55: 359.73 | AM55: 0.0714 | AN55: -4718.37 | AO55: 波兰749 | AP55: PO-ST3001-001 | AQ55: 202605 | AR55: 523.1158 | AS55: 办公室 | AT55: 无氧器械 | AU55: 哑铃 | AV55: =IF(ISNUMBER(MATCH(C55,畅想结算中心!$A$2:$A$436,0)),"有","无") -> 有
A56: 蔡载君 | B56: 昊特赛八公司 | C56: HSG26E004-3 | D56: HSG26E004 | E56: LPP | F56: 主动开发 | G56: 2026-03-26 | H56: 2026-05-28 | I56: 6 | K56: 63 | L56: 2026-11-02 | M56: 1200 | N56: 综合运动 | O56: 哑铃 | P56: 陈依萍 | R56: 1152 | S56: OA 90 DAYS | T56: 0 | U56: 8.06 | V56: 0 | W56: 13.82 | X56: 1115.61 | Y56: 0 | Z56: 0 | AA56: -21.89 | AB56: 131.77 | AC56: 0 | AD56: 0 | AE56: 0 | AF56: 0 | AG56: 0 | AH56: -148.19 | AI56: 7560 | AJ56: 869.73 | AK56: 151.2 | AL56: 579.34 | AM56: 0.0767 | AN56: -7027.82 | AO56: 波兰749 | AP56: PO-ST3001-001 | AQ56: 202605 | AR56: 824.1647 | AS56: 客户第一组 | AT56: 无氧器械 | AU56: 哑铃 | AV56: =IF(ISNUMBER(MATCH(C56,畅想结算中心!$A$2:$A$436,0)),"有","无") -> 有
A57: 蔡载君 | B57: 昊特赛八公司 | C57: HSG26E004-3 | D57: HSG26E004 | E57: LPP | F57: 主动开发 | G57: 2026-03-26 | H57: 2026-05-28 | I57: 6 | K57: 63 | L57: 2026-11-02 | M57: 1500 | N57: 综合运动 | O57: 哑铃 | P57: 陈依萍 | R57: 2820 | S57: OA 90 DAYS | T57: 0 | U57: 19.74 | V57: 0 | W57: 33.84 | X57: 2730.93 | Y57: 0 | Z57: 0 | AA57: -53.57 | AB57: 329.41 | AC57: 0 | AD57: 0 | AE57: 0 | AF57: 0 | AG57: 0 | AH57: -362.66 | AI57: 18900 | AJ57: 2174.34 | AK57: 378 | AL57: 1055.05 | AM57: 0.0571 | AN57: -17566.7 | AO57: 波兰749 | AP57: PO-ST3001-002 | AQ57: 202605 | AR57: 1662.0707 | AS57: 客户第一组 | AT57: 无氧器械 | AU57: 哑铃 | AV57: =IF(ISNUMBER(MATCH(C57,畅想结算中心!$A$2:$A$436,0)),"有","无") -> 有
A58: 蔡载君 | B58: 昊特赛八公司 | C58: HSG26E004-4 | D58: HSG26E003 | E58: LPP | F58: 主动开发 | G58: 2026-03-25 | H58: 2026-05-28 | I58: 6 | K58: 64 | L58: 2026-09-28 | M58: 1200 | N58: 瑜伽和普拉提 | O58: 瑜伽负重袋 | P58: 陈依萍 | R58: 2076 | S58: OA 90 DAYS | T58: 0 | U58: 14.53 | V58: 0 | W58: 24.91 | X58: 2021.55 | Y58: 0 | Z58: 0 | AA58: -39.45 | AB58: 273.16 | AC58: 0 | AD58: 0 | AE58: 0 | AF58: 0 | AG58: 0 | AH58: -267.07 | AI58: 12720 | AJ58: 1463.36 | AK58: 63.6 | AL58: 2092.29 | AM58: 0.1529 | AN58: -11691.78 | AO58: 波兰749 | AP58: PO-YP6001-002 | AQ58: 202605 | AR58: 2324.5306 | AS58: 客户第一组 | AT58: 其他瑜伽和普拉提用品 | AU58: 瑜伽负重袋 | AV58: =IF(ISNUMBER(MATCH(C58,畅想结算中心!$A$2:$A$436,0)),"有","无") -> 有
A59: 蔡载君 | B59: 昊特赛八公司 | C59: HSG26E004-4 | D59: HSG26E004 | E59: LPP | F59: 主动开发 | G59: 2026-03-26 | H59: 2026-05-28 | I59: 6 | K59: 63 | L59: 2026-11-02 | M59: 1008 | N59: 瑜伽平衡 | O59: 常规瑜伽砖 | P59: 陈依萍 | R59: 735.84 | S59: OA 90 DAYS | T59: 0 | U59: 5.15 | V59: 0 | W59: 8.83 | X59: 716.54 | Y59: 0 | Z59: 0 | AA59: -13.98 | AB59: 281.9 | AC59: 0 | AD59: 0 | AE59: 0 | AF59: 0 | AG59: 0 | AH59: -94.64 | AI59: 4636.8 | AJ59: 533.44 | AK59: 23.18 | AL59: 442.46 | AM59: 0.0912 | AN59: -4443.32 | AO59: 波兰749 | AP59: PO-YP2001-001 | AQ59: 202605 | AR59: 525.4166 | AS59: 客户第一组 | AT59: 训练器材 | AU59: 常规瑜伽砖 | AV59: =IF(ISNUMBER(MATCH(C59,畅想结算中心!$A$2:$A$436,0)),"有","无") -> 有
A60: 蔡载君 | B60: 昊特赛八公司 | C60: HSG26E004-4 | D60: HSG26E004 | E60: LPP | F60: 主动开发 | G60: 2026-03-26 | H60: 2026-05-28 | I60: 6 | K60: 63 | L60: 2026-11-02 | M60: 1504 | N60: 瑜伽平衡 | O60: 常规瑜伽垫 | P60: 陈依萍 | R60: 2015.36 | S60: OA 90 DAYS | T60: 0 | U60: 14.11 | V60: 0 | W60: 24.19 | X60: 1962.5 | Y60: 0 | Z60: 0 | AA60: -38.29 | AB60: 932.94 | AC60: 0 | AD60: 0 | AE60: 0 | AF60: 0 | AG60: 0 | AH60: -259.22 | AI60: 13836.8 | AJ60: 1591.84 | AK60: 69.18 | AL60: 38.85 | AM60: 0.0029 | AN60: -13342.58 | AO60: 波兰749 | AP60: PO-YP1001-001 | AQ60: 202605 | AR60: 271.7303 | AS60: 客户第一组 | AT60: 训练器材 | AU60: 常规瑜伽垫 | AV60: =IF(ISNUMBER(MATCH(C60,畅想结算中心!$A$2:$A$436,0)),"有","无") -> 有
A61: 蔡载君 | B61: 昊特赛八公司 | C61: HSG26E004-4 | D61: HSG26E004 | E61: LPP | F61: 主动开发 | G61: 2026-03-26 | H61: 2026-05-28 | I61: 6 | K61: 63 | L61: 2026-11-02 | M61: 810 | N61: 瑜伽平衡 | O61: 常规平衡垫 | P61: 陈依萍 | R61: 1449.9 | S61: OA 90 DAYS | T61: 0 | U61: 10.15 | V61: 0 | W61: 17.4 | X61: 1411.87 | Y61: 0 | Z61: 0 | AA61: -27.55 | AB61: 476.94 | AC61: 0 | AD61: 0 | AE61: 0 | AF61: 0 | AG61: 0 | AH61: -186.51 | AI61: 9963 | AJ61: 1146.19 | AK61: 49.81 | AL61: 214.65 | AM61: 0.0225 | AN61: -9412.28 | AO61: 波兰749 | AP61: PO-BT3001-001 | AQ61: 202605 | AR61: 382.2602 | AS61: 客户第一组 | AT61: 训练器材 | AU61: 常规瑜伽垫 | AV61: =IF(ISNUMBER(MATCH(C61,畅想结算中心!$A$2:$A$436,0)),"有","无") -> 有
A62: 蔡载君 | B62: 昊特赛八公司 | C62: HSG26E004-4 | D62: HSG26E004 | E62: LPP | F62: 主动开发 | G62: 2026-03-26 | H62: 2026-05-28 | I62: 6 | K62: 63 | L62: 2026-11-02 | M62: 800 | N62: 综合运动 | O62: 弹力带 | P62: 陈依萍 | R62: 640 | S62: OA 90 DAYS | T62: 0 | U62: 4.48 | V62: 0 | W62: 7.68 | X62: 623.21 | Y62: 0 | Z62: 0 | AA62: -12.16 | AB62: 35.06 | AC62: 0 | AD62: 0 | AE62: 0 | AF62: 0 | AG62: 0 | AH62: -82.32 | AI62: 4000 | AJ62: 460.18 | AK62: 20 | AL62: 624.19 | AM62: 0.1479 | AN62: -3625.21 | AO62: 波兰749 | AP62: PO-OSP2001-002 | AQ62: 202605 | AR62: 696.1834 | AS62: 客户第一组 | AT62: 其他体育用品 | AU62: 弹力带 | AV62: =IF(ISNUMBER(MATCH(C62,畅想结算中心!$A$2:$A$436,0)),"有","无") -> 有
A63: 李欣然 | B63: 昊特赛二公司 | C63: HSB25E023-1 | D63: HSB25E023 | E63: RMS | F63: 主动开发 | G63: 2025-10-15 | H63: 2026-01-13 | I63: 1 | J63: 202605 | K63: 90 | L63: 2025-11-15 | M63: 3900 | N63: 手工艺品及DIY玩具 | O63: 其他常规DIY玩具 | P63: 叶柳涵 | R63: 3120 | S63: OA 60DAYS | T63: 0 | U63: 21.84 | V63: 0 | W63: 18.72 | X63: 3029.44 | Y63: 0 | Z63: 0 | AA63: -40.56 | AB63: 0 | AC63: 0 | AD63: 0 | AE63: 0 | AF63: 0 | AG63: 0 | AH63: -282.44 | AI63: 19968 | AJ63: 2297.2 | AK63: 399.36 | AL63: 3025.65 | AM63: 0.1434 | AN63: -18222.24 | AO63: 英国2962 | AP63: OD273-CN001 | AQ63: 202601 | AR63: 3555.3705 | AS63: 客户第一组 | AT63: 创意类及材料包 | AU63: 其他常规DIY玩具 | AV63: =IF(ISNUMBER(MATCH(C63,畅想结算中心!$A$2:$A$436,0)),"有","无") -> 有
A64: 李欣然 | B64: 昊特赛二公司 | C64: HSB25E023-2 | D64: HSB25E023 | E64: RMS | F64: 主动开发 | G64: 2025-10-15 | H64: 2026-01-13 | I64: 1 | K64: 90 | L64: 2025-11-15 | M64: 6762 | N64: 手工艺品及DIY玩具 | O64: 其他常规DIY玩具 | P64: 叶柳涵 | R64: 5409.6 | S64: OA 60DAYS | T64: 0 | U64: 37.87 | V64: 108.19 | W64: 32.46 | X64: 5181.08 | Y64: 0 | Z64: 0 | AA64: -178.52 | AB64: 0 | AC64: 0 | AD64: 0 | AE64: 0 | AF64: 0 | AG64: 0 | AH64: -1243.14 | AI64: 34621.44 | AJ64: 3983 | AK64: 692.43 | AL64: 4748.1 | AM64: 0.1316 | AN64: -32347.98 | AO64: 英国2962 | AP64: OD273-CN001 | AQ64: 202601 | AR64: 5666.5646 | AS64: 客户第一组 | AT64: 创意类及材料包 | AU64: 其他常规DIY玩具 | AV64: =IF(ISNUMBER(MATCH(C64,畅想结算中心!$A$2:$A$436,0)),"有","无") -> 有
A65: 李欣然 | B65: 昊特赛二公司 | C65: HSB25E023-3 | D65: HSB25E023 | E65: RMS | F65: 主动开发 | G65: 2025-10-15 | H65: 2026-01-13 | I65: 1 | J65: 202605 | K65: 90 | L65: 2025-11-15 | M65: 4482 | N65: 手工艺品及DIY玩具 | O65: 其他常规DIY玩具 | P65: 叶柳涵 | R65: 3585.6 | S65: OA 60DAYS | T65: 0 | U65: 25.1 | V65: 0 | W65: 21.51 | X65: 3488.99 | Y65: 0 | Z65: 0 | AA65: -46.61 | AB65: 0 | AC65: 0 | AD65: 0 | AE65: 0 | AF65: 0 | AG65: 0 | AH65: -324.57 | AI65: 22947.84 | AJ65: 2640.02 | AK65: 458.96 | AL65: 3529.15 | AM65: 0.1453 | AN65: -20941.57 | AO65: 英国2962 | AP65: OD273-CN001 | AQ65: 202601 | AR65: 4137.8948 | AS65: 客户第一组 | AT65: 创意类及材料包 | AU65: 其他常规DIY玩具 | AV65: =IF(ISNUMBER(MATCH(C65,畅想结算中心!$A$2:$A$436,0)),"有","无") -> 有
A66: 李欣然 | B66: 昊特赛二公司 | C66: HSB25E023-4 | D66: HSB25E023 | E66: RMS | F66: 主动开发 | G66: 2025-10-15 | H66: 2026-01-13 | I66: 1 | J66: 202605 | K66: 90 | L66: 2025-11-15 | M66: 5448 | N66: 手工艺品及DIY玩具 | O66: 其他常规DIY玩具 | P66: 叶柳涵 | R66: 4358.4 | S66: OA 60DAYS | T66: 0 | U66: 30.51 | V66: 87.17 | W66: 26.15 | X66: 4164.57 | Y66: 0 | Z66: 0 | AA66: -143.83 | AB66: 0 | AC66: 0 | AD66: 0 | AE66: 0 | AF66: 0 | AG66: 0 | AH66: -1001.57 | AI66: 27893.76 | AJ66: 3209.02 | AK66: 557.88 | AL66: 3757.78 | AM66: 0.1296 | AN66: -26062.09 | AO66: 英国2962 | AP66: OD273-CN001 | AQ66: 202601 | AR66: 4497.7544 | AS66: 客户第一组 | AT66: 创意类及材料包 | AU66: 其他常规DIY玩具 | AV66: =IF(ISNUMBER(MATCH(C66,畅想结算中心!$A$2:$A$436,0)),"有","无") -> 有
A67: 李欣然 | B67: 昊特赛二公司 | C67: HSB25E023-5 | D67: HSB25E023 | E67: RMS | F67: 主动开发 | G67: 2025-10-15 | H67: 2026-01-13 | I67: 1 | J67: 202605 | K67: 90 | L67: 2025-11-15 | M67: 4182 | N67: 手工艺品及DIY玩具 | O67: 其他常规DIY玩具 | P67: 叶柳涵 | R67: 3345.6 | S67: OA 60DAYS | T67: 0 | U67: 23.42 | V67: 0 | W67: 20.07 | X67: 3252.11 | Y67: 0 | Z67: 0 | AA67: -43.49 | AB67: 0 | AC67: 0 | AD67: 0 | AE67: 0 | AF67: 0 | AG67: 0 | AH67: -302.85 | AI67: 21411.84 | AJ67: 2463.31 | AK67: 428.24 | AL67: 3269.62 | AM67: 0.1444 | AN67: -19539.86 | AO67: 英国2962 | AP67: OD273-CN001 | AQ67: 202601 | AR67: 3837.6216 | AS67: 客户第一组 | AT67: 创意类及材料包 | AU67: 其他常规DIY玩具 | AV67: =IF(ISNUMBER(MATCH(C67,畅想结算中心!$A$2:$A$436,0)),"有","无") -> 有
A68: 李欣然 | B68: 昊特赛二公司 | C68: HSB25E023-6 | D68: HSB25E023 | E68: RMS | F68: 主动开发 | G68: 2025-10-15 | H68: 2026-01-13 | I68: 1 | J68: 202605 | K68: 90 | L68: 2025-11-15 | M68: 5226 | N68: 手工艺品及DIY玩具 | O68: 其他常规DIY玩具 | P68: 叶柳涵 | R68: 4180.8 | S68: OA 60DAYS | T68: 0 | U68: 29.27 | V68: 0 | W68: 25.08 | X68: 4076.45 | Y68: 0 | Z68: 0 | AA68: -54.35 | AB68: 0 | AC68: 0 | AD68: 0 | AE68: 0 | AF68: 0 | AG68: 0 | AH68: -378.47 | AI68: 26757.12 | AJ68: 3078.25 | AK68: 535.14 | AL68: 4172.76 | AM68: 0.147 | AN68: -24417.83 | AO68: 英国2962 | AP68: OD273-CN001 | AQ68: 202601 | AR68: 4882.547 | AS68: 客户第一组 | AT68: 创意类及材料包 | AU68: 其他常规DIY玩具 | AV68: =IF(ISNUMBER(MATCH(C68,畅想结算中心!$A$2:$A$436,0)),"有","无") -> 有
A69: 李雅婷 | B69: 昊特赛二公司 | C69: HSB25M024-1 | D69: HSB25M024 | E69: RMS | F69: 主动开发 | G69: 2025-10-21 | H69: 2026-01-22 | I69: 1 | J69: 202605 | K69: 93 | L69: 2025-12-09 | M69: 333 | N69: 经典玩具 | O69: 常规发光玩具 | P69: 叶柳涵 | R69: 606.06 | S69: OA 60DAYS | T69: 0 | U69: 4.24 | V69: 0 | W69: 3.64 | X69: 548.18 | Y69: 0 | Z69: 0 | AA69: -7.88 | AB69: 1300 | AC69: 0 | AD69: 0 | AE69: 0 | AF69: 0 | AG69: 0 | AH69: -54.77 | AI69: 4195.8 | AJ69: 482.7 | AK69: 83.92 | AL69: -1286.73 | AM69: -0.3377 | AN69: -5126.49 | AO69: 英国2962 | AP69: LT035-led-1 | AQ69: 202601 | AR69: -1177.5068 | AS69: 办公室 | AT69: 发光玩具 | AU69: 常规发光玩具 | AV69: =IF(ISNUMBER(MATCH(C69,畅想结算中心!$A$2:$A$436,0)),"有","无") -> 有
A70: 李雅婷 | B70: 昊特赛二公司 | C70: HSB25M024-10 | D70: HSB25M024 | E70: RMS | F70: 主动开发 | G70: 2025-10-21 | H70: 2026-01-15 | I70: 1 | J70: 202605 | K70: 86 | L70: 2025-12-09 | M70: 1272 | N70: 运动休闲包 | O70: 常规沙滩包 | P70: 叶柳涵 | R70: 4833.6 | S70: OA 60DAYS | T70: 0 | U70: 33.84 | V70: 96.67 | W70: 29 | X70: 4627.7 | Y70: 0 | Z70: 0 | AA70: -159.51 | AB70: 2501.46 | AC70: 0 | AD70: 0 | AE70: 0 | AF70: 0 | AG70: 0 | AH70: -1109.74 | AI70: 31800 | AJ70: 3658.41 | AK70: 636 | AL70: 916.78 | AM70: 0.0285 | AN70: -32187.02 | AO70: 英国2962 | AP70: BB001-STB-1 | AQ70: 202601 | AR70: 1754.5429 | AS70: 办公室 | AT70: 沙滩包 | AU70: 常规沙滩包 | AV70: =IF(ISNUMBER(MATCH(C70,畅想结算中心!$A$2:$A$436,0)),"有","无") -> 有
A71: 李雅婷 | B71: 昊特赛二公司 | C71: HSB25M024-10 | D71: HSB25M024 | E71: RMS | F71: 主动开发 | G71: 2025-10-21 | H71: 2026-01-15 | I71: 1 | J71: 202605 | K71: 86 | L71: 2025-12-09 | M71: 2352 | N71: 装扮玩具 | O71: 其他常规装扮玩具 | P71: 叶柳涵 | R71: 376.32 | S71: OA 60DAYS | T71: 0 | U71: 2.63 | V71: 7.53 | W71: 2.26 | X71: 360.29 | Y71: 0 | Z71: 0 | AA71: -12.42 | AB71: 98.54 | AC71: 0 | AD71: 0 | AE71: 0 | AF71: 0 | AG71: 0 | AH71: -86.41 | AI71: 2916.48 | AJ71: 335.52 | AK71: 58.33 | AL71: -231.22 | AM71: -0.0922 | AN71: -2808.52 | AO71: 英国2962 | AP71: 0D322-PS001 | AQ71: 202601 | AR71: -157.1655 | AS71: 办公室 | AT71: 其他装扮玩具 | AU71: 其他常规装扮玩具 | AV71: =IF(ISNUMBER(MATCH(C71,畅想结算中心!$A$2:$A$436,0)),"有","无") -> 有
A72: 李雅婷 | B72: 昊特赛二公司 | C72: HSB25M024-11 | D72: HSB25M024 | E72: RMS | F72: 主动开发 | G72: 2025-10-21 | H72: 2026-01-17 | I72: 1 | J72: 202605 | K72: 88 | L72: 2025-12-09 | M72: 2400 | N72: 装扮玩具 | O72: 其他常规装扮玩具 | P72: 叶柳涵 | R72: 384 | S72: OA 60DAYS | T72: 0 | U72: 2.69 | V72: 11.52 | W72: 2.3 | X72: 363.7 | Y72: 0 | Z72: 0 | AA72: -16.51 | AB72: 119.48 | AC72: 0 | AD72: 0 | AE72: 0 | AF72: 0 | AG72: 0 | AH72: -114.93 | AI72: 2976 | AJ72: 342.37 | AK72: 59.52 | AL72: -280.81 | AM72: -0.1109 | AN72: -2911.54 | AO72: 英国2962 | AP72: 0D322-PS001 | AQ72: 202601 | AR72: -205.2761 | AS72: 办公室 | AT72: 其他装扮玩具 | AU72: 其他常规装扮玩具 | AV72: =IF(ISNUMBER(MATCH(C72,畅想结算中心!$A$2:$A$436,0)),"有","无") -> 有
A73: 李雅婷 | B73: 昊特赛二公司 | C73: HSB25M024-11 | D73: HSB25M024 | E73: RMS | F73: 主动开发 | G73: 2025-10-21 | H73: 2026-01-17 | I73: 1 | J73: 202605 | K73: 88 | L73: 2025-12-09 | M73: 1232 | N73: 运动休闲包 | O73: 常规沙滩包 | P73: 叶柳涵 | R73: 4681.6 | S73: OA 60DAYS | T73: 0 | U73: 32.77 | V73: 140.45 | W73: 28.09 | X73: 4434.08 | Y73: 0 | Z73: 0 | AA73: -201.31 | AB73: 2880.52 | AC73: 0 | AD73: 0 | AE73: 0 | AF73: 0 | AG73: 0 | AH73: -1401.38 | AI73: 30800 | AJ73: 3543.36 | AK73: 616 | AL73: 113.81 | AM73: 0.0037 | AN73: -31959 | AO73: 英国2962 | AP73: BB001-STB-1 | AQ73: 202601 | AR73: 925.3504 | AS73: 办公室 | AT73: 沙滩包 | AU73: 常规沙滩包 | AV73: =IF(ISNUMBER(MATCH(C73,畅想结算中心!$A$2:$A$436,0)),"有","无") -> 有
A74: 李雅婷 | B74: 昊特赛二公司 | C74: HSB25M024-2 | D74: HSB25M024 | E74: RMS | F74: 主动开发 | G74: 2025-10-21 | H74: 2026-01-14 | I74: 1 | J74: 202605 | K74: 85 | L74: 2025-12-09 | M74: 2020 | N74: 装扮玩具 | O74: 常规工具玩具 | P74: 叶柳涵 | R74: 1616 | S74: OA 60DAYS | T74: 0 | U74: 11.31 | V74: 0 | W74: 9.7 | X74: 1585.57 | Y74: 0 | Z74: 0 | AA74: -21.01 | AB74: 1090.17 | AC74: 0 | AD74: 0 | AE74: 0 | AF74: 0 | AG74: 0 | AH74: -146.36 | AI74: 9898 | AJ74: 1138.71 | AK74: 197.96 | AL74: 997.81 | AM74: 0.0903 | AN74: -10126.23 | AO74: 英国2962 | AP74: TT003-FJWJ001 | AQ74: 202601 | AR74: 1263.3453 | AS74: 办公室 | AT74: 工具玩具 | AU74: 常规工具玩具 | AV74: =IF(ISNUMBER(MATCH(C74,畅想结算中心!$A$2:$A$436,0)),"有","无") -> 有
A75: 李雅婷 | B75: 昊特赛二公司 | C75: HSB25M024-2 | D75: HSB25M024 | E75: RMS | F75: 主动开发 | G75: 2025-10-21 | H75: 2026-01-14 | I75: 1 | J75: 202605 | K75: 85 | L75: 2025-12-09 | M75: 888 | N75: 游泳装备 | O75: 游泳圈 | P75: 叶柳涵 | R75: 1864.8 | S75: OA 60DAYS | T75: 0 | U75: 13.05 | V75: 0 | W75: 11.19 | X75: 1829.69 | Y75: 0 | Z75: 0 | AA75: -24.24 | AB75: 277.62 | AC75: 0 | AD75: 0 | AE75: 0 | AF75: 0 | AG75: 0 | AH75: -168.86 | AI75: 10656 | AJ75: 1225.91 | AK75: 213.12 | AL75: 2824.98 | AM75: 0.2216 | AN75: -10011.76 | AO75: 英国2962 | AP75: ST047-YQ-1 | AQ75: 202601 | AR75: 3115.98 | AS75: 办公室 | AT75: 游泳训练器材 | AU75: 游泳圈 | AV75: =IF(ISNUMBER(MATCH(C75,畅想结算中心!$A$2:$A$436,0)),"有","无") -> 有
A76: 李雅婷 | B76: 昊特赛二公司 | C76: HSB25M024-2 | D76: HSB25M024 | E76: RMS | F76: 主动开发 | G76: 2025-10-21 | H76: 2026-01-14 | I76: 1 | J76: 202605 | K76: 85 | L76: 2025-12-09 | M76: 444 | N76: 游泳装备 | O76: 游泳圈 | P76: 叶柳涵 | R76: 2264.4 | S76: OA 60DAYS | T76: 0 | U76: 15.85 | V76: 0 | W76: 13.59 | X76: 2221.76 | Y76: 0 | Z76: 0 | AA76: -29.44 | AB76: 330.04 | AC76: 0 | AD76: 0 | AE76: 0 | AF76: 0 | AG76: 0 | AH76: -205.08 | AI76: 12432 | AJ76: 1430.23 | AK76: 248.64 | AL76: 3896.55 | AM76: 0.2518 | AN76: -11690.87 | AO76: 英国2962 | AP76: ST049-YQ-2 | AQ76: 202601 | AR76: 4239.86 | AS76: 办公室 | AT76: 游泳训练器材 | AU76: 游泳圈 | AV76: =IF(ISNUMBER(MATCH(C76,畅想结算中心!$A$2:$A$436,0)),"有","无") -> 有
... A99: 窦宇佳 | B99: 昊特赛九公司 | C99: HSA25Y001-4 | D99: HSA25Y007 | E99: LPP | F99: 主动开发 | G99: 2025-10-29 | H99: 2026-01-29 | I99: 2 | J99: 202605 | K99: 92 | L99: 2026-03-27 | M99: 1008 | N99: DIY玩具 | O99: 其他DIY玩具 | P99: 李雅婷 | R99: 1108.8 | S99: OA 90 DAYS | T99: 0 | U99: 7.76 | V99: 0 | W99: 13.3 | X99: 1058.13 | Y99: 0 | Z99: 0 | AA99: -21.07 | AB99: 769.07 | AC99: 0 | AD99: 0 | AE99: 0 | AF99: 0 | AG99: 0 | AH99: -146.17 | AI99: 7358.4 | AJ99: 846.54 | AK99: 73.58 | AL99: -13.74 | AM99: -0.0019 | AN99: -7408.36 | AO99: 波兰749 | AP99: OC003-MQ-brown | AQ99: 202603 | AR99: 152.1137 | AS99: 客户第一组 | AT99: 其他DIY玩具 | AU99: 其他常规DIY玩具 | AV99: =IF(ISNUMBER(MATCH(C99,畅想结算中心!$A$2:$A$436,0)),"有","无") -> 有
A100: 王 晶 | B100: 昊特赛九公司 | C100: HSA25Y002-4 | D100: HSA25Y002 | E100: LPP | F100: 主动开发 | G100: 2025-12-19 | H100: 2026-02-09 | I100: 2 | K100: 52 | L100: 2026-01-16 | M100: 1008 | N100: 玩偶玩具 | O100: 方面包 | P100: 李雅婷 | R100: 1814.4 | S100: OA 90 DAYS | T100: 0 | U100: 12.7 | V100: 0 | W100: 21.77 | X100: 1729.93 | Y100: 0 | Z100: 0 | AA100: -34.47 | AB100: 1836.76 | AC100: 0 | AD100: 0 | AE100: 0 | AF100: 0 | AG100: 0 | AH100: -238.61 | AI100: 12821.76 | AJ100: 1475.07 | AK100: 128.22 | AL100: -1336.58 | AM100: -0.1116 | AN100: -13399.58 | AO100: 波兰749 | AP100: KB-DL200-122 | AQ100: 202602 | AR100: -1057.6574 | AS100: 客户第一组 | AT100: 布艺玩偶 | AU100: 常规布艺玩偶 | AV100: =IF(ISNUMBER(MATCH(C100,畅想结算中心!$A$2:$A$436,0)),"有","无") -> 有
A101: 王 晶 | B101: 昊特赛九公司 | C101: HSA25Y002-5 | D101: HSA25Y002 | E101: LPP | F101: 主动开发 | G101: 2025-12-19 | H101: 2026-03-10 | I101: 3 | K101: 81 | L101: 2026-01-16 | M101: 996 | N101: 玩偶玩具 | O101: 方面包 | P101: 李雅婷 | R101: 1792.8 | S101: OA 90 DAYS | T101: 0 | U101: 12.55 | V101: 0 | W101: 21.51 | X101: 1708.74 | Y101: 0 | Z101: 0 | AA101: -34.06 | AB101: 1452.14 | AC101: 0 | AD101: 0 | AE101: 0 | AF101: 0 | AG101: 0 | AH101: -234.01 | AI101: 12669.12 | AJ101: 1457.51 | AK101: 126.69 | AL101: -1050.37 | AM101: -0.0895 | AN101: -12876.67 | AO101: 波兰749 | AP101: KB-DL200-122 | AQ101: 202603 | AR101: -775.895 | AS101: 客户第一组 | AT101: 布艺玩偶 | AU101: 常规布艺玩偶 | AV101: =IF(ISNUMBER(MATCH(C101,畅想结算中心!$A$2:$A$436,0)),"有","无") -> 有
A102: 窦宇佳 | B102: 昊特赛九公司 | C102: HSA25Y007-3 | D102: HSA25Y007 | E102: LPP | F102: 主动开发 | G102: 2025-10-29 | H102: 2026-04-02 | I102: 4 | K102: 155 | L102: 2026-03-27 | M102: 984 | N102: DIY玩具 | O102: 其他DIY玩具 | P102: 李雅婷 | R102: 1082.4 | S102: OA 90 DAYS | T102: 0 | U102: 7.58 | V102: 0 | W102: 12.99 | X102: 1011.83 | Y102: 0 | Z102: 0 | AA102: -20.57 | AB102: 2017.28 | AC102: 0 | AD102: 0 | AE102: 0 | AF102: 0 | AG102: 0 | AH102: -141.39 | AI102: 7183.2 | AJ102: 826.39 | AK102: 71.83 | AL102: -1491.01 | AM102: -0.2144 | AN102: -8498.03 | AO102: 波兰749 | AP102: OC003-MQ-brown | AQ102: 202604 | AR102: -1329.8914 | AS102: 办公室 | AT102: 其他DIY玩具 | AU102: 其他常规DIY玩具 | AV102: =IF(ISNUMBER(MATCH(C102,畅想结算中心!$A$2:$A$436,0)),"有","无") -> 有
A103: 窦宇佳 | B103: 昊特赛九公司 | C103: HSA25Y012 | D103: HSA25Y012 | E103: LPP | F103: 主动开发 | G103: 2025-11-18 | H103: 2026-05-05 | I103: 5 | K103: 168 | L103: 2026-03-20 | M103: 1008 | N103: 宠物洗美及出行 | O103: 宠物包 | P103: 任江惠 | R103: 4011.84 | S103: OA 90 DAYS | T103: 0 | U103: 28.08 | V103: 0 | W103: 48.14 | X103: 3885.62 | Y103: 0 | Z103: 0 | AA103: -76.22 | AB103: 1326.3 | AC103: 0 | AD103: 0 | AE103: 0 | AF103: 0 | AG103: 0 | AH103: -520.01 | AI103: 27720 | AJ103: 3189.03 | AK103: 554.4 | AL103: 97.97 | AM103: 0.0037 | AN103: -26603.25 | AO103: 波兰749 | AP103: PO-PN600-102 | AQ103: 202605 | AR103: 980.8041 | AS103: 客户第一组 | AT103: 宠物背带及旅行用品 | AU103: 宠物包 | AV103: =IF(ISNUMBER(MATCH(C103,畅想结算中心!$A$2:$A$436,0)),"有","无") -> 有
A104: 窦宇佳 | B104: 昊特赛九公司 | C104: HSA25Y013-1 | D104: HSA25Y011 | E104: LPP | F104: 主动开发 | G104: 2025-11-17 | H104: 2026-02-09 | I104: 2 | J104: 202605 | K104: 84 | L104: 2026-01-23 | M104: 1026 | N104: 经典玩具 | O104: 数字迷宫 | P104: 林元浩 | R104: 1026 | S104: OA 90 DAYS | T104: 0 | U104: 7.18 | V104: 0 | W104: 12.31 | X104: 997.14 | Y104: 0 | Z104: 0 | AA104: -19.49 | AB104: 295.76 | AC104: 0 | AD104: 0 | AE104: 0 | AF104: 0 | AG104: 0 | AH104: -134.92 | AI104: 7387.2 | AJ104: 849.85 | AK104: 73.87 | AL104: -4.47 | AM104: -0.0006 | AN104: -6956.69 | AO104: 波兰749 | AP104: KB-CT600-104 | AQ104: 202602 | AR104: 154.6116 | AS104: 客户第一组 | AT104: 其他经典玩具 | AU104: 其他常规经典玩具 | AV104: =IF(ISNUMBER(MATCH(C104,畅想结算中心!$A$2:$A$436,0)),"有","无") -> 有
A105: 窦宇佳 | B105: 昊特赛九公司 | C105: HSA25Y013-1 | D105: HSA25Y013 | E105: LPP | F105: 主动开发 | G105: 2025-11-26 | H105: 2026-02-09 | I105: 2 | J105: 202605 | K105: 75 | L105: 2026-01-23 | M105: 2024 | N105: 经典玩具 | O105: 其他常规经典玩具 | P105: 李雅婷 | R105: 4452.8 | S105: OA 90 DAYS | T105: 0 | U105: 31.17 | V105: 0 | W105: 53.44 | X105: 4327.56 | Y105: 0 | Z105: 0 | AA105: -84.61 | AB105: 932.65 | AC105: 0 | AD105: 0 | AE105: 0 | AF105: 0 | AG105: 0 | AH105: -585.7 | AI105: 23377.2 | AJ105: 2689.41 | AK105: 116.89 | AL105: 8219.34 | AM105: 0.2744 | AN105: -21953.08 | AO105: 波兰749 | AP105: KB-CT600-1008 | AQ105: 202602 | AR105: 8706.1577 | AS105: 客户第一组 | AT105: 其他经典玩具 | AU105: 其他常规经典玩具 | AV105: =IF(ISNUMBER(MATCH(C105,畅想结算中心!$A$2:$A$436,0)),"有","无") -> 有
A106: 李雅婷 | B106: 昊特赛九公司 | C106: HSB25M019-1 | D106: HSB25M019 | E106: Ofer | F106: others | G106: 2025-08-22 | H106: 2026-01-30 | I106: 2 | J106: 202603 | K106: 161 | L106: 2026-01-20 | M106: 3600 | N106: 能源电工 | O106: 地插灯系列 | P106: 叶柳涵 | R106: 12194.24 | S106: O/A 30 days | T106: 0 | U106: 85.36 | V106: 0 | W106: 0 | X106: 12108.89 | Y106: 0 | Z106: 0 | AA106: -85.36 | AB106: 0 | AC106: 0 | AD106: 0 | AE106: 0 | AF106: 0 | AG106: 0 | AH106: -592.2 | AI106: 84240 | AJ106: 0 | AK106: 0 | AL106: -232.15 | AM106: -0.0028 | AN106: -84832.19 | AO106: 以色列379 | AP106: F-GL142-5 | AQ106: 202603 | AR106: -232.1538 | AS106: 办公室 | AT106: 光伏应用产品 | AU106: 地插灯系列 | AV106: =IF(ISNUMBER(MATCH(C106,畅想结算中心!$A$2:$A$436,0)),"有","无") -> 有
A107: 李雅婷 | B107: 昊特赛九公司 | C107: HSB25M019-1 | D107: HSB25M019 | E107: Ofer | F107: others | G107: 2025-08-22 | H107: 2026-01-30 | I107: 2 | J107: 202603 | K107: 161 | L107: 2026-01-20 | M107: 2400 | N107: 功能照明 | O107: 便携工作灯 | P107: 李 灏 | R107: 16604.93 | S107: O/A 30 days | T107: 0 | U107: 116.23 | V107: 0 | W107: 0 | X107: 16488.69 | Y107: 0 | Z107: 0 | AA107: -116.23 | AB107: 0 | AC107: 0 | AD107: 0 | AE107: 0 | AF107: 0 | AG107: 0 | AH107: -806.37 | AI107: 105600 | AJ107: 0 | AK107: 0 | AL107: 8793.58 | AM107: 0.0769 | AN107: -106406.38 | AO107: 以色列379 | AP107: EL2607-1-10WX7-G1 | AQ107: 202603 | AR107: 8793.5846 | AS107: 办公室 | AT107: 应急灯及工作灯 | AU107: 便携工作灯 | AV107: =IF(ISNUMBER(MATCH(C107,畅想结算中心!$A$2:$A$436,0)),"有","无") -> 有
A108: 李雅婷 | B108: 昊特赛九公司 | C108: HSB25M020 | D108: HSB25M020 | E108: Ofer | F108: others | G108: 2025-08-27 | H108: 2026-03-30 | I108: 4 | J108: 202604 | K108: 215 | L108: 2025-09-30 | M108: 4800 | N108: 经典玩具 | O108: 其他常规经典玩具 | P108: 叶柳涵 | R108: 8060.22 | S108: O/A 30 days | T108: 0 | U108: 56.42 | V108: 0 | W108: 0 | X108: 8003.8 | Y108: 7836.85 | Z108: 55680 | AA108: 7780.43 | AB108: 0 | AC108: 0 | AD108: 0 | AE108: 0 | AF108: 0 | AG108: 0 | AH108: 53747.21 | AI108: 49440 | AJ108: 0 | AK108: 988.8 | AL108: 4861.45 | AM108: 0.0879 | AN108: 5702.84 | AO108: 以色列379 | AP108: OC150-CPQ1 | AQ108: 202604 | AR108: 5850.2504 | AS108: 客户第一组 | AT108: 其他经典玩具 | AU108: 其他常规经典玩具 | AV108: =IF(ISNUMBER(MATCH(C108,畅想结算中心!$A$2:$A$436,0)),"有","无") -> 有
A109: 李 爽 | B109: 昊特赛九公司 | C109: HSB25M022-1 | D109: HSB25M022 | E109: RMS | F109: 主动开发 | G109: 2025-09-28 | H109: 2026-01-13 | I109: 1 | K109: 107 | L109: 2025-11-10 | M109: 11928 | N109: 手工艺品及DIY玩具 | O109: 其他常规DIY玩具 | P109: 叶柳涵 | R109: 14313.6 | S109: OA 60DAYS | T109: 0 | U109: 100.2 | V109: 286.27 | W109: 85.88 | X109: 13791.25 | Y109: 0 | Z109: 0 | AA109: -472.35 | AB109: 5057.75 | AC109: 0 | AD109: 0 | AE109: 0 | AF109: 0 | AG109: 0 | AH109: -3289.26 | AI109: 95424 | AJ109: 10977.98 | AK109: 1908.48 | AL109: 4624.5 | AM109: 0.0482 | AN109: -94103.47 | AO109: 英国2962 | AP109: OD270-SLM001 | AQ109: 202603 | AR109: 7131.0148 | AS109: 客户第一组 | AT109: 创意类及材料包 | AU109: 其他常规DIY玩具 | AV109: =IF(ISNUMBER(MATCH(C109,畅想结算中心!$A$2:$A$436,0)),"有","无") -> 有
A110: 李 爽 | B110: 昊特赛九公司 | C110: HSB25M022-2 | D110: HSB25M022 | E110: RMS | F110: 主动开发 | G110: 2025-09-28 | H110: 2026-01-13 | I110: 1 | K110: 107 | L110: 2025-11-10 | M110: 9228 | N110: 手工艺品及DIY玩具 | O110: 其他常规DIY玩具 | P110: 叶柳涵 | R110: 11073.6 | S110: OA 60DAYS | T110: 0 | U110: 77.52 | V110: 221.47 | W110: 66.44 | X110: 10658.17 | Y110: 0 | Z110: 0 | AA110: -365.43 | AB110: 5057.75 | AC110: 0 | AD110: 0 | AE110: 0 | AF110: 0 | AG110: 0 | AH110: -2544.71 | AI110: 73824 | AJ110: 8493.03 | AK110: 1476.48 | AL110: 2354.03 | AM110: 0.0317 | AN110: -73947.25 | AO110: 英国2962 | AP110: OD270-SLM001 | AQ110: 202603 | AR110: 4293.1707 | AS110: 客户第一组 | AT110: 创意类及材料包 | AU110: 其他常规DIY玩具 | AV110: =IF(ISNUMBER(MATCH(C110,畅想结算中心!$A$2:$A$436,0)),"有","无") -> 有
A111: 李 爽 | B111: 昊特赛九公司 | C111: HSB25M022-3 | D111: HSB25M022 | E111: RMS | F111: 主动开发 | G111: 2025-09-28 | H111: 2026-01-13 | I111: 1 | J111: 202605 | K111: 107 | L111: 2025-11-10 | M111: 6072 | N111: 手工艺品及DIY玩具 | O111: 其他常规DIY玩具 | P111: 叶柳涵 | R111: 7286.4 | S111: OA 60DAYS | T111: 0 | U111: 51 | V111: 145.73 | W111: 43.72 | X111: 6995.95 | Y111: 0 | Z111: 0 | AA111: -240.45 | AB111: 5057.75 | AC111: 0 | AD111: 0 | AE111: 0 | AF111: 0 | AG111: 0 | AH111: -1674.4 | AI111: 48576 | AJ111: 5588.39 | AK111: 971.52 | AL111: -299.88 | AM111: -0.0062 | AN111: -50386.83 | AO111: 英国2962 | AP111: OD270-SLM001 | AQ111: 202603 | AR111: 976.0854 | AS111: 客户第一组 | AT111: 创意类及材料包 | AU111: 其他常规DIY玩具 | AV111: =IF(ISNUMBER(MATCH(C111,畅想结算中心!$A$2:$A$436,0)),"有","无") -> 有
A112: 李 爽 | B112: 昊特赛九公司 | C112: HSB25M022-4 | D112: HSB25M022 | E112: RMS | F112: 主动开发 | G112: 2025-09-28 | H112: 2026-01-13 | I112: 1 | J112: 202605 | K112: 107 | L112: 2025-11-10 | M112: 7392 | N112: 手工艺品及DIY玩具 | O112: 其他常规DIY玩具 | P112: 叶柳涵 | R112: 8870.4 | S112: OA 60DAYS | T112: 0 | U112: 62.09 | V112: 177.41 | W112: 53.22 | X112: 8527.68 | Y112: 0 | Z112: 0 | AA112: -292.72 | AB112: 5057.75 | AC112: 0 | AD112: 0 | AE112: 0 | AF112: 0 | AG112: 0 | AH112: -2038.38 | AI112: 59136 | AJ112: 6803.26 | AK112: 1182.72 | AL112: 810.14 | AM112: 0.0136 | AN112: -60241 | AO112: 英国2962 | AP112: OD270-SLM001 | AQ112: 202603 | AR112: 2363.4618 | AS112: 客户第一组 | AT112: 创意类及材料包 | AU112: 其他常规DIY玩具 | AV112: =IF(ISNUMBER(MATCH(C112,畅想结算中心!$A$2:$A$436,0)),"有","无") -> 有
A113: 李 爽 | B113: 昊特赛九公司 | C113: HSB25M022-5 | D113: HSB25M022 | E113: RMS | F113: 主动开发 | G113: 2025-09-28 | H113: 2026-01-13 | I113: 1 | J113: 202605 | K113: 107 | L113: 2025-11-10 | M113: 5388 | N113: 手工艺品及DIY玩具 | O113: 其他常规DIY玩具 | P113: 叶柳涵 | R113: 6465.6 | S113: OA 60DAYS | T113: 0 | U113: 45.26 | V113: 129.31 | W113: 38.79 | X113: 6202.24 | Y113: 0 | Z113: 0 | AA113: -213.36 | AB113: 5057.75 | AC113: 0 | AD113: 0 | AE113: 0 | AF113: 0 | AG113: 0 | AH113: -1485.75 | AI113: 43104 | AJ113: 4958.87 | AK113: 862.08 | AL113: -875.04 | AM113: -0.0203 | AN113: -45280.6 | AO113: 英国2962 | AP113: OD270-SLM001 | AQ113: 202603 | AR113: 257.1538 | AS113: 客户第一组 | AT113: 创意类及材料包 | AU113: 其他常规DIY玩具 | AV113: =IF(ISNUMBER(MATCH(C113,畅想结算中心!$A$2:$A$436,0)),"有","无") -> 有
A114: 李雅婷 | B114: 昊特赛九公司 | C114: HSB25M024-3 | D114: HSB25M024 | E114: RMS | F114: 主动开发 | G114: 2025-10-21 | H114: 2026-02-03 | I114: 2 | J114: 202605 | K114: 105 | L114: 2025-12-09 | M114: 800 | N114: 游泳装备 | O114: 游泳圈 | P114: 叶柳涵 | R114: 1680 | S114: OA 60DAYS | T114: 0 | U114: 11.76 | V114: 33.6 | W114: 10.08 | X114: 1586.82 | Y114: 0 | Z114: 0 | AA114: -55.44 | AB114: 337.22 | AC114: 0 | AD114: 0 | AE114: 0 | AF114: 0 | AG114: 0 | AH114: -384.06 | AI114: 9600 | AJ114: 1104.42 | AK114: 192 | AL114: 1967.75 | AM114: 0.179 | AN114: -9339.01 | AO114: 英国2962 | AP114: ST047-YQ-1 | AQ114: 202603 | AR114: 2229.6437 | AS114: 办公室 | AT114: 游泳训练器材 | AU114: 游泳圈 | AV114: =IF(ISNUMBER(MATCH(C114,畅想结算中心!$A$2:$A$436,0)),"有","无") -> 有
A115: 李雅婷 | B115: 昊特赛九公司 | C115: HSB25M024-3 | D115: HSB25M024 | E115: RMS | F115: 主动开发 | G115: 2025-10-21 | H115: 2026-02-03 | I115: 2 | J115: 202605 | K115: 105 | L115: 2025-12-09 | M115: 300 | N115: 经典玩具 | O115: 常规发光玩具 | P115: 叶柳涵 | R115: 546 | S115: OA 60DAYS | T115: 0 | U115: 3.82 | V115: 10.92 | W115: 3.28 | X115: 515.72 | Y115: 0 | Z115: 0 | AA115: -18.02 | AB115: 101.16 | AC115: 0 | AD115: 0 | AE115: 0 | AF115: 0 | AG115: 0 | AH115: -124.83 | AI115: 3780 | AJ115: 434.87 | AK115: 75.6 | AL115: 50.7 | AM115: 0.0142 | AN115: -3624.02 | AO115: 英国2962 | AP115: LT035-led-1 | AQ115: 202603 | AR115: 148.954 | AS115: 办公室 | AT115: 发光玩具 | AU115: 常规发光玩具 | AV115: =IF(ISNUMBER(MATCH(C115,畅想结算中心!$A$2:$A$436,0)),"有","无") -> 有
A116: 李雅婷 | B116: 昊特赛九公司 | C116: HSB25M024-6 | D116: HSB25M024 | E116: RMS | F116: 主动开发 | G116: 2025-10-21 | H116: 2026-02-03 | I116: 2 | J116: 202605 | K116: 105 | L116: 2025-12-09 | M116: 300 | N116: 游泳装备 | O116: 游泳圈 | P116: 叶柳涵 | R116: 2550 | S116: OA 60DAYS | T116: 0 | U116: 17.85 | V116: 51 | W116: 15.3 | X116: 2445.6 | Y116: 0 | Z116: 0 | AA116: -84.15 | AB116: 305.45 | AC116: 0 | AD116: 0 | AE116: 0 | AF116: 0 | AG116: 0 | AH116: -582.94 | AI116: 16200 | AJ116: 1863.72 | AK116: 324 | AL116: 1975.92 | AM116: 0.1166 | AN116: -15442.68 | AO116: 英国2962 | AP116: ST048-SC-1 | AQ116: 202603 | AR116: 2405.9099 | AS116: 办公室 | AT116: 游泳训练器材 | AU116: 游泳圈 | AV116: =IF(ISNUMBER(MATCH(C116,畅想结算中心!$A$2:$A$436,0)),"有","无") -> 有
A117: 李雅婷 | B117: 昊特赛九公司 | C117: HSB25M024-6 | D117: HSB25M024 | E117: RMS | F117: 主动开发 | G117: 2025-10-21 | H117: 2026-02-03 | I117: 2 | J117: 202605 | K117: 105 | L117: 2025-12-09 | M117: 400 | N117: 游泳装备 | O117: 游泳圈 | P117: 叶柳涵 | R117: 2040 | S117: OA 60DAYS | T117: 0 | U117: 14.28 | V117: 40.8 | W117: 12.24 | X117: 1956.48 | Y117: 0 | Z117: 0 | AA117: -67.32 | AB117: 336.36 | AC117: 0 | AD117: 0 | AE117: 0 | AF117: 0 | AG117: 0 | AH117: -466.35 | AI117: 11200 | AJ117: 1288.5 | AK117: 224 | AL117: 3081.45 | AM117: 0.2274 | AN117: -10853.43 | AO117: 英国2962 | AP117: ST049-YQ-2 | AQ117: 202603 | AR117: 3390.2416 | AS117: 办公室 | AT117: 游泳训练器材 | AU117: 游泳圈 | AV117: =IF(ISNUMBER(MATCH(C117,畅想结算中心!$A$2:$A$436,0)),"有","无") -> 有
A118: 李雅婷 | B118: 昊特赛九公司 | C118: HSB25M024-6 | D118: HSB25M024 | E118: RMS | F118: 主动开发 | G118: 2025-10-21 | H118: 2026-02-03 | I118: 2 | J118: 202605 | K118: 105 | L118: 2025-12-09 | M118: 2132 | N118: 装扮玩具 | O118: 常规工具玩具 | P118: 叶柳涵 | R118: 1705.6 | S118: OA 60DAYS | T118: 0 | U118: 11.94 | V118: 34.11 | W118: 10.23 | X118: 1635.77 | Y118: 0 | Z118: 0 | AA118: -56.28 | AB118: 1303.11 | AC118: 0 | AD118: 0 | AE118: 0 | AF118: 0 | AG118: 0 | AH118: -389.87 | AI118: 10446.8 | AJ118: 1201.84 | AK118: 208.94 | AL118: 574.63 | AM118: 0.0507 | AN118: -11076.02 | AO118: 英国2962 | AP118: TT003-FJWJ001 | AQ118: 202603 | AR118: 854.4351 | AS118: 办公室 | AT118: 工具玩具 | AU118: 常规工具玩具 | AV118: =IF(ISNUMBER(MATCH(C118,畅想结算中心!$A$2:$A$436,0)),"有","无") -> 有
A119: 李雅婷 | B119: 昊特赛九公司 | C119: HSB25M024-9 | D119: HSB25M024 | E119: RMS | F119: 主动开发 | G119: 2025-10-21 | H119: 2026-01-30 | I119: 2 | J119: 202605 | K119: 101 | L119: 2025-12-09 | M119: 1258 | N119: 运动休闲包 | O119: 常规沙滩包 | P119: 叶柳涵 | R119: 4780.4 | S119: OA 60DAYS | T119: 0 | U119: 33.46 | V119: 95.61 | W119: 28.68 | X119: 4576.44 | Y119: 0 | Z119: 0 | AA119: -157.75 | AB119: 0 | AC119: 0 | AD119: 0 | AE119: 0 | AF119: 0 | AG119: 0 | AH119: -1094.42 | AI119: 31450 | AJ119: 3618.14 | AK119: 629 | AL119: 3289.11 | AM119: 0.1036 | AN119: -29356.27 | AO119: 英国2962 | AP119: BB001-STB-1 | AQ119: 202603 | AR119: 4117.0826 | AS119: 办公室 | AT119: 沙滩包 | AU119: 常规沙滩包 | AV119: =IF(ISNUMBER(MATCH(C119,畅想结算中心!$A$2:$A$436,0)),"有","无") -> 有
A120: 李雅婷 | B120: 昊特赛九公司 | C120: HSB25M024-9 | D120: HSB25M024 | E120: RMS | F120: 主动开发 | G120: 2025-10-21 | H120: 2026-01-30 | I120: 2 | J120: 202605 | K120: 101 | L120: 2025-12-09 | M120: 2448 | N120: 装扮玩具 | O120: 其他常规装扮玩具 | P120: 叶柳涵 | R120: 391.68 | S120: OA 60DAYS | T120: 0 | U120: 2.74 | V120: 7.83 | W120: 2.35 | X120: 374.97 | Y120: 0 | Z120: 0 | AA120: -12.92 | AB120: 0 | AC120: 0 | AD120: 0 | AE120: 0 | AF120: 0 | AG120: 0 | AH120: -89.64 | AI120: 3035.52 | AJ120: 349.22 | AK120: 60.71 | AL120: -145.58 | AM120: -0.056 | AN120: -2820.38 | AO120: 英国2962 | AP120: 0D322-PS001 | AQ120: 202603 | AR120: -68.5679 | AS120: 办公室 | AT120: 其他装扮玩具 | AU120: 其他常规装扮玩具 | AV120: =IF(ISNUMBER(MATCH(C120,畅想结算中心!$A$2:$A$436,0)),"有","无") -> 有
A121: 李雅婷 | B121: 昊特赛九公司 | C121: HSB25M025-1 | D121: HSB25M025 | E121: RMS | F121: 主动开发 | G121: 2025-10-22 | H121: 2026-02-03 | I121: 2 | J121: 202605 | K121: 104 | L121: 2026-01-16 | M121: 176 | N121: 装扮玩具 | O121: 常规工具玩具 | P121: 叶柳涵 | R121: 140.8 | S121: OA 60DAYS | T121: 0 | U121: 0.99 | V121: 2.82 | W121: 0.84 | X121: 86.15 | Y121: 0 | Z121: 0 | AA121: -4.65 | AB121: 0 | AC121: 0 | AD121: 0 | AE121: 0 | AF121: 0 | AG121: 0 | AH121: -32.21 | AI121: 862.4 | AJ121: 99.21 | AK121: 17.25 | AL121: -183.64 | AM121: -0.3077 | AN121: -806.83 | AO121: 英国2962 | AP121: TT003-FJWJ001 | AQ121: 202603 | AR121: -160.5713 | AS121: 办公室 | AT121: 工具玩具 | AU121: 常规工具玩具 | AV121: =IF(ISNUMBER(MATCH(C121,畅想结算中心!$A$2:$A$436,0)),"有","无") -> 有
A122: 李雅婷 | B122: 昊特赛九公司 | C122: HSB25M025-10 | D122: HSB25M025 | E122: RMS | F122: 主动开发 | G122: 2025-10-22 | H122: 2026-04-11 | I122: 4 | K122: 171 | L122: 2026-01-16 | M122: 2520 | N122: 装扮玩具 | O122: 常规工具玩具 | P122: 陈依萍 | R122: 2016 | S122: OA 60DAYS | T122: 0 | U122: 14.11 | V122: 40.32 | W122: 12.1 | X122: 1906.76 | Y122: 0 | Z122: 0 | AA122: -66.53 | AB122: 1645.21 | AC122: 0 | AD122: 0 | AE122: 0 | AF122: 0 | AG122: 0 | AH122: -453.82 | AI122: 12348 | AJ122: 1420.57 | AK122: 246.96 | AL122: 186.98 | AM122: 0.0144 | AN122: -13190.9 | AO122: 英国2962 | AP122: TT003-FJWJ001 | AQ122: 202604 | AR122: 516.4757 | AS122: 办公室 | AT122: 工具玩具 | AU122: 常规工具玩具 | AV122: =IF(ISNUMBER(MATCH(C122,畅想结算中心!$A$2:$A$436,0)),"有","无") -> 有
A123: 李雅婷 | B123: 昊特赛九公司 | C123: HSB25M025-10 | D123: HSB25M025 | E123: RMS | F123: 主动开发 | G123: 2025-10-22 | H123: 2026-04-11 | I123: 4 | K123: 171 | L123: 2026-01-16 | M123: 189 | N123: 经典玩具 | O123: 常规发光玩具 | P123: 陈依萍 | R123: 343.98 | S123: OA 60DAYS | T123: 0 | U123: 2.41 | V123: 6.88 | W123: 2.06 | X123: 325.34 | Y123: 0 | Z123: 0 | AA123: -11.35 | AB123: 56.95 | AC123: 0 | AD123: 0 | AE123: 0 | AF123: 0 | AG123: 0 | AH123: -77.42 | AI123: 2381.4 | AJ123: 273.97 | AK123: 47.63 | AL123: 7.23 | AM123: 0.0033 | AN123: -2275.37 | AO123: 英国2962 | AP123: LT035-led-1 | AQ123: 202604 | AR123: 68.9104 | AS123: 办公室 | AT123: 发光玩具 | AU123: 常规发光玩具 | AV123: =IF(ISNUMBER(MATCH(C123,畅想结算中心!$A$2:$A$436,0)),"有","无") -> 有
A124: 李雅婷 | B124: 昊特赛九公司 | C124: HSB25M025-11 | D124: HSB25M025 | E124: RMS | F124: 主动开发 | G124: 2025-10-22 | H124: 2026-04-11 | I124: 4 | K124: 171 | L124: 2026-01-16 | M124: 172 | N124: 游泳装备 | O124: 游泳圈 | P124: 陈依萍 | R124: 877.2 | S124: OA 60DAYS | T124: 0 | U124: 6.14 | V124: 17.54 | W124: 5.26 | X124: 841.44 | Y124: 0 | Z124: 0 | AA124: -28.95 | AB124: 143.4 | AC124: 0 | AD124: 0 | AE124: 0 | AF124: 0 | AG124: 0 | AH124: -197.48 | AI124: 4816 | AJ124: 554.05 | AK124: 96.32 | AL124: 1238.05 | AM124: 0.2157 | AN124: -4663.22 | AO124: 英国2962 | AP124: ST049-YQ-2 | AQ124: 202604 | AR124: 1370.2522 | AS124: 办公室 | AT124: 游泳训练器材 | AU124: 游泳圈 | AV124: =IF(ISNUMBER(MATCH(C124,畅想结算中心!$A$2:$A$436,0)),"有","无") -> 有
A125: 李雅婷 | B125: 昊特赛九公司 | C125: HSB25M025-11 | D125: HSB25M025 | E125: RMS | F125: 主动开发 | G125: 2025-10-22 | H125: 2026-04-11 | I125: 4 | K125: 171 | L125: 2026-01-16 | M125: 342 | N125: 游泳装备 | O125: 游泳圈 | P125: 陈依萍 | R125: 2907 | S125: OA 60DAYS | T125: 0 | U125: 20.35 | V125: 58.14 | W125: 17.44 | X125: 2788.5 | Y125: 0 | Z125: 0 | AA125: -95.93 | AB125: 348.48 | AC125: 0 | AD125: 0 | AE125: 0 | AF125: 0 | AG125: 0 | AH125: -654.37 | AI125: 18468 | AJ125: 2124.64 | AK125: 369.36 | AL125: 1959.99 | AM125: 0.103 | AN125: -17596.6 | AO125: 英国2962 | AP125: ST048-SC-1 | AQ125: 202604 | AR125: 2448.311 | AS125: 办公室 | AT125: 游泳训练器材 | AU125: 游泳圈 | AV125: =IF(ISNUMBER(MATCH(C125,畅想结算中心!$A$2:$A$436,0)),"有","无") -> 有
A126: 李雅婷 | B126: 昊特赛九公司 | C126: HSB25M025-11 | D126: HSB25M025 | E126: RMS | F126: 主动开发 | G126: 2025-10-22 | H126: 2026-04-11 | I126: 4 | K126: 171 | L126: 2026-01-16 | M126: 1264 | N126: 游泳装备 | O126: 游泳圈 | P126: 陈依萍 | R126: 2654.4 | S126: OA 60DAYS | T126: 0 | U126: 18.58 | V126: 53.09 | W126: 15.93 | X126: 2546.19 | Y126: 0 | Z126: 0 | AA126: -87.59 | AB126: 439.08 | AC126: 0 | AD126: 0 | AE126: 0 | AF126: 0 | AG126: 0 | AH126: -597.48 | AI126: 15168 | AJ126: 1744.99 | AK126: 303.36 | AL126: 3202.88 | AM126: 0.1844 | AN126: -14654.32 | AO126: 英国2962 | AP126: ST047-YQ-1 | AQ126: 202604 | AR126: 3614.9008 | AS126: 办公室 | AT126: 游泳训练器材 | AU126: 游泳圈 | AV126: =IF(ISNUMBER(MATCH(C126,畅想结算中心!$A$2:$A$436,0)),"有","无") -> 有
A127: 李雅婷 | B127: 昊特赛九公司 | C127: HSB25M025-12 | D127: HSB25M025 | E127: RMS | F127: 主动开发 | G127: 2025-10-22 | H127: 2026-04-09 | I127: 4 | K127: 169 | L127: 2026-01-16 | M127: 1314 | N127: 运动休闲包 | O127: 常规沙滩包 | P127: 陈依萍 | R127: 4993.2 | S127: OA 60DAYS | T127: 0 | U127: 34.95 | V127: 99.87 | W127: 29.96 | X127: 4782.06 | Y127: 0 | Z127: 0 | AA127: -164.77 | AB127: 2497.37 | AC127: 0 | AD127: 0 | AE127: 0 | AF127: 0 | AG127: 0 | AH127: -1123.76 | AI127: 32850 | AJ127: 3779.2 | AK127: 657 | AL127: 389.44 | AM127: 0.0119 | AN127: -33144.63 | AO127: 英国2962 | AP127: BB001-STB-1 | AQ127: 202604 | AR127: 1250.7739 | AS127: 办公室 | AT127: 沙滩包 | AU127: 常规沙滩包 | AV127: =IF(ISNUMBER(MATCH(C127,畅想结算中心!$A$2:$A$436,0)),"有","无") -> 有
A128: 李雅婷 | B128: 昊特赛九公司 | C128: HSB25M025-12 | D128: HSB25M025 | E128: RMS | F128: 主动开发 | G128: 2025-10-22 | H128: 2026-04-09 | I128: 4 | K128: 169 | L128: 2026-01-16 | M128: 2448 | N128: 装扮玩具 | O128: 其他常规装扮玩具 | P128: 陈依萍 | R128: 391.68 | S128: OA 60DAYS | T128: 0 | U128: 2.74 | V128: 7.83 | W128: 2.35 | X128: 375.12 | Y128: 0 | Z128: 0 | AA128: -12.93 | AB128: 102.63 | AC128: 0 | AD128: 0 | AE128: 0 | AF128: 0 | AG128: 0 | AH128: -88.19 | AI128: 3035.52 | AJ128: 349.22 | AK128: 60.71 | AL128: -291.25 | AM128: -0.1138 | AN128: -2921.77 | AO128: 英国2962 | AP128: 0D322-PS001 | AQ128: 202604 | AR128: -214.5116 | AS128: 办公室 | AT128: 其他装扮玩具 | AU128: 其他常规装扮玩具 | AV128: =IF(ISNUMBER(MATCH(C128,畅想结算中心!$A$2:$A$436,0)),"有","无") -> 有
A129: 李雅婷 | B129: 昊特赛九公司 | C129: HSB25M025-2 | D129: HSB25M025 | E129: RMS | F129: 主动开发 | G129: 2025-10-22 | H129: 2026-04-10 | I129: 4 | K129: 170 | L129: 2026-01-16 | M129: 2352 | N129: 装扮玩具 | O129: 其他常规装扮玩具 | P129: 陈依萍 | R129: 376.32 | S129: OA 60DAYS | T129: 0 | U129: 2.63 | V129: 7.53 | W129: 2.26 | X129: 360.29 | Y129: 0 | Z129: 0 | AA129: -12.42 | AB129: 277.95 | AC129: 0 | AD129: 0 | AE129: 0 | AF129: 0 | AG129: 0 | AH129: -84.71 | AI129: 4538.48 | AJ129: 522.13 | AK129: 90.77 | AL129: -1927.75 | AM129: -0.7845 | AN129: -4454.38 | AO129: 英国2962 | AP129: 0D322-PS001 | AQ129: 202604 | AR129: -1821.5699 | AS129: 办公室 | AT129: 其他装扮玩具 | AU129: 其他常规装扮玩具 | AV129: =IF(ISNUMBER(MATCH(C129,畅想结算中心!$A$2:$A$436,0)),"有","无") -> 有
A130: 李雅婷 | B130: 昊特赛九公司 | C130: HSB25M025-2 | D130: HSB25M025 | E130: RMS | F130: 主动开发 | G130: 2025-10-22 | H130: 2026-04-10 | I130: 4 | K130: 170 | L130: 2026-01-16 | M130: 1272 | N130: 运动休闲包 | O130: 常规沙滩包 | P130: 陈依萍 | R130: 4833.6 | S130: OA 60DAYS | T130: 0 | U130: 33.84 | V130: 96.67 | W130: 29 | X130: 4627.7 | Y130: 0 | Z130: 0 | AA130: -159.51 | AB130: 6814.55 | AC130: 0 | AD130: 0 | AE130: 0 | AF130: 0 | AG130: 0 | AH130: -1087.92 | AI130: 31800 | AJ130: 3658.41 | AK130: 636 | AL130: -4029.38 | AM130: -0.1277 | AN130: -36482.27 | AO130: 英国2962 | AP130: BB001-STB-1 | AQ130: 202604 | AR130: -3195.5843 | AS130: 办公室 | AT130: 沙滩包 | AU130: 常规沙滩包 | AV130: =IF(ISNUMBER(MATCH(C130,畅想结算中心!$A$2:$A$436,0)),"有","无") -> 有
A131: 李雅婷 | B131: 昊特赛九公司 | C131: HSB25M025-3 | D131: HSB25M025 | E131: RMS | F131: 主动开发 | G131: 2025-10-22 | H131: 2026-04-09 | I131: 4 | K131: 169 | L131: 2026-01-16 | M131: 2448 | N131: 装扮玩具 | O131: 其他常规装扮玩具 | P131: 陈依萍 | R131: 391.68 | S131: OA 60DAYS | T131: 0 | U131: 2.74 | V131: 7.83 | W131: 2.35 | X131: 375.14 | Y131: 0 | Z131: 0 | AA131: -12.93 | AB131: 105.96 | AC131: 0 | AD131: 0 | AE131: 0 | AF131: 0 | AG131: 0 | AH131: -88.19 | AI131: 3035.52 | AJ131: 349.22 | AK131: 60.71 | AL131: -294.44 | AM131: -0.1151 | AN131: -2925.1 | AO131: 英国2962 | AP131: 0D322-PS001 | AQ131: 202604 | AR131: -217.7029 | AS131: 办公室 | AT131: 其他装扮玩具 | AU131: 其他常规装扮玩具 | AV131: =IF(ISNUMBER(MATCH(C131,畅想结算中心!$A$2:$A$436,0)),"有","无") -> 有
A132: 李雅婷 | B132: 昊特赛九公司 | C132: HSB25M025-3 | D132: HSB25M025 | E132: RMS | F132: 主动开发 | G132: 2025-10-22 | H132: 2026-04-09 | I132: 4 | K132: 169 | L132: 2026-01-16 | M132: 1322 | N132: 运动休闲包 | O132: 常规沙滩包 | P132: 陈依萍 | R132: 5023.6 | S132: OA 60DAYS | T132: 0 | U132: 35.17 | V132: 100.48 | W132: 30.14 | X132: 4811.43 | Y132: 0 | Z132: 0 | AA132: -165.78 | AB132: 2594.04 | AC132: 0 | AD132: 0 | AE132: 0 | AF132: 0 | AG132: 0 | AH132: -1130.65 | AI132: 33050 | AJ132: 3802.21 | AK132: 661 | AL132: 312.09 | AM132: 0.0095 | AN132: -33427.95 | AO132: 英国2962 | AP132: BB001-STB-1 | AQ132: 202604 | AR132: 1178.6474 | AS132: 办公室 | AT132: 沙滩包 | AU132: 常规沙滩包 | AV132: =IF(ISNUMBER(MATCH(C132,畅想结算中心!$A$2:$A$436,0)),"有","无") -> 有
A133: 李雅婷 | B133: 昊特赛九公司 | C133: HSB25M025-4 | D133: HSB25M025 | E133: RMS | F133: 主动开发 | G133: 2025-10-22 | H133: 2026-04-09 | I133: 4 | K133: 169 | L133: 2026-01-16 | M133: 2880 | N133: 装扮玩具 | O133: 其他常规装扮玩具 | P133: 陈依萍 | R133: 460.8 | S133: OA 60DAYS | T133: 0 | U133: 3.23 | V133: 9.22 | W133: 2.77 | X133: 441.97 | Y133: 0 | Z133: 0 | AA133: -15.21 | AB133: 125.68 | AC133: 0 | AD133: 0 | AE133: 0 | AF133: 0 | AG133: 0 | AH133: -103.74 | AI133: 3571.2 | AJ133: 410.85 | AK133: 71.42 | AL133: -343.13 | AM133: -0.1138 | AN133: -3442.31 | AO133: 英国2962 | AP133: 0D322-PS001 | AQ133: 202604 | AR133: -252.8202 | AS133: 办公室 | AT133: 其他装扮玩具 | AU133: 其他常规装扮玩具 | AV133: =IF(ISNUMBER(MATCH(C133,畅想结算中心!$A$2:$A$436,0)),"有","无") -> 有
... A149: 李雅婷 | B149: 昊特赛九公司 | C149: HSB25M025-9 | D149: HSB25M025 | E149: RMS | F149: 主动开发 | G149: 2025-10-22 | H149: 2026-04-04 | I149: 4 | K149: 164 | L149: 2026-01-16 | M149: 213 | N149: 经典玩具 | O149: 常规发光玩具 | P149: 陈依萍 | R149: 387.66 | S149: OA 60DAYS | T149: 0 | U149: 2.71 | V149: 7.75 | W149: 2.33 | X149: 368.78 | Y149: 0 | Z149: 0 | AA149: -12.79 | AB149: 62.03 | AC149: 0 | AD149: 0 | AE149: 0 | AF149: 0 | AG149: 0 | AH149: -87.96 | AI149: 2683.8 | AJ149: 308.76 | AK149: 53.68 | AL149: 45.49 | AM149: 0.0179 | AN149: -2562.75 | AO149: 英国2962 | AP149: LT035-led-1 | AQ149: 202604 | AR149: 115.1945 | AS149: 办公室 | AT149: 发光玩具 | AU149: 常规发光玩具 | AV149: =IF(ISNUMBER(MATCH(C149,畅想结算中心!$A$2:$A$436,0)),"有","无") -> 有
A150: 李雅婷 | B150: 昊特赛九公司 | C150: HSB25M026-1 | D150: HSB25M026 | E150: RMS | F150: 主动开发 | G150: 2025-10-22 | H150: 2026-02-08 | I150: 2 | J150: 202605 | K150: 109 | L150: 2026-01-28 | M150: 2544 | N150: 装扮玩具 | O150: 其他常规装扮玩具 | P150: 叶柳涵 | R150: 407.04 | S150: OA 60DAYS | T150: 0 | U150: 2.85 | V150: 8.14 | W150: 2.44 | X150: 389.95 | Y150: 0 | Z150: 0 | AA150: -13.43 | AB150: 0 | AC150: 0 | AD150: 0 | AE150: 0 | AF150: 0 | AG150: 0 | AH150: -93.03 | AI150: 3154.56 | AJ150: 362.91 | AK150: 63.09 | AL150: -153.44 | AM150: -0.0568 | AN150: -2930.87 | AO150: 英国2962 | AP150: 0D322-PS001 | AQ150: 202603 | AR150: -73.4428 | AS150: 办公室 | AT150: 其他装扮玩具 | AU150: 其他常规装扮玩具 | AV150: =IF(ISNUMBER(MATCH(C150,畅想结算中心!$A$2:$A$436,0)),"有","无") -> 有
A151: 李雅婷 | B151: 昊特赛九公司 | C151: HSB25M026-1 | D151: HSB25M026 | E151: RMS | F151: 主动开发 | G151: 2025-10-22 | H151: 2026-02-08 | I151: 2 | J151: 202605 | K151: 109 | L151: 2026-01-28 | M151: 1356 | N151: 运动休闲包 | O151: 常规沙滩包 | P151: 叶柳涵 | R151: 5152.8 | S151: OA 60DAYS | T151: 0 | U151: 36.07 | V151: 103.06 | W151: 30.92 | X151: 4936.41 | Y151: 0 | Z151: 0 | AA151: -170.05 | AB151: 0 | AC151: 0 | AD151: 0 | AE151: 0 | AF151: 0 | AG151: 0 | AH151: -1177.99 | AI151: 33900 | AJ151: 3900 | AK151: 678 | AL151: 3517.99 | AM151: 0.1029 | AN151: -31641.79 | AO151: 英国2962 | AP151: BB001-STB-1 | AQ151: 202603 | AR151: 4410.1851 | AS151: 办公室 | AT151: 沙滩包 | AU151: 常规沙滩包 | AV151: =IF(ISNUMBER(MATCH(C151,畅想结算中心!$A$2:$A$436,0)),"有","无") -> 有
A152: 李雅婷 | B152: 昊特赛九公司 | C152: HSB25M026-10 | D152: HSB25M025 | E152: RMS | F152: 主动开发 | G152: 2025-10-22 | H152: 2026-02-05 | I152: 2 | J152: 202605 | K152: 106 | L152: 2026-01-16 | M152: 3548 | N152: 装扮玩具 | O152: 常规工具玩具 | P152: 叶柳涵 | R152: 2838.4 | S152: OA 60DAYS | T152: 0 | U152: 19.87 | V152: 56.77 | W152: 17.03 | X152: 2694.73 | Y152: 0 | Z152: 0 | AA152: -93.67 | AB152: 1726.4 | AC152: 0 | AD152: 0 | AE152: 0 | AF152: 0 | AG152: 0 | AH152: -649.61 | AI152: 17385.2 | AJ152: 2000.07 | AK152: 347.7 | AL152: 1228.99 | AM152: 0.0658 | AN152: -17990.74 | AO152: 英国2962 | AP152: TT003-FJWJ001 | AQ152: 202603 | AR152: 1694.7941 | AS152: 办公室 | AT152: 工具玩具 | AU152: 常规工具玩具 | AV152: =IF(ISNUMBER(MATCH(C152,畅想结算中心!$A$2:$A$436,0)),"有","无") -> 有
A153: 李雅婷 | B153: 昊特赛九公司 | C153: HSB25M026-2 | D153: HSB25M026 | E153: RMS | F153: 主动开发 | G153: 2025-10-22 | H153: 2026-01-30 | I153: 2 | J153: 202605 | K153: 100 | L153: 2026-01-28 | M153: 1348 | N153: 运动休闲包 | O153: 常规沙滩包 | P153: 叶柳涵 | R153: 5122.4 | S153: OA 60DAYS | T153: 0 | U153: 35.85 | V153: 102.45 | W153: 30.73 | X153: 4906.98 | Y153: 0 | Z153: 0 | AA153: -169.04 | AB153: 0 | AC153: 0 | AD153: 0 | AE153: 0 | AF153: 0 | AG153: 0 | AH153: -1172.75 | AI153: 33700 | AJ153: 3876.99 | AK153: 674 | AL153: 3546.15 | AM153: 0.1042 | AN153: -31456.54 | AO153: 英国2962 | AP153: BB001-STB-1 | AQ153: 202603 | AR153: 4433.3419 | AS153: 办公室 | AT153: 沙滩包 | AU153: 常规沙滩包 | AV153: =IF(ISNUMBER(MATCH(C153,畅想结算中心!$A$2:$A$436,0)),"有","无") -> 有
A154: 李雅婷 | B154: 昊特赛九公司 | C154: HSB25M026-2 | D154: HSB25M026 | E154: RMS | F154: 主动开发 | G154: 2025-10-22 | H154: 2026-01-30 | I154: 2 | J154: 202605 | K154: 100 | L154: 2026-01-28 | M154: 2496 | N154: 装扮玩具 | O154: 其他常规装扮玩具 | P154: 叶柳涵 | R154: 399.36 | S154: OA 60DAYS | T154: 0 | U154: 2.8 | V154: 7.99 | W154: 2.4 | X154: 382.56 | Y154: 0 | Z154: 0 | AA154: -13.18 | AB154: 0 | AC154: 0 | AD154: 0 | AE154: 0 | AF154: 0 | AG154: 0 | AH154: -91.44 | AI154: 3095.04 | AJ154: 356.07 | AK154: 61.9 | AL154: -146.79 | AM154: -0.0553 | AN154: -2875.68 | AO154: 英国2962 | AP154: 0D322-PS001 | AQ154: 202603 | AR154: -68.2365 | AS154: 办公室 | AT154: 其他装扮玩具 | AU154: 其他常规装扮玩具 | AV154: =IF(ISNUMBER(MATCH(C154,畅想结算中心!$A$2:$A$436,0)),"有","无") -> 有
A155: 李雅婷 | B155: 昊特赛九公司 | C155: HSB25M026-3 | D155: HSB25M026 | E155: RMS | F155: 主动开发 | G155: 2025-10-22 | H155: 2026-02-16 | I155: 2 | J155: 202605 | K155: 117 | L155: 2026-01-28 | M155: 1728 | N155: 装扮玩具 | O155: 其他常规装扮玩具 | P155: 叶柳涵 | R155: 276.48 | S155: OA 60DAYS | T155: 0 | U155: 1.94 | V155: 5.53 | W155: 1.66 | X155: 263.75 | Y155: 0 | Z155: 0 | AA155: -9.12 | AB155: 0 | AC155: 0 | AD155: 0 | AE155: 0 | AF155: 0 | AG155: 0 | AH155: -62.88 | AI155: 2142.72 | AJ155: 246.51 | AK155: 42.85 | AL155: -120.59 | AM155: -0.0663 | AN155: -1990.53 | AO155: 英国2962 | AP155: 0D322-PS001 | AQ155: 202603 | AR155: -66.2901 | AS155: 办公室 | AT155: 其他装扮玩具 | AU155: 其他常规装扮玩具 | AV155: =IF(ISNUMBER(MATCH(C155,畅想结算中心!$A$2:$A$436,0)),"有","无") -> 有
A156: 李雅婷 | B156: 昊特赛九公司 | C156: HSB25M026-3 | D156: HSB25M026 | E156: RMS | F156: 主动开发 | G156: 2025-10-22 | H156: 2026-02-16 | I156: 2 | J156: 202605 | K156: 117 | L156: 2026-01-28 | M156: 936 | N156: 运动休闲包 | O156: 常规沙滩包 | P156: 叶柳涵 | R156: 3556.8 | S156: OA 60DAYS | T156: 0 | U156: 24.89 | V156: 71.13 | W156: 21.34 | X156: 3393.04 | Y156: 0 | Z156: 0 | AA156: -117.37 | AB156: 0 | AC156: 0 | AD156: 0 | AE156: 0 | AF156: 0 | AG156: 0 | AH156: -809.23 | AI156: 23400 | AJ156: 2692.04 | AK156: 468 | AL156: 2218.03 | AM156: 0.0948 | AN156: -21838.03 | AO156: 英国2962 | AP156: BB001-STB-1 | AQ156: 202603 | AR156: 2833.1612 | AS156: 办公室 | AT156: 沙滩包 | AU156: 常规沙滩包 | AV156: =IF(ISNUMBER(MATCH(C156,畅想结算中心!$A$2:$A$436,0)),"有","无") -> 有
A157: 李雅婷 | B157: 昊特赛九公司 | C157: HSB25M026-4 | D157: HSB25M026 | E157: RMS | F157: 主动开发 | G157: 2025-10-22 | H157: 2026-02-02 | I157: 2 | J157: 202605 | K157: 103 | L157: 2026-01-28 | M157: 246 | N157: 经典玩具 | O157: 常规发光玩具 | P157: 叶柳涵 | R157: 447.72 | S157: OA 60DAYS | T157: 0 | U157: 3.13 | V157: 8.95 | W157: 2.69 | X157: 425.52 | Y157: 0 | Z157: 0 | AA157: -14.77 | AB157: 17.02 | AC157: 0 | AD157: 0 | AE157: 0 | AF157: 0 | AG157: 0 | AH157: -102.46 | AI157: 3099.6 | AJ157: 356.59 | AK157: 61.99 | AL157: 129.73 | AM157: 0.044 | AN157: -2905.88 | AO157: 英国2962 | AP157: LT035-led-1 | AQ157: 202603 | AR157: 210.306 | AS157: 办公室 | AT157: 发光玩具 | AU157: 常规发光玩具 | AV157: =IF(ISNUMBER(MATCH(C157,畅想结算中心!$A$2:$A$436,0)),"有","无") -> 有
A158: 李雅婷 | B158: 昊特赛九公司 | C158: HSB25M026-4 | D158: HSB25M026 | E158: RMS | F158: 主动开发 | G158: 2025-10-22 | H158: 2026-02-02 | I158: 2 | J158: 202605 | K158: 103 | L158: 2026-01-28 | M158: 3208 | N158: 装扮玩具 | O158: 常规工具玩具 | P158: 叶柳涵 | R158: 2566.4 | S158: OA 60DAYS | T158: 0 | U158: 17.97 | V158: 51.33 | W158: 15.39 | X158: 2439.14 | Y158: 0 | Z158: 0 | AA158: -84.69 | AB158: 2015.32 | AC158: 0 | AD158: 0 | AE158: 0 | AF158: 0 | AG158: 0 | AH158: -587.48 | AI158: 15719.2 | AJ158: 1808.4 | AK158: 314.38 | AL158: 679.33 | AM158: 0.0401 | AN158: -16721.16 | AO158: 英国2962 | AP158: TT003-FJWJ001 | AQ158: 202603 | AR158: 1100.5396 | AS158: 办公室 | AT158: 工具玩具 | AU158: 常规工具玩具 | AV158: =IF(ISNUMBER(MATCH(C158,畅想结算中心!$A$2:$A$436,0)),"有","无") -> 有
A159: 李雅婷 | B159: 昊特赛九公司 | C159: HSB25M026-5 | D159: HSB25M025 | E159: RMS | F159: 主动开发 | G159: 2025-10-22 | H159: 2026-02-18 | I159: 2 | J159: 202605 | K159: 119 | L159: 2026-01-16 | M159: 243 | N159: 经典玩具 | O159: 常规发光玩具 | P159: 叶柳涵 | R159: 442.26 | S159: OA 60DAYS | T159: 0 | U159: 3.1 | V159: 8.85 | W159: 2.65 | X159: 377.66 | Y159: 0 | Z159: 0 | AA159: -14.6 | AB159: 335.36 | AC159: 0 | AD159: 0 | AE159: 0 | AF159: 0 | AG159: 0 | AH159: -100.69 | AI159: 3061.8 | AJ159: 352.24 | AK159: 61.24 | AL159: -501.55 | AM159: -0.1926 | AN159: -3188.57 | AO159: 英国2962 | AP159: LT035-led-1 | AQ159: 202603 | AR159: -422.0335 | AS159: 办公室 | AT159: 发光玩具 | AU159: 常规发光玩具 | AV159: =IF(ISNUMBER(MATCH(C159,畅想结算中心!$A$2:$A$436,0)),"有","无") -> 有
A160: 李雅婷 | B160: 昊特赛九公司 | C160: HSB25M026-6 | D160: HSB25M026 | E160: RMS | F160: 主动开发 | G160: 2025-10-22 | H160: 2026-02-09 | I160: 2 | J160: 202605 | K160: 110 | L160: 2026-01-28 | M160: 219 | N160: 经典玩具 | O160: 常规发光玩具 | P160: 叶柳涵 | R160: 398.58 | S160: OA 60DAYS | T160: 0 | U160: 2.79 | V160: 7.97 | W160: 2.39 | X160: 377.11 | Y160: 0 | Z160: 0 | AA160: -13.15 | AB160: 0 | AC160: 0 | AD160: 0 | AE160: 0 | AF160: 0 | AG160: 0 | AH160: -91.03 | AI160: 2759.4 | AJ160: 317.45 | AK160: 55.19 | AL160: 113.33 | AM160: 0.0434 | AN160: -2571.64 | AO160: 英国2962 | AP160: LT035-led-1 | AQ160: 202603 | AR160: 185.0659 | AS160: 办公室 | AT160: 发光玩具 | AU160: 常规发光玩具 | AV160: =IF(ISNUMBER(MATCH(C160,畅想结算中心!$A$2:$A$436,0)),"有","无") -> 有
A161: 李雅婷 | B161: 昊特赛九公司 | C161: HSB25M026-6 | D161: HSB25M026 | E161: RMS | F161: 主动开发 | G161: 2025-10-22 | H161: 2026-02-09 | I161: 2 | J161: 202605 | K161: 110 | L161: 2026-01-28 | M161: 2496 | N161: 装扮玩具 | O161: 常规工具玩具 | P161: 叶柳涵 | R161: 1996.8 | S161: OA 60DAYS | T161: 0 | U161: 13.98 | V161: 39.94 | W161: 11.98 | X161: 1889.22 | Y161: 0 | Z161: 0 | AA161: -65.9 | AB161: 0 | AC161: 0 | AD161: 0 | AE161: 0 | AF161: 0 | AG161: 0 | AH161: -456.18 | AI161: 12230.4 | AJ161: 1407.04 | AK161: 244.61 | AL161: 2009.77 | AM161: 0.1537 | AN161: -11441.21 | AO161: 英国2962 | AP161: TT003-FJWJ001 | AQ161: 202603 | AR161: 2337.314 | AS161: 办公室 | AT161: 工具玩具 | AU161: 常规工具玩具 | AV161: =IF(ISNUMBER(MATCH(C161,畅想结算中心!$A$2:$A$436,0)),"有","无") -> 有
... A167: 李雅婷 | B167: 昊特赛九公司 | C167: HSB25M026-9 | D167: HSB25M026 | E167: RMS | F167: 主动开发 | G167: 2025-10-22 | H167: 2026-02-03 | I167: 2 | J167: 202605 | K167: 104 | L167: 2026-01-28 | M167: 56 | N167: 游泳装备 | O167: 游泳圈 | P167: 叶柳涵 | R167: 285.6 | S167: OA 60DAYS | T167: 0 | U167: 2 | V167: 5.71 | W167: 1.71 | X167: 270.86 | Y167: 0 | Z167: 0 | AA167: -9.42 | AB167: 0 | AC167: 0 | AD167: 0 | AE167: 0 | AF167: 0 | AG167: 0 | AH167: -65.26 | AI167: 1568 | AJ167: 180.39 | AK167: 31.36 | AL167: 457.38 | AM167: 0.2438 | AN167: -1472.39 | AO167: 英国2962 | AP167: ST049-YQ-2 | AQ167: 202603 | AR167: 500.6601 | AS167: 办公室 | AT167: 游泳训练器材 | AU167: 游泳圈 | AV167: =IF(ISNUMBER(MATCH(C167,畅想结算中心!$A$2:$A$436,0)),"有","无") -> 有
A168: 李雅婷 | B168: 昊特赛九公司 | C168: HSB25M027-1 | D168: HSB25M027 | E168: RMS | F168: 主动开发 | G168: 2025-10-22 | H168: 2026-03-10 | I168: 3 | K168: 139 | L168: 2026-03-15 | M168: 3528 | N168: 运动休闲包 | O168: 常规沙滩包 | P168: 叶柳涵 | R168: 13406.4 | S168: OA 60DAYS | T168: 0 | U168: 93.84 | V168: 268.12 | W168: 80.44 | X168: 12917.55 | Y168: 0 | Z168: 0 | AA168: -442.41 | AB168: 4644.35 | AC168: 0 | AD168: 0 | AE168: 0 | AF168: 0 | AG168: 0 | AH168: -3039.62 | AI168: 88200 | AJ168: 10146.9 | AK168: 1764 | AL168: 4289.87 | AM168: 0.0483 | AN168: -86948.39 | AO168: 英国2962 | AP168: BB001-STB-1 | AQ168: 202603 | AR168: 6606.4703 | AS168: 办公室 | AT168: 沙滩包 | AU168: 常规沙滩包 | AV168: =IF(ISNUMBER(MATCH(C168,畅想结算中心!$A$2:$A$436,0)),"有","无") -> 有
A169: 李雅婷 | B169: 昊特赛九公司 | C169: HSB25M027-1 | D169: HSB25M027 | E169: RMS | F169: 主动开发 | G169: 2025-10-22 | H169: 2026-03-10 | I169: 3 | K169: 139 | L169: 2026-03-15 | M169: 6408 | N169: 装扮玩具 | O169: 其他常规装扮玩具 | P169: 叶柳涵 | R169: 1025.28 | S169: OA 60DAYS | T169: 0 | U169: 7.18 | V169: 20.51 | W169: 6.15 | X169: 987.89 | Y169: 0 | Z169: 0 | AA169: -33.83 | AB169: 179.65 | AC169: 0 | AD169: 0 | AE169: 0 | AF169: 0 | AG169: 0 | AH169: -232.43 | AI169: 7945.92 | AJ169: 914.13 | AK169: 158.92 | AL169: -582.96 | AM169: -0.0859 | AN169: -7560.55 | AO169: 英国2962 | AP169: 0D322-PS001 | AQ169: 202603 | AR169: -381.7139 | AS169: 办公室 | AT169: 其他装扮玩具 | AU169: 其他常规装扮玩具 | AV169: =IF(ISNUMBER(MATCH(C169,畅想结算中心!$A$2:$A$436,0)),"有","无") -> 有
A170: 李雅婷 | B170: 昊特赛九公司 | C170: HSB25M027-10 | D170: HSB25M024 | E170: RMS | F170: 主动开发 | G170: 2025-10-21 | H170: 2026-03-17 | I170: 3 | K170: 147 | L170: 2025-12-09 | M170: 1354 | N170: 运动休闲包 | O170: 常规沙滩包 | P170: 叶柳涵 | R170: 5145.2 | S170: OA 60DAYS | T170: 0 | U170: 36.02 | V170: 102.91 | W170: 30.87 | X170: 4929.04 | Y170: 0 | Z170: 0 | AA170: -169.79 | AB170: 2500.83 | AC170: 0 | AD170: 0 | AE170: 0 | AF170: 0 | AG170: 0 | AH170: -1166.41 | AI170: 33850 | AJ170: 3894.25 | AK170: 677 | AL170: 727.44 | AM170: 0.0215 | AN170: -34087.94 | AO170: 英国2962 | AP170: BB001-STB-1 | AQ170: 202603 | AR170: 1616.5111 | AS170: 办公室 | AT170: 沙滩包 | AU170: 常规沙滩包 | AV170: =IF(ISNUMBER(MATCH(C170,畅想结算中心!$A$2:$A$436,0)),"有","无") -> 有
A171: 李雅婷 | B171: 昊特赛九公司 | C171: HSB25M027-10 | D171: HSB25M027 | E171: RMS | F171: 主动开发 | G171: 2025-10-22 | H171: 2026-03-17 | I171: 3 | K171: 146 | L171: 2026-03-15 | M171: 2520 | N171: 装扮玩具 | O171: 其他常规装扮玩具 | P171: 叶柳涵 | R171: 403.2 | S171: OA 60DAYS | T171: 0 | U171: 2.82 | V171: 8.06 | W171: 2.42 | X171: 386.26 | Y171: 0 | Z171: 0 | AA171: -13.31 | AB171: 99.17 | AC171: 0 | AD171: 0 | AE171: 0 | AF171: 0 | AG171: 0 | AH171: -91.44 | AI171: 3124.8 | AJ171: 359.49 | AK171: 62.5 | AL171: -273.49 | AM171: -0.1031 | AN171: -3001.77 | AO171: 英国2962 | AP171: 0D322-PS001 | AQ171: 202603 | AR171: -194.3643 | AS171: 办公室 | AT171: 其他装扮玩具 | AU171: 其他常规装扮玩具 | AV171: =IF(ISNUMBER(MATCH(C171,畅想结算中心!$A$2:$A$436,0)),"有","无") -> 有
A172: 李雅婷 | B172: 昊特赛九公司 | C172: HSB25M027-2 | D172: HSB25M027 | E172: RMS | F172: 主动开发 | G172: 2025-10-22 | H172: 2026-03-14 | I172: 3 | K172: 143 | L172: 2026-03-15 | M172: 273 | N172: 游泳装备 | O172: 游泳圈 | P172: 叶柳涵 | R172: 2320.5 | S172: OA 60DAYS | T172: 0 | U172: 16.24 | V172: 46.41 | W172: 13.92 | X172: 2221.79 | Y172: 0 | Z172: 0 | AA172: -76.58 | AB172: 342.77 | AC172: 0 | AD172: 0 | AE172: 0 | AF172: 0 | AG172: 0 | AH172: -528.02 | AI172: 14742 | AJ172: 1695.98 | AK172: 294.84 | AL172: 1635.62 | AM172: 0.1068 | AN172: -14115.63 | AO172: 英国2962 | AP172: ST048-SC-1 | AQ172: 202603 | AR172: 2026.4362 | AS172: 办公室 | AT172: 游泳训练器材 | AU172: 游泳圈 | AV172: =IF(ISNUMBER(MATCH(C172,畅想结算中心!$A$2:$A$436,0)),"有","无") -> 有
A173: 李雅婷 | B173: 昊特赛九公司 | C173: HSB25M027-2 | D173: HSB25M027 | E173: RMS | F173: 主动开发 | G173: 2025-10-22 | H173: 2026-03-14 | I173: 3 | K173: 143 | L173: 2026-03-15 | M173: 1032 | N173: 游泳装备 | O173: 游泳圈 | P173: 叶柳涵 | R173: 2167.2 | S173: OA 60DAYS | T173: 0 | U173: 15.17 | V173: 43.34 | W173: 13 | X173: 2075.01 | Y173: 0 | Z173: 0 | AA173: -71.52 | AB173: 441.73 | AC173: 0 | AD173: 0 | AE173: 0 | AF173: 0 | AG173: 0 | AH173: -493.13 | AI173: 12384 | AJ173: 1424.71 | AK173: 247.68 | AL173: 2658.49 | AM173: 0.1858 | AN173: -12052.16 | AO173: 英国2962 | AP173: ST047-YQ-1 | AQ173: 202603 | AR173: 2995.8788 | AS173: 办公室 | AT173: 游泳训练器材 | AU173: 游泳圈 | AV173: =IF(ISNUMBER(MATCH(C173,畅想结算中心!$A$2:$A$436,0)),"有","无") -> 有
A174: 李雅婷 | B174: 昊特赛九公司 | C174: HSB25M027-2 | D174: HSB25M027 | E174: RMS | F174: 主动开发 | G174: 2025-10-22 | H174: 2026-03-14 | I174: 3 | K174: 143 | L174: 2026-03-15 | M174: 148 | N174: 游泳装备 | O174: 游泳圈 | P174: 叶柳涵 | R174: 754.8 | S174: OA 60DAYS | T174: 0 | U174: 5.28 | V174: 15.1 | W174: 4.53 | X174: 722.69 | Y174: 0 | Z174: 0 | AA174: -24.91 | AB174: 152.04 | AC174: 0 | AD174: 0 | AE174: 0 | AF174: 0 | AG174: 0 | AH174: -171.75 | AI174: 4144 | AJ174: 476.74 | AK174: 82.88 | AL174: 1080.77 | AM174: 0.2169 | AN174: -4042.69 | AO174: 英国2962 | AP174: ST049-YQ-2 | AQ174: 202603 | AR174: 1194.889 | AS174: 办公室 | AT174: 游泳训练器材 | AU174: 游泳圈 | AV174: =IF(ISNUMBER(MATCH(C174,畅想结算中心!$A$2:$A$436,0)),"有","无") -> 有
A175: 李雅婷 | B175: 昊特赛九公司 | C175: HSB25M027-3 | D175: HSB25M026 | E175: RMS | F175: 主动开发 | G175: 2025-10-22 | H175: 2026-03-12 | I175: 3 | K175: 141 | L175: 2026-01-28 | M175: 164 | N175: 游泳装备 | O175: 游泳圈 | P175: 叶柳涵 | R175: 836.4 | S175: OA 60DAYS | T175: 0 | U175: 5.86 | V175: 16.73 | W175: 5.02 | X175: 801.47 | Y175: 0 | Z175: 0 | AA175: -27.6 | AB175: 127.2 | AC175: 0 | AD175: 0 | AE175: 0 | AF175: 0 | AG175: 0 | AH175: -189.43 | AI175: 4592 | AJ175: 528.28 | AK175: 91.84 | AL175: 1217.97 | AM175: 0.2214 | AN175: -4437.75 | AO175: 英国2962 | AP175: ST049-YQ-2 | AQ175: 202603 | AR175: 1344.2664 | AS175: 办公室 | AT175: 游泳训练器材 | AU175: 游泳圈 | AV175: =IF(ISNUMBER(MATCH(C175,畅想结算中心!$A$2:$A$436,0)),"有","无") -> 有
A176: 李雅婷 | B176: 昊特赛九公司 | C176: HSB25M027-3 | D176: HSB25M027 | E176: RMS | F176: 主动开发 | G176: 2025-10-22 | H176: 2026-03-12 | I176: 3 | K176: 141 | L176: 2026-03-15 | M176: 1080 | N176: 游泳装备 | O176: 游泳圈 | P176: 叶柳涵 | R176: 2268 | S176: OA 60DAYS | T176: 0 | U176: 15.88 | V176: 45.36 | W176: 13.61 | X176: 2173.28 | Y176: 0 | Z176: 0 | AA176: -74.84 | AB176: 349.02 | AC176: 0 | AD176: 0 | AE176: 0 | AF176: 0 | AG176: 0 | AH176: -513.65 | AI176: 12960 | AJ176: 1490.97 | AK176: 259.2 | AL176: 2838.62 | AM176: 0.1903 | AN176: -12497.54 | AO176: 英国2962 | AP176: ST047-YQ-1 | AQ176: 202603 | AR176: 3191.2323 | AS176: 办公室 | AT176: 游泳训练器材 | AU176: 游泳圈 | AV176: =IF(ISNUMBER(MATCH(C176,畅想结算中心!$A$2:$A$436,0)),"有","无") -> 有
A177: 李雅婷 | B177: 昊特赛九公司 | C177: HSB25M027-3 | D177: HSB25M027 | E177: RMS | F177: 主动开发 | G177: 2025-10-22 | H177: 2026-03-12 | I177: 3 | K177: 141 | L177: 2026-03-15 | M177: 306 | N177: 游泳装备 | O177: 游泳圈 | P177: 叶柳涵 | R177: 2601 | S177: OA 60DAYS | T177: 0 | U177: 18.21 | V177: 52.02 | W177: 15.6 | X177: 2492.37 | Y177: 0 | Z177: 0 | AA177: -85.83 | AB177: 290.08 | AC177: 0 | AD177: 0 | AE177: 0 | AF177: 0 | AG177: 0 | AH177: -589.08 | AI177: 16524 | AJ177: 1900.99 | AK177: 330.48 | AL177: 1862.32 | AM177: 0.1089 | AN177: -15725.57 | AO177: 英国2962 | AP177: ST048-SC-1 | AQ177: 202603 | AR177: 2299.9332 | AS177: 办公室 | AT177: 游泳训练器材 | AU177: 游泳圈 | AV177: =IF(ISNUMBER(MATCH(C177,畅想结算中心!$A$2:$A$436,0)),"有","无") -> 有
A178: 李雅婷 | B178: 昊特赛九公司 | C178: HSB25M027-4 | D178: HSB25M025 | E178: RMS | F178: 主动开发 | G178: 2025-10-22 | H178: 2026-03-19 | I178: 3 | K178: 148 | L178: 2026-01-16 | M178: 261 | N178: 游泳装备 | O178: 游泳圈 | P178: 叶柳涵 | R178: 2218.5 | S178: OA 60DAYS | T178: 0 | U178: 15.53 | V178: 44.37 | W178: 13.31 | X178: 2127.8 | Y178: 0 | Z178: 0 | AA178: -73.21 | AB178: 238.02 | AC178: 0 | AD178: 0 | AE178: 0 | AF178: 0 | AG178: 0 | AH178: -504.06 | AI178: 14094 | AJ178: 1621.43 | AK178: 281.88 | AL178: 1657.65 | AM178: 0.1131 | AN178: -13404.87 | AO178: 英国2962 | AP178: ST048-SC-1 | AQ178: 202603 | AR178: 2031.1703 | AS178: 办公室 | AT178: 游泳训练器材 | AU178: 游泳圈 | AV178: =IF(ISNUMBER(MATCH(C178,畅想结算中心!$A$2:$A$436,0)),"有","无") -> 有
A179: 李雅婷 | B179: 昊特赛九公司 | C179: HSB25M027-4 | D179: HSB25M025 | E179: RMS | F179: 主动开发 | G179: 2025-10-22 | H179: 2026-03-19 | I179: 3 | K179: 148 | L179: 2026-01-16 | M179: 872 | N179: 游泳装备 | O179: 游泳圈 | P179: 叶柳涵 | R179: 1831.2 | S179: OA 60DAYS | T179: 0 | U179: 12.82 | V179: 36.62 | W179: 10.99 | X179: 1756.33 | Y179: 0 | Z179: 0 | AA179: -60.43 | AB179: 271.1 | AC179: 0 | AD179: 0 | AE179: 0 | AF179: 0 | AG179: 0 | AH179: -416.07 | AI179: 10464 | AJ179: 1203.82 | AK179: 209.28 | AL179: 2351.95 | AM179: 0.1945 | AN179: -10080.96 | AO179: 英国2962 | AP179: ST047-YQ-1 | AQ179: 202603 | AR179: 2636.8991 | AS179: 办公室 | AT179: 游泳训练器材 | AU179: 游泳圈 | AV179: =IF(ISNUMBER(MATCH(C179,畅想结算中心!$A$2:$A$436,0)),"有","无") -> 有
... A227: 林元浩 | B227: 昊特赛九公司 | C227: HSE26C005-1 | D227: HSE26C005 | E227: LPP | F227: 主动开发 | G227: 2026-05-22 | H227: 2026-06-21 | I227: 6 | K227: 30 | L227: 2026-08-31 | M227: 804 | N227: 宠物运动 | O227: 猫抓板 | P227: 陈依萍 | R227: 2251.2 | S227: 100% T/T At sight of B/L copy | T227: 0 | U227: 15.76 | V227: 0 | W227: 0 | X227: 2185.44 | Y227: 0 | Z227: 0 | AA227: -15.76 | AB227: 1200 | AC227: 0 | AD227: 0 | AE227: 0 | AF227: 0 | AG227: 0 | AH227: -106.61 | AI227: 13426.8 | AJ227: 1544.68 | AK227: 268.54 | AL227: 1433.18 | AM227: 0.0969 | AN227: -13457.28 | AO227: 波兰749 | AP227: CS295-1 | AQ227: 202606 | AR227: 1701.7221 | AS227: 办公室 | AT227: 猫爬架及抓板 | AU227: 猫抓板 | AV227: =IF(ISNUMBER(MATCH(C227,畅想结算中心!$A$2:$A$436,0)),"有","无") -> 有
A228: 林元浩 | B228: 昊特赛九公司 | C228: HSE26L007-1 | D228: HSE26L007 | E228: LPP | F228: 主动开发 | G228: 2026-04-16 | H228: 2026-06-09 | I228: 6 | K228: 54 | L228: 2026-09-07 | M228: 1200 | N228: 宠物日用及玩具 | O228: 宠物阶梯 | P228: 陈依萍 | Q228: 陈依萍 | R228: 4920 | S228: 100% T/T At sight of B/L copy | T228: 0 | U228: 34.44 | V228: 0 | W228: 0 | X228: 4858.31 | Y228: 0 | Z228: 0 | AA228: -34.44 | AB228: 1089.92 | AC228: 0 | AD228: 0 | AE228: 0 | AF228: 0 | AG228: 0 | AH228: -233.02 | AI228: 33720 | AJ228: 3879.29 | AK228: 168.6 | AL228: 1772.1 | AM228: 0.0539 | AN228: -31332.26 | AO228: 波兰749 | AP228: PO-PN200-1001 | AQ228: 202606 | AR228: 1940.6992 | AS228: 办公室 | AT228: 宠物家具 | AU228: 宠物阶梯 | AV228: =IF(ISNUMBER(MATCH(C228,畅想结算中心!$A$2:$A$436,0)),"有","无") -> 有
A229: 林元浩 | B229: 昊特赛九公司 | C229: HSE26L007-1 | D229: HSE26L007 | E229: LPP | F229: 主动开发 | G229: 2026-04-16 | H229: 2026-06-09 | I229: 6 | K229: 54 | L229: 2026-09-07 | M229: 1002 | N229: 宠物日用及玩具 | O229: 宠物阶梯 | P229: 陈依萍 | Q229: 陈依萍 | R229: 4108.2 | S229: 100% T/T At sight of B/L copy | T229: 0 | U229: 28.76 | V229: 0 | W229: 0 | X229: 4056.69 | Y229: 0 | Z229: 0 | AA229: -28.76 | AB229: 910.08 | AC229: 0 | AD229: 0 | AE229: 0 | AF229: 0 | AG229: 0 | AH229: -194.59 | AI229: 28156.2 | AJ229: 3239.21 | AK229: 140.78 | AL229: 1479.71 | AM229: 0.0539 | AN229: -26162.43 | AO229: 波兰749 | AP229: PO-PN200-1001 | AQ229: 202606 | AR229: 1620.4916 | AS229: 办公室 | AT229: 宠物家具 | AU229: 宠物阶梯 | AV229: =IF(ISNUMBER(MATCH(C229,畅想结算中心!$A$2:$A$436,0)),"有","无") -> 有
A230: 蔡载君 | B230: 昊特赛九公司 | C230: HSG26E004-5 | D230: HSG26E003 | E230: LPP | F230: 主动开发 | G230: 2026-03-25 | H230: 2026-06-08 | I230: 6 | K230: 75 | L230: 2026-09-28 | M230: 800 | N230: 瑜伽和普拉提 | O230: 瑜伽负重袋 | P230: 陈依萍 | R230: 1136 | S230: OA 90 DAYS | T230: 0 | U230: 7.95 | V230: 0 | W230: 13.63 | X230: 1107.23 | Y230: 0 | Z230: 0 | AA230: -21.59 | AB230: 114.15 | AC230: 0 | AD230: 0 | AE230: 0 | AF230: 0 | AG230: 0 | AH230: -146.19 | AI230: 7040 | AJ230: 809.91 | AK230: 35.2 | AL230: 1118.05 | AM230: 0.1491 | AN230: -6433.29 | AO230: 波兰749 | AP230: PO-YP6001-001 | AQ230: 202606 | AR230: 1245.5489 | AS230: 客户第一组 | AT230: 其他瑜伽和普拉提用品 | AU230: 瑜伽负重袋 | AV230: =IF(ISNUMBER(MATCH(C230,畅想结算中心!$A$2:$A$436,0)),"有","无") -> 有
...

Sheet 畅想外销合同（外销合同导出）
A1: 分公司 | B1: 外销合同 | C1: 合同日期 | D1: 外 销 员 | E1: 客户简称 | F1: 预算毛利率 | G1: 外销币种 | H1: 已出运金额 | I1: 出运毛利率 | J1: 实际毛利额 | K1: 毛利额差异 | L1: 货值合计 | M1: 人民币货值 | N1: 毛利额 | O1: 首次内部交期 | P1: 外销交期 | Q1: 内部交期 | R1: 交付月份 | S1: 审核通过 | T1: 客户编号 | U1: 我方公司 | V1: 价格条款 | W1: 结汇方式 | X1: 已收定金 | Y1: 跟 单 员 | Z1: 审核状态 | AA1: 数量合计 | AB1: 核算美金合计 | AC1: 箱数合计 | AD1: 毛重合计 | AE1: 净重合计 | AF1: 体积合计 | AG1: 折合美金 | AH1: 货值总计 | AI1: 预计 汇率 | AJ1: 推广费 | AK1: 退 税 款 | AL1: 单证银行费 | AM1: 单证 费用 | AN1: 验货 费用 | AO1: 实收 FOB | AP1: 出口信用保险费 | AQ1: 毛 利 | AR1: 合同备注 | AS1: 情况说明(不会带到采购合同) | AT1: 是否监装 | AU1: 工艺单提供时间 | AV1: 柜型 | AW1: 信保抬头 | AX1: 资金成本 | AY1: 同意特采 | AZ1: 是否客验 | BA1: 组别 | BB1: 拼柜类型 | BC1: 客诉预提 | BD1: 账期利息 | BE1: 需要定金未到 | BF1: 分公司毛利 | BG1: 45天以上 | BH1: 数据来源 | BI1: 出厂总价合计 | BJ1: 流程启动次数 | BK1: 客验时间 | BL1: 定金情况说明 | BM1: 分公司毛利率 | BN1: 出厂RMB总价合计 | BO1: 重流原因 | BP1: 货柜结构 | BQ1: 出厂价_资金成本 | BR1: 出厂价_退税款 | BS1: 出厂价_实付 | BT1: 出厂价_毛利 | BU1: 出厂价_毛利率 | BV1: 出厂价_分公司毛利 | BW1: 出厂价_分公司毛利率 | BX1: 测价毛利率 | BY1: 是否斯帕克备库 | BZ1: 产品毛利 | CA1: 开发1 | CB1: 产品毛利率 | CC1: 预开船日期 | CD1: 开发2 | CE1: 逾期库存 | CF1: 逾期应收 | CG1: 生产周期 | CH1: 采购合计 | CI1: 信保抬头BR | CJ1: 内陆费计算 | CK1: RMB采购合计 | CL1: 内陆费增减 | CM1: 海运费 | CN1: 库存时间 | CO1: 流程进度 | CP1: 工作流 | CQ1: 关税 | CR1: 与畅想下单对比
A2: 昊特赛三公司 | B2: HSC26X031 | C2: 46174 | D2: 黄家辉 | E2: LPP | F2: 0.2334 | G2: USD | H2: =IFERROR(SUMIFS(畅想出运数据透视!$B$4:$B$500,畅想出运数据透视!$A$4:$A$500,B2),"0") -> 3101.78 | I2: =IFERROR(VLOOKUP(B2,CHOOSE({1,2},畅想出运数据透视!$A$4:$A$500,畅想出运数据透视!$D$4:$D$500),2,FALSE),"") -> 17.34% | L2: 8261.6 | M2: =L2*6.6 -> 54526.56 | N2: =M2*F2 -> 12726.499 | O2: 2026-07-13 | P2: 2026-07-20 | Q2: 2026-07-13 | R2: =MONTH(Q2) -> 7 | S2: 已通过 | T2: 波兰749 | U2: 宁波昊特赛进出口有限公司 | V2: FOB | W2: 100% T/T At sight of B/L copy | X2: 0 | Y2: 待审核 | Z2: 已审核 | AA2: 7564 | AB2: 0 | AC2: 153 | AD2: 1450.67 | AE2: 1338.87 | AF2: 12.7497 | AG2: 0 | AH2: 8261.6 | AI2: 6.6 | AJ2: 0 | AK2: 5193.78 | AL2: 20 | AM2: 50 | AN2: 0 | AO2: 8183.77 | AP2: 57.83 | AQ2: 12606.57 | AR2: PIMLQZ-20260626085 | AT2: 否 | AU2: 2026-06-26 | AV2: 40HQ | AW2: LPP S.A. | AX2: 560.44 | AY2: False | AZ2: 否 | BA2: 办公室 | BB2: 外部工厂 | BC2: 0 | BD2: 0 | BE2: False | BF2: 9340.35 | BG2: False | BI2: 45145.92 | BJ2: 1 | BL2: 无定金 | BM2: 0.1729 | BN2: 45145.92 | BP2: 无 | BQ2: 560.44 | BR2: 5193.78 | BS2: 40845.87 | BT2: 12606.57 | BU2: 0.2334 | BV2: 9340.35 | BW2: 0.1729 | BX2: 0 | BY2: 否 | BZ2: 14574.42 | CA2: False | CB2: 0.26729 | CC2: 2026-07-20 | CD2: False | CE2: 0 | CF2: 0 | CG2: 20 | CH2: 45145.92 | CJ2: 843.73 | CK2: 45145.92 | CL2: 0 | CM2: 0 | CN2: 4 | CO2: 财务-通过 | CP2: 已结束 | CQ2: 0 | CR2: =IF(COUNTIF('畅想下单（外销合同导出）'!$B$2:$B$100,B2)>0,"有","无") -> 有
A3: 昊特赛六公司 | B3: HSE26L009 | C3: 46174 | D3: 林元浩 | E3: HDT ASIA LATAM LIMITED | F3: 0.0936 | G3: USD | H3: =IFERROR(SUMIFS(畅想出运数据透视!$B$4:$B$500,畅想出运数据透视!$A$4:$A$500,B3),"0") -> 0 | I3: =IFERROR(VLOOKUP(B3,CHOOSE({1,2},畅想出运数据透视!$A$4:$A$500,畅想出运数据透视!$D$4:$D$500),2,FALSE),"") | L3: 3104.64 | M3: =L3*6.6 -> 20490.624 | N3: =M3*F3 -> 1917.9224 | O3: 2026-07-30 | P3: 2026-07-31 | Q3: 2026-07-30 | R3: =MONTH(Q3) -> 7 | S3: 已通过 | T3: 墨西哥744 | U3: 宁波昊特赛进出口有限公司 | V3: FOB | W3: 100% T/T At sight of B/L copy | X3: 0 | Y3: 待审核 | Z3: 已审核 | AA3: 2016 | AB3: 0 | AC3: 56 | AD3: 672 | AE3: 616 | AF3: 1.1368 | AG3: 0 | AH3: 3104.64 | AI3: 6.6 | AJ3: 0 | AK3: 2365.68 | AL3: 20 | AM3: 50 | AN3: 0 | AO3: 3062.91 | AP3: 21.73 | AQ3: 1892.44 | AR3: 此票客户发上海保税仓，无港内运杂费等额外费用。且后续会跟其他订单一起进仓 节约运费。 | AS3: PIMLQZ-20260624084 毛利前置流程 | AT3: 否 | AU3: 2026-07-05 | AV3: LCL | AW3: HDT ASIA LATAM LIMITED | AX3: 0 | AY3: False | AZ3: 是 | BA3: 办公室 | BB3: 自拼 | BC3: 0 | BD3: 0 | BE3: False | BF3: 0 | BG3: False | BI3: 20563.2 | BJ3: 1 | BK3: 2026-07-25 | BL3: 无 | BM3: 0 | BN3: 20563.2 | BP3: 保税仓 | BQ3: 0 | BR3: 2365.68 | BS3: 18322.75 | BT3: 1892.44 | BU3: 0.0936 | BV3: 0 | BW3: 0 | BX3: 0 | BY3: 否 | BZ3: 2293.1 | CA3: False | CB3: 0.11191 | CC3: 2026-07-29 | CD3: False | CE3: 0 | CF3: 0 | CG3: 40 | CH3: 20563.2 | CJ3: 75.23 | CK3: 20563.2 | CL3: 0 | CM3: 0 | CN3: -6 | CO3: 财务经理-通过 | CP3: 已结束 | CQ3: 0 | CR3: =IF(COUNTIF('畅想下单（外销合同导出）'!$B$2:$B$100,B3)>0,"有","无") -> 有
A4: 昊特赛六公司 | B4: HSE20L009 | C4: 46174 | D4: 林元浩 | E4: HDT ASIA LATAM LIMITED | F4: 0.0936 | G4: USD | H4: =IFERROR(SUMIFS(畅想出运数据透视!$B$4:$B$500,畅想出运数据透视!$A$4:$A$500,B4),"0") -> 0 | I4: =IFERROR(VLOOKUP(B4,CHOOSE({1,2},畅想出运数据透视!$A$4:$A$500,畅想出运数据透视!$D$4:$D$500),2,FALSE),"") | L4: 3104.64 | M4: =L4*6.6 -> 20490.624 | N4: =M4*F4 -> 1917.9224 | O4: 2026-07-30 | P4: 2026-07-31 | Q4: 2026-07-30 | R4: =MONTH(Q4) -> 7 | S4: 不通过 | T4: 墨西哥744 | U4: 宁波昊特赛进出口有限公司 | V4: FOB | W4: 100% T/T At sight of B/L copy | X4: 0 | Y4: 待审核 | Z4: 待审核 | AA4: 2016 | AB4: 0 | AC4: 56 | AD4: 672 | AE4: 616 | AF4: 1.1368 | AG4: 0 | AH4: 3104.64 | AI4: 6.6 | AJ4: 0 | AK4: 2365.68 | AL4: 20 | AM4: 50 | AN4: 0 | AO4: 3062.91 | AP4: 21.73 | AQ4: 1892.44 | AR4: 此票客户发上海保税仓，无港内运杂费等额外费用。且后续会跟其他订单一起进仓 节约运费。 | AS4: PIMLQZ-20260624084 毛利前置流程 | AT4: 否 | AU4: 2026-06-30 | AV4: LCL | AW4: HDT ASIA LATAM LIMITED | AX4: 0 | AY4: False | AZ4: 是 | BA4: 办公室 | BB4: 自拼 | BC4: 0 | BD4: 0 | BE4: False | BF4: 0 | BG4: False | BI4: 20563.2 | BJ4: 0 | BK4: 2026-07-25 | BL4: 无 | BM4: 0 | BN4: 20563.2 | BP4: 保税仓 | BQ4: 0 | BR4: 2365.68 | BS4: 18322.75 | BT4: 1892.44 | BU4: 0.0936 | BV4: 0 | BW4: 0 | BX4: 0 | BY4: 否 | BZ4: 2293.1 | CA4: False | CB4: 0.11191 | CD4: False | CE4: 0 | CF4: 0 | CG4: 0 | CH4: 20563.2 | CJ4: 75.23 | CK4: 20563.2 | CL4: 0 | CM4: 0 | CN4: 0 | CP4: 未启动 | CQ4: 0 | CR4: =IF(COUNTIF('畅想下单（外销合同导出）'!$B$2:$B$100,B4)>0,"有","无") -> 有
A5: 昊特赛十公司 | B5: HSJ26R005-4 | C5: 46174 | D5: 夏煜昕 | E5: DGL-HT | F5: 0.0855 | G5: USD | H5: =IFERROR(SUMIFS(畅想出运数据透视!$B$4:$B$500,畅想出运数据透视!$A$4:$A$500,B5),"0") -> 108683.5 | I5: =IFERROR(VLOOKUP(B5,CHOOSE({1,2},畅想出运数据透视!$A$4:$A$500,畅想出运数据透视!$D$4:$D$500),2,FALSE),"") -> 15.94% | L5: 109500 | M5: =L5*6.6 -> 722700 | N5: =M5*F5 -> 61790.85 | O5: 2026-07-20 | P5: 2026-07-25 | Q5: 2026-07-20 | R5: =MONTH(Q5) -> 7 | S5: 已通过 | T5: 美国0830 | U5: 宁波昊特赛进出口有限公司 | V5: DDP | W5: 100% T/T Before shipment | X5: 0 | Y5: 待审核 | Z5: 已审核 | AA5: 30000 | AB5: 0 | AC5: 5000 | AD5: 19000 | AE5: 15000 | AF5: 39.5 | AG5: 0 | AH5: 109500 | AI5: 6.6 | AJ5: 0 | AK5: 67300.88 | AL5: 219 | AM5: 50 | AN5: 1000 | AO5: 108514.5 | AP5: 766.5 | AQ5: 61230.98 | AS5: PI毛利前置审批已完成，流程编号：PIMLQZ-20260611078 | AT5: 否 | AU5: 2026-06-22 | AV5: LCL | AX5: 2925 | AY5: False | AZ5: 否 | BA5: 办公室 | BB5: 自拼 | BC5: 0 | BD5: 0 | BE5: False | BF5: 36738.59 | BG5: False | BI5: 585000 | BJ5: 1 | BL5: / | BM5: 0.0513 | BN5: 585000 | BP5: LCL | BQ5: 2925 | BR5: 67300.88 | BS5: 652039.72 | BT5: 61230.98 | BU5: 0.0855 | BV5: 36738.59 | BW5: 0.0513 | BX5: 0 | BY5: 否 | BZ5: 205000.88 | CA5: True | CB5: 0.28366 | CC5: 2026-07-25 | CD5: False | CE5: 0 | CF5: 0 | CG5: 30 | CH5: 585000 | CJ5: 2613.97 | CK5: 585000 | CL5: 130676.63 | CM5: 0 | CN5: 3 | CO5: 财务经理-通过 | CP5: 已结束 | CQ5: 0 | CR5: =IF(COUNTIF('畅想下单（外销合同导出）'!$B$2:$B$100,B5)>0,"有","无") -> 有
A6: 昊特赛三公司 | B6: HSC26X027 | C6: 46174 | D6: 熊环英 | E6: URBAN IMPORTS | F6: 0.2024 | G6: USD | H6: =IFERROR(SUMIFS(畅想出运数据透视!$B$4:$B$500,畅想出运数据透视!$A$4:$A$500,B6),"0") -> 8010.65 | I6: =IFERROR(VLOOKUP(B6,CHOOSE({1,2},畅想出运数据透视!$A$4:$A$500,畅想出运数据透视!$D$4:$D$500),2,FALSE),"") -> 26.04% | L6: 13884 | M6: =L6*6.6 -> 91634.4 | N6: =M6*F6 -> 18546.803 | O6: 2026-07-30 | P6: 2026-07-30 | Q6: 2026-07-30 | R6: =MONTH(Q6) -> 7 | S6: 已通过 | T6: 美国5529 | U6: 宁波昊特赛进出口有限公司 | V6: FOB | W6: OA 60DAYS | X6: 0 | Y6: 待审核 | Z6: 已审核 | AA6: 27360 | AB6: 0 | AC6: 1640 | AD6: 3968.48 | AE6: 3396.48 | AF6: 43.83 | AG6: 0 | AH6: 13884 | AI6: 6.6 | AJ6: 0 | AK6: 8906.96 | AL6: 27.77 | AM6: 50 | AN6: 0 | AO6: 13759.04 | AP6: 97.19 | AQ6: 18380.69 | AS6: PIMLQZ-20260622083 | AT6: 否 | AU6: 2026-06-28 | AV6: 45HQ | AX6: 505.19 | AY6: False | AZ6: 否 | BA6: 客户第一组 | BB6: 自拼 | BC6: 0 | BD6: 458.17 | BE6: False | BF6: 12808.94 | BG6: False | BI6: 77422.08 | BJ6: 2 | BL6: 无 | BM6: 0.1411 | BN6: 77422.08 | BO6: 修改替换工厂 | BP6: 无 | BQ6: 505.19 | BR6: 8906.96 | BS6: 71465.63 | BT6: 18380.69 | BU6: 0.2024 | BV6: 12808.94 | BW6: 0.1411 | BX6: 0 | BY6: 否 | BZ6: 23119.28 | CA6: False | CB6: 0.252299 | CC6: 2026-08-05 | CD6: False | CE6: 0 | CF6: 0 | CG6: 35 | CH6: 77422.08 | CJ6: 2900.51 | CK6: 77422.08 | CL6: 0 | CM6: 0 | CN6: 7 | CO6: 财务-通过 | CP6: 已结束 | CQ6: 0 | CR6: =IF(COUNTIF('畅想下单（外销合同导出）'!$B$2:$B$100,B6)>0,"有","无") -> 有
A7: 昊特赛六公司 | B7: HSE26L008 | C7: 46174 | D7: 林元浩 | E7: LPP | F7: 0.0913 | G7: USD | H7: =IFERROR(SUMIFS(畅想出运数据透视!$B$4:$B$500,畅想出运数据透视!$A$4:$A$500,B7),"0") -> 0 | I7: =IFERROR(VLOOKUP(B7,CHOOSE({1,2},畅想出运数据透视!$A$4:$A$500,畅想出运数据透视!$D$4:$D$500),2,FALSE),"") | L7: 29520 | M7: =L7*6.6 -> 194832 | N7: =M7*F7 -> 17788.162 | O7: 2027-04-13 | P7: 2027-04-19 | Q7: 2027-04-13 | R7: =MONTH(Q7) -> 4 | S7: 已通过 | T7: 波兰749 | U7: 宁波昊特赛进出口有限公司 | V7: FOB | W7: 100% T/T At sight of B/L copy | X7: 0 | Y7: 待审核 | Z7: 已审核 | AA7: 7200 | AB7: 0 | AC7: 1200 | AD7: 7680 | AE7: 6000 | AF7: 65.28 | AG7: 0 | AH7: 29520 | AI7: 6.6 | AJ7: 0 | AK7: 22116.12 | AL7: 59.04 | AM7: 50 | AN7: 0 | AO7: 29254.32 | AP7: 206.64 | AQ7: 17623.43 | AT7: 否 | AU7: 2026-07-15 | AV7: LCL | AW7: LPP S.A. | AX7: 961.2 | AY7: False | AZ7: 否 | BA7: 办公室 | BB7: 自拼 | BC7: 0 | BD7: 0 | BE7: False | BF7: 17623.44 | BG7: True | BI7: 192240 | BJ7: 1 | BL7: 无定金 | BM7: 0.0913 | BN7: 192240 | BP7: 客户自拼LCL | BQ7: 961.2 | BR7: 22116.12 | BS7: 174493.88 | BT7: 17623.43 | BU7: 0.0913 | BV7: 17623.44 | BW7: 0.0913 | BX7: 0 | BY7: 否 | BZ7: 24708.12 | CA7: False | CB7: 0.126818 | CC7: 2027-04-10 | CD7: False | CE7: 0 | CF7: 0 | CG7: 45 | CH7: 192240 | CJ7: 4320 | CK7: 192240 | CL7: 0 | CM7: 0 | CN7: 251 | CO7: 财务经理-通过 | CP7: 已结束 | CQ7: 0 | CR7: =IF(COUNTIF('畅想下单（外销合同导出）'!$B$2:$B$100,B7)>0,"有","无") -> 有
A8: 昊特赛十公司 | B8: HSJ26R005-3 | C8: 46174 | D8: 夏煜昕 | E8: DGL-HT | F8: 0.0748 | G8: USD | H8: =IFERROR(SUMIFS(畅想出运数据透视!$B$4:$B$500,畅想出运数据透视!$A$4:$A$500,B8),"0") -> 87184.7 | I8: =IFERROR(VLOOKUP(B8,CHOOSE({1,2},畅想出运数据透视!$A$4:$A$500,畅想出运数据透视!$D$4:$D$500),2,FALSE),"") -> 4.86% | L8: 143220 | M8: =L8*6.6 -> 945252 | N8: =M8*F8 -> 70704.85 | O8: 2026-07-20 | P8: 2026-07-25 | Q8: 2026-07-20 | R8: =MONTH(Q8) -> 7 | S8: 已通过 | T8: 美国0830 | U8: 宁波昊特赛进出口有限公司 | V8: DDP | W8: 100% T/T Before shipment | X8: 0 | Y8: 待审核 | Z8: 已审核 | AA8: 42000 | AB8: 0 | AC8: 7000 | AD8: 55000 | AE8: 51000 | AF8: 172.1 | AG8: 0 | AH8: 143220 | AI8: 6.6 | AJ8: 0 | AK8: 92426.55 | AL8: 286.44 | AM8: 50 | AN8: 1500 | AO8: 141931.02 | AP8: 1002.54 | AQ8: 70110.37 | AS8: PI毛利前置审批已完成 流程编号：PIMLQZ-20260611078 销售合同变更已完成，流程编号HTBG-202606252528 | AT8: 否 | AU8: 2026-06-16 | AV8: LCL | AX8: 13404 | AY8: False | AZ8: 否 | BA8: 办公室 | BB8: 自拼 | BC8: 0 | BD8: 0 | BE8: False | BF8: 42066.22 | BG8: False | BI8: 803400 | BJ8: 2 | BL8: / | BM8: 0.0449 | BN8: 803400 | BO8: 客户新增外箱箱规与封箱胶带要求，订单成本增加 | BP8: LCL | BQ8: 13404 | BR8: 92426.55 | BS8: 853230.36 | BT8: 70110.37 | BU8: 0.0748 | BV8: 42066.22 | BW8: 0.0449 | BX8: 0 | BY8: 否 | BZ8: 234278.55 | CA8: False | CB8: 0.247848 | CC8: 2026-07-24 | CD8: False | CE8: 0 | CF8: 0 | CG8: 30 | CH8: 803400 | CJ8: 11388.97 | CK8: 803400 | CL8: 129317.94 | CM8: 0 | CN8: 8 | CO8: 财务经理-通过 | CP8: 已结束 | CQ8: 0 | CR8: =IF(COUNTIF('畅想下单（外销合同导出）'!$B$2:$B$100,B8)>0,"有","无") -> 有
A9: 昊特赛十公司 | B9: HSJ26R005-2 | C9: 46174 | D9: 夏煜昕 | E9: DGL-HT | F9: 0.0861 | G9: USD | H9: =IFERROR(SUMIFS(畅想出运数据透视!$B$4:$B$500,畅想出运数据透视!$A$4:$A$500,B9),"0") -> 76537.76 | I9: =IFERROR(VLOOKUP(B9,CHOOSE({1,2},畅想出运数据透视!$A$4:$A$500,畅想出运数据透视!$D$4:$D$500),2,FALSE),"") -> 10.92% | L9: 77178 | M9: =L9*6.6 -> 509374.8 | N9: =M9*F9 -> 43857.17 | O9: 2026-07-13 | P9: 2026-07-15 | Q9: 2026-07-13 | R9: =MONTH(Q9) -> 7 | S9: 已通过 | T9: 美国0830 | U9: 宁波昊特赛进出口有限公司 | V9: FOB | W9: 100% T/T Before shipment | X9: 0 | Y9: 待审核 | Z9: 已审核 | AA9: 33888 | AB9: 0 | AC9: 3486 | AD9: 14371.72 | AE9: 11490.4 | AF9: 61.1926 | AG9: 0 | AH9: 77178 | AI9: 6.6 | AJ9: 0 | AK9: 58177.23 | AL9: 154.36 | AM9: 50 | AN9: 1000 | AO9: 76483.39 | AP9: 540.25 | AQ9: 43458.07 | AS9: PI毛利前置审批已完成 流程编号：PIMLQZ-20260611078 | AT9: 否 | AU9: 2026-06-16 | AV9: LCL | AX9: 3565.16 | AY9: False | AZ9: 否 | BA9: 办公室 | BB9: 自拼 | BC9: 0 | BD9: 0 | BE9: False | BF9: 15895.12 | BG9: False | BI9: 505694.4 | BJ9: 1 | BL9: / | BM9: 0.0315 | BN9: 505694.4 | BP9: LCL | BQ9: 3565.16 | BR9: 58177.23 | BS9: 457767.17 | BT9: 43458.07 | BU9: 0.0861 | BV9: 15895.12 | BW9: 0.0315 | BX9: 0 | BY9: 否 | BZ9: 61857.63 | CA9: True | CB9: 0.121438 | CC9: 2026-07-20 | CD9: False | CE9: 0 | CF9: 0 | CG9: 30 | CH9: 505694.4 | CJ9: 4049.51 | CK9: 505694.4 | CL9: 5150.49 | CM9: 0 | CN9: 4 | CO9: 财务经理-通过 | CP9: 已结束 | CQ9: 0 | CR9: =IF(COUNTIF('畅想下单（外销合同导出）'!$B$2:$B$100,B9)>0,"有","无") -> 有
A10: 昊特赛九公司 | B10: HSI26L009 | C10: 46174 | D10: 李雅婷 | E10: Joinco | F10: 0.0569 | G10: USD | H10: =IFERROR(SUMIFS(畅想出运数据透视!$B$4:$B$500,畅想出运数据透视!$A$4:$A$500,B10),"0") -> 0 | I10: =IFERROR(VLOOKUP(B10,CHOOSE({1,2},畅想出运数据透视!$A$4:$A$500,畅想出运数据透视!$D$4:$D$500),2,FALSE),"") | L10: 122100 | M10: =L10*6.6 -> 805860 | N10: =M10*F10 -> 45853.434 | O10: 2026-09-15 | P10: 2026-09-15 | Q10: 2026-09-15 | R10: =MONTH(Q10) -> 9 | S10: 已通过 | T10: 波兰700 | U10: 宁波昊特赛进出口有限公司 | V10: FOB | W10: OA 75 Days | X10: 0 | Y10: 待审核 | Z10: 已审核 | AA10: 145000 | AB10: 0 | AC10: 7500 | AD10: 30000 | AE10: 26250 | AF10: 155.25 | AG10: 0 | AH10: 122100 | AI10: 6.6 | AJ10: 0 | AK10: 94986.26 | AL10: 244.2 | AM10: 50 | AN10: 2000 | AO10: 121001.1 | AP10: 854.7 | AQ10: 45447.42 | AS10: 毛利前置合同号：PIMLQZ-20260616079 | AT10: 否 | AU10: 2026-07-20 | AV10: 40HQ | AW10: JOINCO IMPORTACAO E EXPORTACAO LDA | AX10: 4128.25 | AY10: False | AZ10: 是 | BA10: 办公室 | BB10: 自拼 | BC10: 0 | BD10: 6043.95 | BE10: False | BF10: 45447.4 | BG10: True | BI10: 825650 | BJ10: 2 | BK10: 2026-09-10 | BL10: 无，客户实际账期TT30天，无账期利息 | BM10: 0.0569 | BN10: 825650 | BO10: 更新工厂产品线 | BP10: 无 | BQ10: 4128.25 | BR10: 94986.26 | BS10: 742987.64 | BT10: 45447.42 | BU10: 0.0569 | BV10: 45447.4 | BW10: 0.0569 | BX10: 0 | BY10: 否 | BZ10: 75196.26 | CA10: False | CB10: 0.093312 | CC10: 2026-09-15 | CD10: False | CE10: 0 | CF10: 0 | CG10: 75 | CH10: 825650 | CJ10: 10273.9 | CK10: 825650 | CL10: 0 | CM10: 0 | CN10: 14 | CO10: 财务经理-通过 | CP10: 已结束 | CQ10: 0 | CR10: =IF(COUNTIF('畅想下单（外销合同导出）'!$B$2:$B$100,B10)>0,"有","无") -> 有
A11: 昊特赛十公司 | B11: HSJ26R005-1 | C11: 46174 | D11: 夏煜昕 | E11: DGL-HT | F11: 0.0551 | G11: USD | H11: =IFERROR(SUMIFS(畅想出运数据透视!$B$4:$B$500,畅想出运数据透视!$A$4:$A$500,B11),"0") -> 11425.58 | I11: =IFERROR(VLOOKUP(B11,CHOOSE({1,2},畅想出运数据透视!$A$4:$A$500,畅想出运数据透视!$D$4:$D$500),2,FALSE),"") -> -10.76% | J11: =I11*M11 -> -8206.9498 | K11: =J11-N11 -> -12409.579 | L11: 11556.48 | M11: =L11*6.6 -> 76272.768 | N11: =M11*F11 -> 4202.6295 | O11: 2026-06-20 | P11: 2026-06-21 | Q11: 2026-06-20 | R11: =MONTH(Q11) -> 6 | S11: 已通过 | T11: 美国0830 | U11: 宁波昊特赛进出口有限公司 | V11: DDP | W11: 100% T/T Before shipment | X11: 0 | Y11: 待审核 | Z11: 已审核 | AA11: 2496 | AB11: 0 | AC11: 104 | AD11: 1560 | AE11: 1612 | AF11: 4.3472 | AG11: 0 | AH11: 11556.48 | AI11: 6.6 | AJ11: 0 | AK11: 7035.19 | AL11: 23.11 | AM11: 50 | AN11: 0 | AO11: 11452.47 | AP11: 80.9 | AQ11: 4162.08 | AS11: PI毛利前置审批已完成 流程编号：PIMLQZ-20260611078 | AT11: 否 | AU11: 2026-06-12 | AV11: LCL | AX11: 1223.04 | AY11: False | AZ11: 否 | BA11: 办公室 | BB11: 自拼 | BC11: 0 | BD11: 0 | BE11: False | BF11: 2497.23 | BG11: False | BI11: 61152 | BJ11: 1 | BL11: / | BM11: 0.033 | BN11: 61152 | BO11: 修改海运费 | BP11: LCL | BQ11: 1223.04 | BR11: 7035.19 | BS11: 70201.21 | BT11: 4162.08 | BU11: 0.0551 | BV11: 2497.23 | BW11: 0.033 | BX11: 0 | BY11: 否 | BZ11: 22155.96 | CA11: False | CB11: 0.290483 | CC11: 2026-06-24 | CD11: False | CE11: 0 | CF11: 0 | CG11: 9 | CH11: 61152 | CJ11: 287.68 | CK11: 61152 | CL11: 15746.72 | CM11: 0 | CN11: 3 | CO11: 财务经理-通过 | CP11: 已结束 | CQ11: 0 | CR11: =IF(COUNTIF('畅想下单（外销合同导出）'!$B$2:$B$100,B11)>0,"有","无") -> 有
A12: 昊特赛三公司 | B12: HSC26H013 | C12: 46174 | D12: 黄家辉 | E12: LPP | F12: 0.1691 | G12: USD | H12: =IFERROR(SUMIFS(畅想出运数据透视!$B$4:$B$500,畅想出运数据透视!$A$4:$A$500,B12),"0") -> 1798.48 | I12: =IFERROR(VLOOKUP(B12,CHOOSE({1,2},畅想出运数据透视!$A$4:$A$500,畅想出运数据透视!$D$4:$D$500),2,FALSE),"") -> 11.08% | L12: 5896.8 | M12: =L12*6.6 -> 38918.88 | N12: =M12*F12 -> 6581.1826 | O12: 2026-06-22 | P12: 2026-06-22 | Q12: 2026-06-22 | R12: =MONTH(Q12) -> 6 | S12: 已通过 | T12: 波兰749 | U12: 宁波昊特赛进出口有限公司 | V12: FOB | W12: OA 90 DAYS | X12: 0 | Y12: 待审核 | Z12: 已审核 | AA12: 4536 | AB12: 0 | AC12: 189 | AD12: 2797.2 | AE12: 2929.5 | AF12: 10.7352 | AG12: 0 | AH12: 5896.8 | AI12: 6.6 | AJ12: 0 | AK12: 3965.99 | AL12: 20 | AM12: 50 | AN12: 0 | AO12: 5835.52 | AP12: 41.28 | AQ12: 6512.49 | AR12: PIMLQZ-20260608077 | AT12: 否 | AU12: 2026-06-09 | AV12: 40HQ | AW12: LPP S.A. | AX12: 344.74 | AY12: False | AZ12: 否 | BA12: 办公室 | BB12: 外部工厂 | BC12: 0 | BD12: 389.19 | BE12: False | BF12: 0 | BG12: False | BI12: 34473.6 | BJ12: 1 | BL12: 无定金 | BM12: 0 | BN12: 34473.6 | BP12: 、 | BQ12: 344.74 | BR12: 3965.99 | BS12: 31268.03 | BT12: 6512.49 | BU12: 0.1691 | BV12: 0 | BW12: 0 | BX12: 0 | BY12: 否 | BZ12: 8411.27 | CA12: False | CB12: 0.216123 | CC12: 2026-06-29 | CD12: False | CE12: 0 | CF12: 0 | CG12: 20 | CH12: 34473.6 | CJ12: 710.42 | CK12: 34473.6 | CL12: 0 | CM12: 0 | CN12: 0 | CO12: 财务-通过 | CP12: 已结束 | CQ12: 0 | CR12: =IF(COUNTIF('畅想下单（外销合同导出）'!$B$2:$B$100,B12)>0,"有","无") -> 有
A13: 昊特赛三公司 | B13: HSC26X022-2 | C13: 46174 | D13: 熊环英 | E13: URBAN IMPORTS | F13: 0.1366 | G13: USD | H13: =IFERROR(SUMIFS(畅想出运数据透视!$B$4:$B$500,畅想出运数据透视!$A$4:$A$500,B13),"0") -> 9064.93 | I13: =IFERROR(VLOOKUP(B13,CHOOSE({1,2},畅想出运数据透视!$A$4:$A$500,畅想出运数据透视!$D$4:$D$500),2,FALSE),"") -> 15.55% | L13: 9193.2 | M13: =L13*6.6 -> 60675.12 | N13: =M13*F13 -> 8288.2214 | O13: 2026-07-20 | P13: 2026-07-30 | Q13: 2026-07-20 | R13: =MONTH(Q13) -> 7 | S13: 已通过 | T13: 美国5529 | U13: 宁波昊特赛进出口有限公司 | V13: FOB | W13: OA 60DAYS | X13: 0 | Y13: 待审核 | Z13: 已审核 | AA13: 7608 | AB13: 0 | AC13: 253 | AD13: 707.76 | AE13: 570.53 | AF13: 8.5202 | AG13: 0 | AH13: 9193.2 | AI13: 6.6 | AJ13: 0 | AK13: 6554.21 | AL13: 20 | AM13: 50 | AN13: 0 | AO13: 9108.85 | AP13: 64.35 | AQ13: 8214.47 | AS13: PIMLQZ-20260605076 | AT13: 否 | AU13: 2026-06-13 | AV13: LCL | AX13: 569.71 | AY13: False | AZ13: 否 | BA13: 客户第一组 | BB13: 自拼 | BC13: 0 | BD13: 303.38 | BE13: False | BF13: 0 | BG13: False | BI13: 56971.2 | BJ13: 2 | BL13: 无 | BM13: 0 | BN13: 56971.2 | BO13: 更改50014和50015的价格 | BP13: 无 | BQ13: 569.71 | BR13: 6554.21 | BS13: 51030.83 | BT13: 8214.47 | BU13: 0.1366 | BV13: 0 | BW13: 0 | BX13: 0 | BY13: 否 | BZ13: 10258.14 | CA13: False | CB13: 0.169067 | CC13: 2026-07-30 | CD13: False | CE13: 0 | CF13: 0 | CG13: 45 | CH13: 56971.2 | CJ13: 563.84 | CK13: 56971.2 | CL13: 0 | CM13: 0 | CN13: 7 | CO13: 财务-通过 | CP13: 已结束 | CQ13: 0 | CR13: =IF(COUNTIF('畅想下单（外销合同导出）'!$B$2:$B$100,B13)>0,"有","无") -> 有
A14: 昊特赛三公司 | B14: HSC26X024 | C14: 46174 | D14: 熊环英 | E14: LPP | F14: 0.2004 | G14: USD | H14: =IFERROR(SUMIFS(畅想出运数据透视!$B$4:$B$500,畅想出运数据透视!$A$4:$A$500,B14),"0") -> 2929 | I14: =IFERROR(VLOOKUP(B14,CHOOSE({1,2},畅想出运数据透视!$A$4:$A$500,畅想出运数据透视!$D$4:$D$500),2,FALSE),"") -> 23.19% | L14: 3000 | M14: =L14*6.6 -> 19800 | N14: =M14*F14 -> 3967.92 | O14: 2026-07-20 | P14: 2026-07-27 | Q14: 2026-07-20 | R14: =MONTH(Q14) -> 7 | S14: 已通过 | T14: 波兰749 | U14: 宁波昊特赛进出口有限公司 | V14: FOB | W14: 100% T/T At sight of B/L copy | X14: 0 | Y14: 待审核 | Z14: 已审核 | AA14: 1000 | AB14: 0 | AC14: 50 | AD14: 430 | AE14: 400 | AF14: 3.73 | AG14: 0 | AH14: 3000 | AI14: 6.6 | AJ14: 0 | AK14: 1840.71 | AL14: 20 | AM14: 50 | AN14: 0 | AO14: 2959 | AP14: 21 | AQ14: 3913.27 | AS14: PI前置流程编号：PIMLQZ-20260604074 | AT14: 否 | AU14: 2026-06-25 | AV14: LCL | AW14: LPP S.A. | AX14: 160 | AY14: False | AZ14: 否 | BA14: 客户第一组 | BB14: 外部工厂 | BC14: 0 | BD14: 0 | BE14: False | BF14: 0 | BG14: True | BI14: 16000 | BJ14: 1 | BL14: 无 | BM14: 0 | BN14: 16000 | BP14: 无 | BQ14: 160 | BR14: 1840.71 | BS14: 15456.13 | BT14: 3913.27 | BU14: 0.2004 | BV14: 0 | BW14: 0 | BX14: 0 | BY14: 否 | BZ14: 5640.71 | CA14: False | CB14: 0.284884 | CC14: 2026-07-27 | CD14: False | CE14: 0 | CF14: 0 | CG14: 35 | CH14: 16000 | CJ14: 246.84 | CK14: 16000 | CL14: 1000 | CM14: 0 | CN14: 18 | CO14: 财务-通过 | CP14: 已结束 | CQ14: 0 | CR14: =IF(COUNTIF('畅想下单（外销合同导出）'!$B$2:$B$100,B14)>0,"有","无") -> 有
A15: 昊特赛三公司 | B15: HSC26X025 | C15: 46174 | D15: 熊环英 | E15: DM | F15: 0.0703 | G15: USD | H15: =IFERROR(SUMIFS(畅想出运数据透视!$B$4:$B$500,畅想出运数据透视!$A$4:$A$500,B15),"0") -> 0 | I15: =IFERROR(VLOOKUP(B15,CHOOSE({1,2},畅想出运数据透视!$A$4:$A$500,畅想出运数据透视!$D$4:$D$500),2,FALSE),"") | L15: 47395.59 | M15: =L15*6.6 -> 312810.89 | N15: =M15*F15 -> 21990.606 | O15: 2026-10-31 | P15: 2026-11-08 | Q15: 2026-10-31 | R15: =MONTH(Q15) -> 10 | S15: 已通过 | T15: 加拿大925 | U15: 宁波昊特赛进出口有限公司 | V15: FOB | W15: 100% T/T At sight of B/L copy | X15: 0 | Y15: 待审核 | Z15: 已审核 | AA15: 164568 | AB15: 0 | AC15: 6857 | AD15: 11656.9 | AE15: 9462.66 | AF15: 95.3123 | AG15: 0 | AH15: 47395.59 | AI15: 6.6 | AJ15: 0 | AK15: 35971.95 | AL15: 94.79 | AM15: 50 | AN15: 0 | AO15: 46969.03 | AP15: 331.77 | AQ15: 21804.13 | AS15: PI前置流程编号：PIMLQZ-20260604075 | AT15: 否 | AU15: 2026-08-25 | AV15: LCL | AW15: DOLLARAMA | AX15: 3126.79 | AY15: False | AZ15: 否 | BA15: 客户第一组 | BB15: 外部工厂 | BC15: 0 | BD15: 0 | BE15: False | BF15: 21804.12 | BG15: True | BI15: 312679.2 | BJ15: 1 | BL15: 无订金 | BM15: 0.0703 | BN15: 312679.2 | BP15: 无 | BQ15: 3126.79 | BR15: 35971.95 | BS15: 285064.68 | BT15: 21804.13 | BU15: 0.0703 | BV15: 21804.12 | BW15: 0.0703 | BX15: 0 | BY15: 否 | BZ15: 36103.65 | CA15: False | CB15: 0.115417 | CC15: 2026-11-08 | CD15: False | CE15: 0 | CF15: 0 | CG15: 110 | CH15: 312679.2 | CJ15: 6307.43 | CK15: 312679.2 | CL15: 2000 | CM15: 0 | CN15: 47 | CO15: 财务经理-通过 | CP15: 已结束 | CQ15: 0 | CR15: =IF(COUNTIF('畅想下单（外销合同导出）'!$B$2:$B$100,B15)>0,"有","无") -> 有
A16: 昊特赛九公司 | B16: HSI26L008 | C16: 46174 | D16: 李雅婷 | E16: LPP | F16: 0.123 | G16: USD | H16: =IFERROR(SUMIFS(畅想出运数据透视!$B$4:$B$500,畅想出运数据透视!$A$4:$A$500,B16),"0") -> 1452.96 | I16: =IFERROR(VLOOKUP(B16,CHOOSE({1,2},畅想出运数据透视!$A$4:$A$500,畅想出运数据透视!$D$4:$D$500),2,FALSE),"") -> 12.73% | J16: =I16*M16 -> 1330.0385 | K16: =J16-N16 -> 44.926675 | L16: 1583.04 | M16: =L16*6.6 -> 10448.064 | N16: =M16*F16 -> 1285.1119 | O16: 2026-08-10 | P16: 2026-08-10 | Q16: 2026-08-10 | R16: =MONTH(Q16) -> 8 | S16: 已通过 | T16: 波兰749 | U16: 宁波昊特赛进出口有限公司 | V16: FOB | W16: OA 90 DAYS | X16: 0 | Y16: 待审核 | Z16: 已审核 | AA16: 1632 | AB16: 0 | AC16: 68 | AD16: 503.2 | AE16: 435.2 | AF16: 6.0248 | AG16: 0 | AH16: 1583.04 | AI16: 6.6 | AJ16: 0 | AK16: 0 | AL16: 20 | AM16: 50 | AN16: 0 | AO16: 1551.96 | AP16: 11.08 | AQ16: 1260.23 | AR16: 毛利前置流程编号：PIMLQZ-20260601073 | AT16: 否 | AU16: 2026-06-05 | AV16: LCL | AW16: LPP S.A. | AX16: 77.52 | AY16: False | AZ16: 否 | BA16: 办公室 | BB16: 外部工厂 | BC16: 0 | BD16: 104.48 | BE16: False | BF16: 0 | BG16: True | BI16: 7752 | BJ16: 1 | BL16: 无 | BM16: 0 | BN16: 7752 | BP16: 无 | BQ16: 77.52 | BR16: 0 | BS16: 8800.7 | BT16: 1260.23 | BU16: 0.123 | BV16: 0 | BW16: 0 | BX16: 0 | BY16: 否 | BZ16: 2696.06 | CA16: False | CB16: 0.258044 | CC16: 2026-08-10 | CD16: False | CE16: 0 | CF16: 0 | CG16: 35 | CH16: 7752 | CJ16: 398.7 | CK16: 7752 | CL16: 600 | CM16: 0 | CN16: 35 | CO16: 财务-通过 | CP16: 已结束 | CQ16: 0 | CR16: =IF(COUNTIF('畅想下单（外销合同导出）'!$B$2:$B$100,B16)>0,"有","无") -> 有
A17: 昊特赛三公司 | B17: HSC26X021 | C17: 46174 | D17: 熊环英 | E17: LPP | F17: 0.2354 | G17: USD | H17: =IFERROR(SUMIFS(畅想出运数据透视!$B$4:$B$500,畅想出运数据透视!$A$4:$A$500,B17),"0") -> 1666.88 | I17: =IFERROR(VLOOKUP(B17,CHOOSE({1,2},畅想出运数据透视!$A$4:$A$500,畅想出运数据透视!$D$4:$D$500),2,FALSE),"") -> 19.69% | L17: 3628.8 | M17: =L17*6.6 -> 23950.08 | N17: =M17*F17 -> 5637.8488 | O17: 2026-06-30 | P17: 2026-07-01 | Q17: 2026-06-30 | R17: =MONTH(Q17) -> 6 | S17: 已通过 | T17: 波兰749 | U17: 宁波昊特赛进出口有限公司 | V17: FOB | W17: OA 90 DAYS | X17: 0 | Y17: 待审核 | Z17: 已审核 | AA17: 3024 | AB17: 0 | AC17: 84 | AD17: 1638 | AE17: 1596 | AF17: 7.7616 | AG17: 0 | AH17: 3628.8 | AI17: 6.65 | AJ17: 0 | AK17: 2174.34 | AL17: 20 | AM17: 50 | AN17: 0 | AO17: 3583.4 | AP17: 25.4 | AQ17: 5609.98 | AS17: PIMLQZ-20260526068 | AT17: 否 | AU17: 2026-06-07 | AV17: LCL | AW17: LPP S.A. | AX17: 189 | AY17: False | AZ17: 否 | BA17: 客户第一组 | BB17: 外部工厂 | BC17: 0 | BD17: 241.32 | BE17: False | BF17: 0 | BG17: False | BI17: 18900 | BJ17: 1 | BL17: 无 | BM17: 0 | BN17: 18900 | BP17: 无 | BQ17: 189 | BR17: 2174.34 | BS17: 17789.3 | BT17: 5609.98 | BU17: 0.2354 | BV17: 0 | BW17: 0 | BX17: 0 | BY17: 否 | BZ17: 7405.86 | CA17: False | CB17: 0.306896 | CC17: 2026-07-05 | CD17: False | CE17: 0 | CF17: 0 | CG17: 30 | CH17: 18900 | CJ17: 513.64 | CK17: 18900 | CL17: 500 | CM17: 0 | CN17: 3 | CO17: 财务-通过 | CP17: 已结束 | CQ17: 0 | CR17: =IF(COUNTIF('畅想下单（外销合同导出）'!$B$2:$B$100,B17)>0,"有","无") -> 有
A18: 昊特赛三公司 | B18: HSC26X023 | C18: 46143 | D18: 熊环英 | E18: URBAN IMPORTS | F18: 0.2274 | G18: USD | H18: =IFERROR(SUMIFS(畅想出运数据透视!$B$4:$B$500,畅想出运数据透视!$A$4:$A$500,B18),"0") -> 16315.22 | I18: =IFERROR(VLOOKUP(B18,CHOOSE({1,2},畅想出运数据透视!$A$4:$A$500,畅想出运数据透视!$D$4:$D$500),2,FALSE),"") -> 23.76% | L18: 16546.08 | M18: =L18*6.6 -> 109204.13 | N18: =M18*F18 -> 24833.019 | O18: 2026-07-10 | P18: 2026-07-25 | Q18: 2026-07-10 | R18: =MONTH(Q18) -> 7 | S18: 已通过 | T18: 美国5529 | U18: 宁波昊特赛进出口有限公司 | V18: FOB | W18: OA 60DAYS | X18: 0 | Y18: 待审核 | Z18: 已审核 | AA18: 20448 | AB18: 0 | AC18: 757 | AD18: 3007.87 | AE18: 2766.38 | AF18: 12.0258 | AG18: 0 | AH18: 16546.08 | AI18: 6.65 | AJ18: 0 | AK18: 10703.03 | AL18: 33.09 | AM18: 50 | AN18: 0 | AO18: 16397.17 | AP18: 115.82 | AQ18: 24796.1 | AS18: PIMLQZ-20260528071 | AT18: 否 | AU18: 2026-06-05 | AV18: LCL | AX18: 518.02 | AY18: False | AZ18: 否 | BA18: 客户第一组 | BB18: 外部工厂 | BC18: 0 | BD18: 550.16 | BE18: False | BF18: 0 | BG18: False | BI18: 93034.08 | BJ18: 1 | BL18: 无 | BM18: 0 | BN18: 93034.08 | BP18: 无 | BQ18: 518.02 | BR18: 10703.03 | BS18: 83176.88 | BT18: 24796.1 | BU18: 0.2274 | BV18: 0 | BW18: 0 | BX18: 0 | BY18: 否 | BZ18: 27700.4 | CA18: False | CB18: 0.25175 | CC18: 2026-07-25 | CD18: False | CE18: 0 | CF18: 0 | CG18: 45 | CH18: 93034.08 | CJ18: 795.83 | CK18: 93034.08 | CL18: 0 | CM18: 0 | CN18: 12 | CO18: 财务-通过 | CP18: 已结束 | CQ18: 0 | CR18: =IF(COUNTIF('畅想下单（外销合同导出）'!$B$2:$B$100,B18)>0,"有","无") -> 有
A19: 昊特赛三公司 | B19: HSC26X022-1 | C19: 46143 | D19: 熊环英 | E19: URBAN IMPORTS | F19: 0.2803 | G19: USD | H19: =IFERROR(SUMIFS(畅想出运数据透视!$B$4:$B$500,畅想出运数据透视!$A$4:$A$500,B19),"0") -> 16738.13 | I19: =IFERROR(VLOOKUP(B19,CHOOSE({1,2},畅想出运数据透视!$A$4:$A$500,畅想出运数据透视!$D$4:$D$500),2,FALSE),"") -> 26.57% | L19: 16974.96 | M19: =L19*6.6 -> 112034.74 | N19: =M19*F19 -> 31403.337 | O19: 2026-07-31 | P19: 2026-07-31 | Q19: 2026-07-31 | R19: =MONTH(Q19) -> 7 | S19: 已通过 | T19: 美国5529 | U19: 宁波昊特赛进出口有限公司 | V19: FOB | W19: OA 60DAYS | X19: 0 | Y19: 待审核 | Z19: 已审核 | AA19: 18456 | AB19: 0 | AC19: 204 | AD19: 1833.1 | AE19: 1692.3 | AF19: 6.7995 | AG19: 0 | AH19: 16974.96 | AI19: 6.65 | AJ19: 0 | AK19: 10149 | AL19: 33.95 | AM19: 50 | AN19: 0 | AO19: 16822.19 | AP19: 118.82 | AQ19: 31351.72 | AS19: PI毛利前置流程编号：PIMLQZ-20260527070 | AT19: 否 | AU19: 2026-06-30 | AV19: LCL | AX19: 882.18 | AY19: False | AZ19: 否 | BA19: 客户第一组 | BB19: 外部工厂 | BC19: 0 | BD19: 564.42 | BE19: False | BF19: 0 | BG19: True | BI19: 88218.24 | BJ19: 2 | BL19: 无定金 | BM19: 0 | BN19: 88218.24 | BO19: 产品少了1个 | BP19: 无 | BQ19: 882.18 | BR19: 10149 | BS19: 79069.21 | BT19: 31351.72 | BU19: 0.2803 | BV19: 0 | BW19: 0 | BX19: 0 | BY19: 否 | BZ19: 34814.24 | CA19: False | CB19: 0.308409 | CC19: 2026-07-31 | CD19: True | CE19: 0 | CF19: 0 | CG19: 45 | CH19: 88218.24 | CJ19: 449.97 | CK19: 88218.24 | CL19: 500 | CM19: 0 | CN19: 20 | CO19: 财务-通过 | CP19: 已结束 | CQ19: 0 | CR19: =IF(COUNTIF('畅想下单（外销合同导出）'!$B$2:$B$100,B19)>0,"有","无") -> 有
A20: 昊特赛九公司 | B20: HSG26E005 | C20: 46143 | D20: 杜 娟 | E20: LPP | F20: 0.1279 | G20: USD | H20: =IFERROR(SUMIFS(畅想出运数据透视!$B$4:$B$500,畅想出运数据透视!$A$4:$A$500,B20),"0") -> 4743.06 | I20: =IFERROR(VLOOKUP(B20,CHOOSE({1,2},畅想出运数据透视!$A$4:$A$500,畅想出运数据透视!$D$4:$D$500),2,FALSE),"") -> 12.02% | J20: =I20*M20 -> 7517.3417 | K20: =J20-N20 -> -481.56016 | L20: 9475.8 | M20: =L20*6.6 -> 62540.28 | N20: =M20*F20 -> 7998.9018 | O20: 2026-09-27 | P20: 2026-10-05 | Q20: 2026-09-27 | R20: =MONTH(Q20) -> 9 | S20: 已通过 | T20: 波兰749 | U20: 宁波昊特赛进出口有限公司 | V20: FOB | W20: 100% T/T At sight of B/L copy | X20: 0 | Y20: 待审核 | Z20: 已审核 | AA20: 9620 | AB20: 0 | AC20: 271 | AD20: 2052 | AE20: 1906.6 | AF20: 32.8874 | AG20: 0 | AH20: 9475.8 | AI20: 6.65 | AJ20: 0 | AK20: 6724.33 | AL20: 20 | AM20: 50 | AN20: 0 | AO20: 9389.47 | AP20: 66.33 | AQ20: 7985.08 | AT20: 否 | AU20: 2026-06-04 | AV20: 40HQ | AW20: LPP S.A. | AX20: 502.85 | AY20: False | AZ20: 否 | BA20: 客户第一组 | BB20: 外部工厂 | BC20: 0 | BD20: 0 | BE20: False | BF20: 0 | BG20: True | BI20: 58450 | BJ20: 1 | BL20: 流程编号：PIMLQZ-20260526069 PI毛利前置已归档 | BM20: 0 | BN20: 58450 | BP20: LCL | BQ20: 502.85 | BR20: 6724.33 | BS20: 53952.04 | BT20: 7985.08 | BU20: 0.1279 | BV20: 0 | BW20: 0 | BX20: 0 | BY20: 否 | BZ20: 11288.4 | CA20: False | CB20: 0.179141 | CC20: 2026-10-05 | CD20: False | CE20: 0 | CF20: 0 | CG20: 30 | CH20: 58450 | CJ20: 2176.37 | CK20: 58450 | CL20: 0 | CM20: 0 | CN20: 99 | CO20: 财务-通过 | CP20: 已结束 | CQ20: 0 | CR20: =IF(COUNTIF('畅想下单（外销合同导出）'!$B$2:$B$100,B20)>0,"有","无") -> 有
A21: 昊特赛三公司 | B21: HSC26X020 | C21: 46143 | D21: 熊环英 | E21: LPP | F21: 0.1256 | G21: USD | H21: =IFERROR(SUMIFS(畅想出运数据透视!$B$4:$B$500,畅想出运数据透视!$A$4:$A$500,B21),"0") -> 1737.4 | I21: =IFERROR(VLOOKUP(B21,CHOOSE({1,2},畅想出运数据透视!$A$4:$A$500,畅想出运数据透视!$D$4:$D$500),2,FALSE),"") -> 2.19% | J21: =I21*M21 -> 522.42538 | K21: =J21-N21 -> -2473.7676 | L21: 3614.4 | M21: =L21*6.6 -> 23855.04 | N21: =M21*F21 -> 2996.193 | O21: 2026-06-05 | P21: 2026-06-20 | Q21: 2026-06-05 | R21: =MONTH(Q21) -> 6 | S21: 已通过 | T21: 波兰749 | U21: 宁波昊特赛进出口有限公司 | V21: FOB | W21: 100% T/T At sight of B/L copy | X21: 0 | Y21: 待审核 | Z21: 已审核 | AA21: 3012 | AB21: 0 | AC21: 46 | AD21: 893 | AE21: 852 | AF21: 2.8394 | AG21: 0 | AH21: 3614.4 | AI21: 6.65 | AJ21: 0 | AK21: 0 | AL21: 20 | AM21: 50 | AN21: 0 | AO21: 3569.1 | AP21: 25.3 | AQ21: 2981.03 | AS21: PIMLQZ-20260525067 | AT21: 否 | AU21: 2026-05-29 | AV21: LCL | AW21: LPP S.A. | AX21: 197.18 | AY21: False | AZ21: 否 | BA21: 客户第一组 | BB21: 自拼 | BC21: 0 | BD21: 0 | BE21: False | BF21: 0 | BG21: False | BI21: 19718.4 | BJ21: 1 | BL21: 无 | BM21: 0 | BN21: 19718.4 | BP21: 无 | BQ21: 197.18 | BR21: 0 | BS21: 20556.3 | BT21: 2981.03 | BU21: 0.1256 | BV21: 0 | BW21: 0 | BX21: 0 | BY21: 否 | BZ21: 4317.36 | CA21: False | CB21: 0.179622 | CC21: 2026-06-20 | CD21: False | CE21: 0 | CF21: 0 | CG21: 20 | CH21: 19718.4 | CJ21: 187.9 | CK21: 19718.4 | CL21: 600 | CM21: 0 | CN21: 6 | CO21: 财务-通过 | CP21: 已结束 | CQ21: 0 | CR21: =IF(COUNTIF('畅想下单（外销合同导出）'!$B$2:$B$100,B21)>0,"有","无") -> 有
A22: 昊特赛六公司 | B22: HSE26C005 | C22: 46143 | D22: 林元浩 | E22: LPP | F22: 0.0771 | G22: USD | H22: =IFERROR(SUMIFS(畅想出运数据透视!$B$4:$B$500,畅想出运数据透视!$A$4:$A$500,B22),"0") -> 3088.72 | I22: =IFERROR(VLOOKUP(B22,CHOOSE({1,2},畅想出运数据透视!$A$4:$A$500,畅想出运数据透视!$D$4:$D$500),2,FALSE),"") -> 0.62% | J22: =I22*M22 -> 170.6855 | K22: =J22-N22 -> -1951.8713 | L22: 4171.2 | M22: =L22*6.6 -> 27529.92 | N22: =M22*F22 -> 2122.5568 | O22: 2026-08-30 | P22: 2026-08-31 | Q22: 2026-08-30 | R22: =MONTH(Q22) -> 8 | S22: 已通过 | T22: 波兰749 | U22: 宁波昊特赛进出口有限公司 | V22: FOB | W22: 100% T/T At sight of B/L copy | X22: 0 | Y22: 待审核 | Z22: 已审核 | AA22: 2004 | AB22: 0 | AC22: 167 | AD22: 1169 | AE22: 1085.5 | AF22: 12.9553 | AG22: 0 | AH22: 4171.2 | AI22: 6.65 | AJ22: 0 | AK22: 2925.21 | AL22: 20 | AM22: 50 | AN22: 0 | AO22: 4122 | AP22: 29.2 | AQ22: 2113.84 | AS22: PI毛利前置流程号PIMLQZ-20260522066 | AT22: 否 | AU22: 2026-06-11 | AV22: LCL | AW22: LPP S.A. | AX22: 388.54 | AY22: False | AZ22: 否 | BA22: 办公室 | BB22: 外部工厂 | BC22: 0 | BD22: 0 | BE22: False | BF22: 0 | BG22: True | BI22: 25426.8 | BJ22: 2 | BL22: 无定金 | BM22: 0 | BN22: 25426.8 | BO22: 更新供应商及采购价 | BP22: 客户自拼 | BQ22: 388.54 | BR22: 2925.21 | BS22: 24908.93 | BT22: 2113.84 | BU22: 0.0771 | BV22: 0 | BW22: 0 | BX22: 0 | BY22: 否 | BZ22: 5236.89 | CA22: False | CB22: 0.188795 | CC22: 2026-08-31 | CD22: False | CE22: 0 | CF22: 0 | CG22: 30 | CH22: 25426.8 | CJ22: 857.34 | CK22: 25426.8 | CL22: 1500 | CM22: 0 | CN22: 68 | CO22: 财务经理-通过 | CP22: 已结束 | CQ22: 0 | CR22: =IF(COUNTIF('畅想下单（外销合同导出）'!$B$2:$B$100,B22)>0,"有","无") -> 有
A23: 昊特赛六公司 | B23: HSE26C003 | C23: 46143 | D23: 林元浩 | E23: SPLASH | F23: 0.1744 | G23: USD | H23: =IFERROR(SUMIFS(畅想出运数据透视!$B$4:$B$500,畅想出运数据透视!$A$4:$A$500,B23),"0") -> 2132.61 | I23: =IFERROR(VLOOKUP(B23,CHOOSE({1,2},畅想出运数据透视!$A$4:$A$500,畅想出运数据透视!$D$4:$D$500),2,FALSE),"") -> 17.13% | J23: =I23*M23 -> 2485.0148 | K23: =J23-N23 -> -44.97108 | L23: 2198 | M23: =L23*6.6 -> 14506.8 | N23: =M23*F23 -> 2529.9859 | O23: 2026-06-10 | P23: 2026-06-11 | Q23: 2026-06-10 | R23: =MONTH(Q23) -> 6 | S23: 已通过 | T23: 加拿大950 | U23: 宁波昊特赛进出口有限公司 | V23: FOB | W23: 30% Deposit,70% T/T before shipment | X23: 0 | Y23: 待审核 | Z23: 已审核 | AA23: 500 | AB23: 0 | AC23: 12 | AD23: 89 | AE23: 83 | AF23: 1.503 | AG23: 0 | AH23: 2198 | AI23: 6.65 | AJ23: 0 | AK23: 1369.03 | AL23: 20 | AM23: 50 | AN23: 0 | AO23: 2162.61 | AP23: 15.39 | AQ23: 2507.95 | AS23: 毛利前置流程编号：PIMLQZ-20260512064 | AT23: 否 | AU23: 2026-05-28 | AV23: LCL | AX23: 193 | AY23: False | AZ23: 否 | BA23: 办公室 | BB23: 外部工厂 | BC23: 0 | BD23: 0 | BE23: True | BF23: 0 | BG23: False | BI23: 11900 | BJ23: 2 | BL23: 100%定金 | BM23: 0 | BN23: 11900 | BO23: 更新供应商客户范围 | BP23: 客户自拼 | BQ23: 193 | BR23: 1369.03 | BS23: 11680.43 | BT23: 2507.95 | BU23: 0.1744 | BV23: 0 | BW23: 0 | BX23: 0 | BY23: 否 | BZ23: 4085.73 | CA23: False | CB23: 0.279525 | CC23: 2026-06-11 | CD23: False | CE23: 0 | CF23: 0 | CG23: 30 | CH23: 11900 | CJ23: 99.46 | CK23: 11900 | CL23: 1000 | CM23: 0 | CN23: -1 | CO23: 财务-通过 | CP23: 已结束 | CQ23: 0 | CR23: =IF(COUNTIF('畅想下单（外销合同导出）'!$B$2:$B$100,B23)>0,"有","无") -> 有
A24: 昊特赛六公司 | B24: HSE26C004 | C24: 46143 | D24: 林元浩 | E24: LPP | F24: 0.1264 | G24: USD | H24: =IFERROR(SUMIFS(畅想出运数据透视!$B$4:$B$500,畅想出运数据透视!$A$4:$A$500,B24),"0") -> 0 | I24: =IFERROR(VLOOKUP(B24,CHOOSE({1,2},畅想出运数据透视!$A$4:$A$500,畅想出运数据透视!$D$4:$D$500),2,FALSE),"") | L24: 1600 | M24: =L24*6.6 -> 10560 | N24: =M24*F24 -> 1334.784 | O24: 2026-05-31 | P24: 2026-06-01 | Q24: 2026-05-31 | R24: =MONTH(Q24) -> 5 | S24: 已通过 | T24: 波兰749 | U24: 宁波昊特赛进出口有限公司 | V24: FOB | W24: 100% T/T At sight of B/L copy | X24: 0 | Y24: 待审核 | Z24: 已审核 | AA24: 800 | AB24: 0 | AC24: 20 | AD24: 490 | AE24: 480 | AF24: 1.4 | AG24: 0 | AH24: 1600 | AI24: 6.65 | AJ24: 0 | AK24: 1159.65 | AL24: 20 | AM24: 50 | AN24: 0 | AO24: 1568.8 | AP24: 11.2 | AQ24: 1319.12 | AS24: PI毛利前置流程号PIMLQZ-20260507063 | AT24: 否 | AU24: 2026-05-20 | AV24: LCL | AW24: LPP S.A. | AX24: 50.4 | AY24: False | AZ24: 否 | BA24: 办公室 | BB24: 外部工厂 | BC24: 0 | BD24: 0 | BE24: False | BF24: 0 | BG24: False | BI24: 10080 | BJ24: 1 | BL24: 无定金 | BM24: 0 | BN24: 10080 | BP24: 客户自拼 | BQ24: 50.4 | BR24: 1159.65 | BS24: 9063 | BT24: 1319.12 | BU24: 0.1264 | BV24: 0 | BW24: 0 | BX24: 0 | BY24: 否 | BZ24: 1719.65 | CA24: False | CB24: 0.161621 | CC24: 2026-06-01 | CD24: False | CE24: 0 | CF24: 0 | CG24: 30 | CH24: 10080 | CJ24: 92.65 | CK24: 10080 | CL24: 0 | CM24: 0 | CN24: -5 | CO24: 财务-通过 | CP24: 已结束 | CQ24: 0 | CR24: =IF(COUNTIF('畅想下单（外销合同导出）'!$B$2:$B$100,B24)>0,"有","无") -> 有
A25: 昊特赛三公司 | B25: HSC26X019 | C25: 46143 | D25: 熊环英 | E25: DM | F25: 0.1187 | G25: USD | H25: =IFERROR(SUMIFS(畅想出运数据透视!$B$4:$B$500,畅想出运数据透视!$A$4:$A$500,B25),"0") -> 5792.59 | I25: =IFERROR(VLOOKUP(B25,CHOOSE({1,2},畅想出运数据透视!$A$4:$A$500,畅想出运数据透视!$D$4:$D$500),2,FALSE),"") -> 10.17% | J25: =I25*M25 -> 6463.2378 | K25: =J25-N25 -> -1080.3839 | L25: 9629.09 | M25: =L25*6.6 -> 63551.994 | N25: =M25*F25 -> 7543.6217 | O25: 2026-06-02 | P25: 2026-06-10 | Q25: 2026-06-02 | R25: =MONTH(Q25) -> 6 | S25: 已通过 | T25: 加拿大925 | U25: 宁波昊特赛进出口有限公司 | V25: FOB | W25: 100% T/T At sight of B/L copy | X25: 0 | Y25: 待审核 | Z25: 已审核 | AA25: 56016 | AB25: 0 | AC25: 2334 | AD25: 7710.31 | AE25: 6788.11 | AF25: 52.872 | AG25: 0 | AH25: 9629.09 | AI25: 6.7 | AJ25: 0 | AK25: 6799.67 | AL25: 20 | AM25: 50 | AN25: 0 | AO25: 9541.69 | AP25: 67.4 | AQ25: 7590.09 | AS25: PIMLQZ-20260430061 | AT25: 否 | AU25: 2026-05-20 | AV25: LCL | AW25: DOLLARAMA | AX25: 485.2 | AY25: False | AZ25: 否 | BA25: 客户第一组 | BB25: 外部工厂 | BC25: 0 | BD25: 0 | BE25: False | BF25: 7590.16 | BG25: False | BI25: 59104.8 | BJ25: 2 | BL25: 无 | BM25: 0.1187 | BN25: 59104.8 | BO25: 修改价格+附上合同 | BP25: 无 | BQ25: 485.2 | BR25: 6799.67 | BS25: 55854.01 | BT25: 7590.09 | BU25: 0.1187 | BV25: 7590.16 | BW25: 0.1187 | BX25: 0 | BY25: 否 | BZ25: 12209.77 | CA25: False | CB25: 0.189255 | CC25: 2026-06-06 | CD25: False | CE25: 0 | CF25: 0 | CG25: 30 | CH25: 59104.8 | CJ25: 3498.88 | CK25: 59104.8 | CL25: 0 | CM25: 0 | CN25: 1 | CO25: 财务-通过 | CP25: 已结束 | CQ25: 0 | CR25: =IF(COUNTIF('畅想下单（外销合同导出）'!$B$2:$B$100,B25)>0,"有","无") -> 有
A26: 昊特赛三公司 | B26: HSC26H012 | C26: 46143 | D26: 黄家辉 | E26: Joinco | F26: 0.0804 | G26: USD | H26: =IFERROR(SUMIFS(畅想出运数据透视!$B$4:$B$500,畅想出运数据透视!$A$4:$A$500,B26),"0") -> 53728.73 | I26: =IFERROR(VLOOKUP(B26,CHOOSE({1,2},畅想出运数据透视!$A$4:$A$500,畅想出运数据透视!$D$4:$D$500),2,FALSE),"") -> 6.06% | J26: =I26*M26 -> 21879.412 | K26: =J26-N26 -> -7148.7187 | L26: 54704 | M26: =L26*6.6 -> 361046.4 | N26: =M26*F26 -> 29028.131 | O26: 2026-06-01 | P26: 2026-06-15 | Q26: 2026-06-01 | R26: =MONTH(Q26) -> 6 | S26: 已通过 | T26: 波兰700 | U26: 宁波昊特赛进出口有限公司 | V26: FOB | W26: OA 75 Days | X26: 0 | Y26: 待审核 | Z26: 已审核 | AA26: 40000 | AB26: 0 | AC26: 1360 | AD26: 11688 | AE26: 10624 | AF26: 72.808 | AG26: 0 | AH26: 54704 | AI26: 6.7 | AJ26: 0 | AK26: 41876.11 | AL26: 109.41 | AM26: 50 | AN26: 0 | AO26: 54211.66 | AP26: 382.93 | AQ26: 29213.19 | AR26: PIMLQZ-20260430062 | AT26: 是 | AU26: 2026-04-30 | AV26: 40HQ | AW26: JOINCO IMPORTACAO E EXPORTACAO LDA | AX26: 4264 | AY26: False | AZ26: 是 | BA26: 办公室 | BB26: 自拼 | BC26: 0 | BD26: 2748.88 | BE26: False | BF26: 0 | BG26: False | BI26: 364000 | BJ26: 1 | BK26: 2026-04-30 | BL26: 无 | BM26: 0 | BN26: 364000 | BP26: 无 | BQ26: 4264 | BR26: 41876.11 | BS26: 326992.07 | BT26: 29213.19 | BU26: 0.0804 | BV26: 0 | BW26: 0 | BX26: 0 | BY26: 否 | BZ26: 44392.91 | CA26: False | CB26: 0.121121 | CC26: 2026-06-15 | CD26: False | CE26: 0 | CF26: 0 | CG26: 45 | CH26: 364000 | CJ26: 4818.18 | CK26: 364000 | CL26: 0 | CM26: 0 | CN26: 1 | CO26: 财务经理-通过 | CP26: 已结束 | CQ26: 0 | CR26: =IF(COUNTIF('畅想下单（外销合同导出）'!$B$2:$B$100,B26)>0,"有","无") -> 有
A27: 昊特赛九公司 | B27: HSI26L007 | C27: 46143 | D27: 李雅婷 | E27: X5 | F27: 0.1206 | G27: RMB | H27: =IFERROR(SUMIFS(畅想出运数据透视!$B$4:$B$500,畅想出运数据透视!$A$4:$A$500,B27),"0") -> 0 | I27: =IFERROR(VLOOKUP(B27,CHOOSE({1,2},畅想出运数据透视!$A$4:$A$500,畅想出运数据透视!$D$4:$D$500),2,FALSE),"") | L27: 136791.6 | M27: =L27 -> 136791.6 | N27: =M27*F27 -> 16497.067 | O27: 2026-06-25 | P27: 2026-07-20 | Q27: 2026-06-25 | R27: =MONTH(Q27) -> 6 | S27: 已通过 | T27: 俄罗斯2087 | U27: 宁波缤诺国际贸易有限公司 | V27: FOB | W27: OA 60DAYS | X27: 0 | Y27: 待审核 | Z27: 已审核 | AA27: 5676 | AB27: 0 | AC27: 473 | AD27: 3784 | AE27: 3311 | AF27: 25.3528 | AG27: 0 | AH27: 136791.6 | AI27: 1 | AJ27: 0 | AK27: 14692.3 | AL27: 273.58 | AM27: 50 | AN27: 1500 | AO27: 135560.48 | AP27: 957.54 | AQ27: 16353.96 | AR27: 毛利前置流程编号：PIMLQZ-20260429060 | AT27: 否 | AU27: 2026-04-30 | AV27: LCL | AW27: AKTSIONERNOE OBSCHESTVO "ARVIAY (RASHEN VENCHUR INVESTMENTS)" | AX27: 1277.1 | AY27: False | AZ27: 是 | BA27: 办公室 | BB27: 自拼 | BC27: 0 | BD27: 683.96 | BE27: False | BF27: 0 | BG27: True | BI27: 127710 | BJ27: 1 | BK27: 2026-06-20 | BL27: 无定金 | BM27: 0 | BN27: 127710 | BP27: 无 | BQ27: 1277.1 | BR27: 14692.3 | BS27: 117245.46 | BT27: 16353.96 | BU27: 0.1206 | BV27: 0 | BW27: 0 | BX27: 0 | BY27: 否 | BZ27: 23773.9 | CA27: False | CB27: 0.173796 | CC27: 2026-07-20 | CD27: False | CE27: 0 | CF27: 0 | CG27: 75 | CH27: 127710 | CJ27: 1677.76 | CK27: 127710 | CL27: 1000 | CM27: 0 | CN27: 6 | CO27: 财务-通过 | CP27: 已结束 | CQ27: 0 | CR27: =IF(COUNTIF('畅想下单（外销合同导出）'!$B$2:$B$100,B27)>0,"有","无") -> 有
A28: 昊特赛六公司 | B28: HSE26C002 | C28: 46113 | D28: 林元浩 | E28: LPP | F28: 0.1532 | G28: USD | H28: =IFERROR(SUMIFS(畅想出运数据透视!$B$4:$B$500,畅想出运数据透视!$A$4:$A$500,B28),"0") -> 1286.13 | I28: =IFERROR(VLOOKUP(B28,CHOOSE({1,2},畅想出运数据透视!$A$4:$A$500,畅想出运数据透视!$D$4:$D$500),2,FALSE),"") -> -2.01% | J28: =I28*M28 -> -542.04876 | K28: =J28-N28 -> -4673.4851 | L28: 4086 | M28: =L28*6.6 -> 26967.6 | N28: =M28*F28 -> 4131.4363 | O28: 2026-08-29 | P28: 2026-08-31 | Q28: 2026-08-29 | R28: =MONTH(Q28) -> 8 | S28: 已通过 | T28: 波兰749 | U28: 宁波昊特赛进出口有限公司 | V28: FOB | W28: OA 90 DAYS | X28: 0 | Y28: 待审核 | Z28: 已审核 | AA28: 1800 | AB28: 0 | AC28: 180 | AD28: 990 | AE28: 810 | AF28: 19.296 | AG28: 0 | AH28: 4086 | AI28: 6.7 | AJ28: 0 | AK28: 2754.15 | AL28: 20 | AM28: 50 | AN28: 0 | AO28: 4037.4 | AP28: 28.6 | AQ28: 4144.32 | AR28: 此票包含3个PO，客户会分批出运 | AS28: PI毛利前置流程号 PIMLQZ-20260427059 | AT28: 否 | AU28: 2026-05-31 | AV28: LCL | AW28: LPP S.A. | AX28: 119.7 | AY28: False | AZ28: 否 | BA28: 办公室 | BB28: 外部工厂 | BC28: 0 | BD28: 273.76 | BE28: False | BF28: 0 | BG28: True | BI28: 23940 | BJ28: 3 | BL28: 无定金 | BM28: 0 | BN28: 23940 | BO28: 增加PI前置流程号 | BP28: 客户自拼 | BQ28: 119.7 | BR28: 2754.15 | BS28: 22512.79 | BT28: 4144.32 | BU28: 0.1532 | BV28: 0 | BW28: 0 | BX28: 0 | BY28: 否 | BZ28: 6190.35 | CA28: False | CB28: 0.226122 | CC28: 2026-08-31 | CD28: False | CE28: 0 | CF28: 0 | CG28: 30 | CH28: 23940 | CJ28: 1276.94 | CK28: 23940 | CL28: 0 | CM28: 0 | CN28: 96 | CO28: 财务-通过 | CP28: 已结束 | CQ28: 0 | CR28: =IF(COUNTIF('畅想下单（外销合同导出）'!$B$2:$B$100,B28)>0,"有","无") -> 有
A29: 昊特赛三公司 | B29: HSC26X018 | C29: 46113 | D29: 熊环英 | E29: LPP | F29: 0.1525 | G29: USD | H29: =IFERROR(SUMIFS(畅想出运数据透视!$B$4:$B$500,畅想出运数据透视!$A$4:$A$500,B29),"0") -> 0 | I29: =IFERROR(VLOOKUP(B29,CHOOSE({1,2},畅想出运数据透视!$A$4:$A$500,畅想出运数据透视!$D$4:$D$500),2,FALSE),"") | L29: 1791 | M29: =L29*6.6 -> 11820.6 | N29: =M29*F29 -> 1802.6415 | O29: 2026-06-30 | P29: 2026-07-13 | Q29: 2026-06-30 | R29: =MONTH(Q29) -> 6 | S29: 已通过 | T29: 波兰749 | U29: 宁波昊特赛进出口有限公司 | V29: FOB | W29: 100% T/T At sight of B/L copy | X29: 0 | Y29: 待审核 | Z29: 已审核 | AA29: 1990 | AB29: 0 | AC29: 21 | AD29: 451 | AE29: 430 | AF29: 1.2096 | AG29: 0 | AH29: 1791 | AI29: 6.7 | AJ29: 0 | AK29: 1144.69 | AL29: 20 | AM29: 50 | AN29: 0 | AO29: 1758.46 | AP29: 12.54 | AQ29: 1796.59 | AS29: PIMLQZ-20260423058 | AT29: 否 | AU29: 2026-04-30 | AV29: LCL | AW29: LPP S.A. | AX29: 49.75 | AY29: False | AZ29: 否 | BA29: 客户第一组 | BB29: 外部工厂 | BC29: 0 | BD29: 0 | BE29: False | BF29: 1796.57 | BG29: True | BI29: 9950 | BJ29: 1 | BL29: 无 | BM29: 0.1525 | BN29: 9950 | BP29: 无 | BQ29: 49.75 | BR29: 1144.69 | BS29: 9935.36 | BT29: 1796.59 | BU29: 0.1525 | BV29: 1796.57 | BW29: 0.1525 | BX29: 0 | BY29: 否 | BZ29: 3194.39 | CA29: False | CB29: 0.266206 | CC29: 2026-07-13 | CD29: False | CE29: 0 | CF29: 0 | CG29: 60 | CH29: 9950 | CJ29: 80.05 | CK29: 9950 | CL29: 1000 | CM29: 0 | CN29: 21 | CO29: 财务-通过 | CP29: 已结束 | CQ29: 0 | CR29: =IF(COUNTIF('畅想下单（外销合同导出）'!$B$2:$B$100,B29)>0,"有","无") -> 有
A30: 昊特赛九公司 | B30: HSI26L006 | C30: 46113 | D30: 李雅婷 | E30: X5 | F30: 0.0897 | G30: RMB | H30: =IFERROR(SUMIFS(畅想出运数据透视!$B$4:$B$500,畅想出运数据透视!$A$4:$A$500,B30),"0") -> 4672.28 | I30: =IFERROR(VLOOKUP(B30,CHOOSE({1,2},畅想出运数据透视!$A$4:$A$500,畅想出运数据透视!$D$4:$D$500),2,FALSE),"") -> 9.09% | J30: =I30*M30 -> 2939.1606 | K30: =J30-N30 -> 38.8008 | L30: 32334 | M30: =L30 -> 32334 | N30: =M30*F30 -> 2900.3598 | O30: 2026-06-25 | P30: 2026-07-15 | Q30: 2026-06-25 | R30: =MONTH(Q30) -> 6 | S30: 已通过 | T30: 俄罗斯2087 | U30: 宁波缤诺国际贸易有限公司 | V30: FOB | W30: OA 60DAYS | X30: 0 | Y30: 待审核 | Z30: 已审核 | AA30: 5100 | AB30: 0 | AC30: 85 | AD30: 935 | AE30: 850 | AF30: 6.375 | AG30: 0 | AH30: 32334 | AI30: 1 | AJ30: 0 | AK30: 3403.01 | AL30: 134 | AM30: 50 | AN30: 1000 | AO30: 31973.66 | AP30: 226.34 | AQ30: 2867.32 | AR30: 毛利前置流程编号：PIMLQZ-20260422057 | AT30: 否 | AU30: 2026-04-24 | AV30: LCL | AW30: AKTSIONERNOE OBSCHESTVO "ARVIAY (RASHEN VENCHUR INVESTMENTS)" | AX30: 295.8 | AY30: False | AZ30: 是 | BA30: 办公室 | BB30: 外部工厂 | BC30: 0 | BD30: 161.67 | BE30: False | BF30: 0 | BG30: True | BI30: 29580 | BJ30: 1 | BK30: 2026-06-30 | BL30: 无 | BM30: 0 | BN30: 29580 | BP30: 无 | BQ30: 295.8 | BR30: 3403.01 | BS30: 28648.87 | BT30: 2867.32 | BU30: 0.0897 | BV30: 0 | BW30: 0 | BX30: 0 | BY30: 否 | BZ30: 6157.01 | CA30: False | CB30: 0.190419 | CC30: 2026-07-15 | CD30: False | CE30: 0 | CF30: 0 | CG30: 60 | CH30: 29580 | CJ30: 421.88 | CK30: 29580 | CL30: 1000 | CM30: 0 | CN30: 24 | CO30: 财务经理-通过 | CP30: 已结束 | CQ30: 0 | CR30: =IF(COUNTIF('畅想下单（外销合同导出）'!$B$2:$B$100,B30)>0,"有","无") -> 有
A31: 昊特赛九公司 | B31: HSI26L005 | C31: 46113 | D31: 李雅婷 | E31: X5 | F31: 0.0906 | G31: RMB | H31: =IFERROR(SUMIFS(畅想出运数据透视!$B$4:$B$500,畅想出运数据透视!$A$4:$A$500,B31),"0") -> 190193.07 | I31: =IFERROR(VLOOKUP(B31,CHOOSE({1,2},畅想出运数据透视!$A$4:$A$500,畅想出运数据透视!$D$4:$D$500),2,FALSE),"") -> 9.87% | J31: =I31*M31 -> 128629.96 | K31: =J31-N31 -> 10556.258 | L31: 1303241.8 | M31: =L31 -> 1303241.8 | N31: =M31*F31 -> 118073.7 | O31: 2026-07-20 | P31: 2026-07-20 | Q31: 2026-07-20 | R31: =MONTH(Q31) -> 7 | S31: 已通过 | T31: 俄罗斯2087 | U31: 宁波缤诺国际贸易有限公司 | V31: FOB | W31: OA 60DAYS | X31: 0 | Y31: 待审核 | Z31: 已审核 | AA31: 312528 | AB31: 0 | AC31: 6511 | AD31: 97665 | AE31: 91154 | AF31: 289.0884 | AG31: 0 | AH31: 1303241.8 | AI31: 1 | AJ31: 0 | AK31: 147413.65 | AL31: 2606.48 | AM31: 50 | AN31: 2000 | AO31: 1291512.6 | AP31: 9122.69 | AQ31: 117050.73 | AR31: 毛利前置流程编号：PIMLQZ-20260422056 | AT31: 否 | AU31: 2026-04-22 | AV31: 40HQ | AW31: AKTSIONERNOE OBSCHESTVO "ARVIAY (RASHEN VENCHUR INVESTMENTS)" | AX31: 12813.65 | AY31: False | AZ31: 否 | BA31: 办公室 | BB31: 自拼 | BC31: 0 | BD31: 6516.21 | BE31: False | BF31: 0 | BG31: True | BI31: 1281364.8 | BJ31: 1 | BL31: 无定金 | BM31: 0 | BN31: 1281364.8 | BP31: 无 | BQ31: 12813.65 | BR31: 147413.65 | BS31: 1155132 | BT31: 117050.73 | BU31: 0.0906 | BV31: 0 | BW31: 0 | BX31: 0 | BY31: 否 | BZ31: 169290.61 | CA31: False | CB31: 0.1299 | CC31: 2026-07-20 | CD31: False | CE31: 0 | CF31: 0 | CG31: 60 | CH31: 1281364.8 | CJ31: 19130.85 | CK31: 1281364.8 | CL31: 0 | CM31: 0 | CN31: 29 | CO31: 财务经理-通过 | CP31: 已结束 | CQ31: 0 | CR31: =IF(COUNTIF('畅想下单（外销合同导出）'!$B$2:$B$100,B31)>0,"有","无") -> 有
A32: 昊特赛六公司 | B32: HSE26L007 | C32: 46113 | D32: 林元浩 | E32: LPP | F32: 0.0559 | G32: USD | H32: =IFERROR(SUMIFS(畅想出运数据透视!$B$4:$B$500,畅想出运数据透视!$A$4:$A$500,B32),"0") -> 17830 | I32: =IFERROR(VLOOKUP(B32,CHOOSE({1,2},畅想出运数据透视!$A$4:$A$500,畅想出运数据透视!$D$4:$D$500),2,FALSE),"") -> 4.33% | J32: =I32*M32 -> 1172.7632 | K32: =J32-N32 -> -341.26596 | L32: 27084.6 | M32: =L32 -> 27084.6 | N32: =M32*F32 -> 1514.0291 | O32: 2026-08-30 | P32: 2026-09-07 | Q32: 2026-08-30 | R32: =MONTH(Q32) -> 8 | S32: 已通过 | T32: 波兰749 | U32: 宁波昊特赛进出口有限公司 | V32: FOB | W32: 100% T/T At sight of B/L copy | X32: 0 | Y32: 待审核 | Z32: 已审核 | AA32: 6606 | AB32: 0 | AC32: 1101 | AD32: 10459.5 | AE32: 9358.5 | AF32: 68.4822 | AG32: 0 | AH32: 27084.6 | AI32: 6.7 | AJ32: 0 | AK32: 21355.5 | AL32: 54.17 | AM32: 50 | AN32: 0 | AO32: 26840.84 | AP32: 189.59 | AQ32: 10050.46 | AR32: 此票包含3个PO，客户会分批出运 | AT32: 否 | AU32: 2026-04-30 | AV32: LCL | AW32: LPP S.A. | AX32: 928.14 | AY32: False | AZ32: 否 | BA32: 办公室 | BB32: 外部工厂 | BC32: 0 | BD32: 0 | BE32: False | BF32: 10050.54 | BG32: True | BI32: 185628.6 | BJ32: 1 | BL32: 无定金 | BM32: 0.0559 | BN32: 185628.6 | BP32: 客户自拼 | BQ32: 928.14 | BR32: 21355.5 | BS32: 168855.01 | BT32: 10050.46 | BU32: 0.0559 | BV32: 10050.54 | BW32: 0.0559 | BX32: 0 | BY32: 否 | BZ32: 17193.72 | CA32: False | CB32: 0.094749 | CC32: 2026-09-07 | CD32: True | CE32: 0 | CF32: 0 | CG32: 40 | CH32: 185628.6 | CJ32: 4531.91 | CK32: 185628.6 | CL32: 0 | CM32: 0 | CN32: 100 | CO32: 财务经理-通过 | CP32: 已结束 | CQ32: 0 | CR32: =IF(COUNTIF('畅想下单（外销合同导出）'!$B$2:$B$100,B32)>0,"有","无") -> 有
A33: 昊特赛三公司 | B33: HSC26H011 | C33: 46113 | D33: 黄家辉 | E33: JES | F33: 0.0088 | G33: USD | H33: =IFERROR(SUMIFS(畅想出运数据透视!$B$4:$B$500,畅想出运数据透视!$A$4:$A$500,B33),"0") -> 2094.88 | I33: =IFERROR(VLOOKUP(B33,CHOOSE({1,2},畅想出运数据透视!$A$4:$A$500,畅想出运数据透视!$D$4:$D$500),2,FALSE),"") -> -4.88% | J33: =I33*M33 -> -105.408 | K33: =J33-N33 -> -124.416 | L33: 2160 | M33: =L33 -> 2160 | N33: =M33*F33 -> 19.008 | O33: 2026-05-05 | P33: 2026-05-15 | Q33: 2026-05-05 | R33: =MONTH(Q33) -> 5 | S33: 已通过 | T33: 德国1586 | U33: 宁波昊特赛进出口有限公司 | V33: FOB | W33: 100% T/T At sight of B/L copy | X33: 0 | Y33: 待审核 | Z33: 已审核 | AA33: 12000 | AB33: 0 | AC33: 125 | AD33: 937.5 | AE33: 875 | AF33: 9.625 | AG33: 0 | AH33: 2160 | AI33: 6.7 | AJ33: 0 | AK33: 1725.66 | AL33: 20 | AM33: 50 | AN33: 0 | AO33: 2124.88 | AP33: 15.12 | AQ33: 125.41 | AR33: PIMLQZ-20260413053 | AT33: 否 | AU33: 2026-04-15 | AV33: 40HQ | AW33: J. E. Schum GmbH & Co. KG | AX33: 150 | AY33: False | AZ33: 否 | BA33: 办公室 | BB33: 外部工厂 | BC33: 0 | BD33: 0 | BE33: False | BF33: 0 | BG33: False | BI33: 15000 | BJ33: 2 | BL33: 无 | BM33: 0 | BN33: 15000 | BO33: 供应商选错了 | BP33: 无 | BQ33: 150 | BR33: 1725.66 | BS33: 13961.29 | BT33: 125.41 | BU33: 0.0088 | BV33: 0 | BW33: 0 | BX33: 0 | BY33: 否 | BZ33: 1197.66 | CA33: False | CB33: 0.082757 | CC33: 2026-05-30 | CD33: False | CE33: 0 | CF33: 0 | CG33: 30 | CH33: 15000 | CJ33: 636.95 | CK33: 15000 | CL33: 0 | CM33: 0 | CN33: 15 | CO33: 财务经理-通过 | CP33: 已结束 | CQ33: 0 | CR33: =IF(COUNTIF('畅想下单（外销合同导出）'!$B$2:$B$100,B33)>0,"有","无") -> 有
A34: 昊特赛三公司 | B34: HSC26X015 | C34: 46113 | D34: 熊环英 | E34: DM | F34: 0.0286 | G34: USD | H34: =IFERROR(SUMIFS(畅想出运数据透视!$B$4:$B$500,畅想出运数据透视!$A$4:$A$500,B34),"0") -> 17274.76 | I34: =IFERROR(VLOOKUP(B34,CHOOSE({1,2},畅想出运数据透视!$A$4:$A$500,畅想出运数据透视!$D$4:$D$500),2,FALSE),"") -> -1.19% | J34: =I34*M34 -> -894.20646 | K34: =J34-N34 -> -3043.3077 | L34: 75143.4 | M34: =L34 -> 75143.4 | N34: =M34*F34 -> 2149.1012 | O34: 2026-05-20 | P34: 2026-06-15 | Q34: 2026-05-20 | R34: =MONTH(Q34) -> 5 | S34: 已通过 | T34: 加拿大925 | U34: 宁波昊特赛进出口有限公司 | V34: FOB | W34: 100% T/T At sight of B/L copy | X34: 0 | Y34: 待审核 | Z34: 已审核 | AA34: 250080 | AB34: 0 | AC34: 10420 | AD34: 41783.81 | AE34: 36279.13 | AF34: 150.1478 | AG34: 0 | AH34: 75143.4 | AI34: 6.7 | AJ34: 0 | AK34: 61029.5 | AL34: 150.29 | AM34: 50 | AN34: 0 | AO34: 74467.11 | AP34: 526 | AQ34: 14265.81 | AS34: PIMLQZ-20260413052 | AT34: 否 | AU34: 2026-05-03 | AV34: 40HQ | AW34: DOLLARAMA | AX34: 5219.81 | AY34: False | AZ34: 否 | BA34: 客户第一组 | BB34: 自拼 | BC34: 0 | BD34: 0 | BE34: False | BF34: 14265.84 | BG34: True | BI34: 530487.24 | BJ34: 1 | BL34: 无 | BM34: 0.0286 | BN34: 530487.24 | BP34: 无 | BQ34: 5219.81 | BR34: 61029.5 | BS34: 479443.99 | BT34: 14265.81 | BU34: 0.0286 | BV34: 14265.84 | BW34: 0.0286 | BX34: 0 | BY34: 否 | BZ34: 34003.04 | CA34: False | CB34: 0.067539 | CC34: 2026-05-25 | CD34: False | CE34: 0 | CF34: 0 | CG34: 30 | CH34: 530487.24 | CJ34: 9936.25 | CK34: 530487.24 | CL34: 0 | CM34: 0 | CN34: 11 | CO34: 财务经理-通过 | CP34: 已结束 | CQ34: 0 | CR34: =IF(COUNTIF('畅想下单（外销合同导出）'!$B$2:$B$100,B34)>0,"有","无") -> 有
A35: 昊特赛六公司 | B35: HSE26L006 | C35: 46113 | D35: 林元浩 | E35: Mondou | F35: 0.0679 | G35: USD | H35: =IFERROR(SUMIFS(畅想出运数据透视!$B$4:$B$500,畅想出运数据透视!$A$4:$A$500,B35),"0") -> 24609.01 | I35: =IFERROR(VLOOKUP(B35,CHOOSE({1,2},畅想出运数据透视!$A$4:$A$500,畅想出运数据透视!$D$4:$D$500),2,FALSE),"") -> -0.67% | J35: =I35*M35 -> -175.49712 | K35: =J35-N35 -> -1954.0426 | L35: 26193.6 | M35: =L35 -> 26193.6 | N35: =M35*F35 -> 1778.5454 | O35: 2026-07-10 | P35: 2026-07-15 | Q35: 2026-07-10 | R35: =MONTH(Q35) -> 7 | S35: 已通过 | T35: 加拿大896 | U35: 宁波昊特赛进出口有限公司 | V35: FOB | W35: 100% T/T At sight of B/L copy | X35: 0 | Y35: 待审核 | Z35: 已审核 | AA35: 3192 | AB35: 0 | AC35: 266 | AD35: 3777.2 | AE35: 3511.2 | AF35: 25.3056 | AG35: 0 | AH35: 26193.6 | AI35: 6.7 | AJ35: 0 | AK35: 20732.82 | AL35: 52.39 | AM35: 50 | AN35: 0 | AO35: 25957.85 | AP35: 183.36 | AQ35: 11808.73 | AS35: 毛利前置流程编号 PIMLQZ-20260413051 | AT35: 否 | AU35: 2026-04-20 | AV35: LCL | AX35: 901.08 | AY35: False | AZ35: 是 | BA35: 办公室 | BB35: 外部工厂 | BC35: 0 | BD35: 0 | BE35: False | BF35: 11808.77 | BG35: True | BI35: 180216 | BJ35: 1 | BK35: 2026-07-10 | BL35: 无 | BM35: 0.0679 | BN35: 180216 | BP35: LCL | BQ35: 901.08 | BR35: 20732.82 | BS35: 161207.82 | BT35: 11808.73 | BU35: 0.0679 | BV35: 11808.77 | BW35: 0.0679 | BX35: 0 | BY35: 否 | BZ35: 16013.94 | CA35: False | CB35: 0.091249 | CC35: 2026-07-15 | CD35: True | CE35: 0 | CF35: 0 | CG35: 45 | CH35: 180216 | CJ35: 1674.64 | CK35: 180216 | CL35: 0 | CM35: 0 | CN35: 47 | CO35: 财务经理-通过 | CP35: 已结束 | CQ35: 0 | CR35: =IF(COUNTIF('畅想下单（外销合同导出）'!$B$2:$B$100,B35)>0,"有","无") -> 有
A36: 昊特赛九公司 | B36: HSI26L004 | C36: 46113 | D36: 李雅婷 | E36: LPP | F36: 0.1773 | G36: USD | H36: =IFERROR(SUMIFS(畅想出运数据透视!$B$4:$B$500,畅想出运数据透视!$A$4:$A$500,B36),"0") -> 9517.21 | I36: =IFERROR(VLOOKUP(B36,CHOOSE({1,2},畅想出运数据透视!$A$4:$A$500,畅想出运数据透视!$D$4:$D$500),2,FALSE),"") -> 15.24% | J36: =I36*M36 -> 4740.9811 | K36: =J36-N36 -> -774.60912 | L36: 31108.8 | M36: =L36 -> 31108.8 | N36: =M36*F36 -> 5515.5902 | O36: 2026-08-31 | P36: 2026-08-31 | Q36: 2026-08-31 | R36: =MONTH(Q36) -> 8 | S36: 已通过 | T36: 波兰749 | U36: 宁波昊特赛进出口有限公司 | V36: FOB | W36: OA 90 DAYS | X36: 0 | Y36: 待审核 | Z36: 已审核 | AA36: 11008 | AB36: 0 | AC36: 521 | AD36: 4548 | AE36: 3994 | AF36: 22.9698 | AG36: 0 | AH36: 31108.8 | AI36: 6.7 | AJ36: 0 | AK36: 20162.19 | AL36: 62.22 | AM36: 50 | AN36: 0 | AO36: 30828.82 | AP36: 217.76 | AQ36: 36614.64 | AR36: 毛利前置流程编号：PIMLQZ-20260420055 | AT36: 否 | AU36: 2026-04-13 | AV36: LCL | AW36: LPP S.A. | AX36: 1190.28 | AY36: False | AZ36: 否 | BA36: 办公室 | BB36: 外部工厂 | BC36: 0 | BD36: 2084.29 | BE36: False | BF36: 0 | BG36: True | BI36: 175256 | BJ36: 1 | BL36: 无 | BM36: 0 | BN36: 175256 | BP36: 无 | BQ36: 1190.28 | BR36: 20162.19 | BS36: 166663.87 | BT36: 36614.64 | BU36: 0.1773 | BV36: 0 | BW36: 0 | BX36: 0 | BY36: 否 | BZ36: 53335.15 | CA36: True | CB36: 0.255891 | CC36: 2026-08-31 | CD36: False | CE36: 0 | CF36: 0 | CG36: 35 | CH36: 175256 | CJ36: 1520.06 | CK36: 175256 | CL36: 10000 | CM36: 0 | CN36: 98 | CO36: 财务-通过 | CP36: 已结束 | CQ36: 0 | CR36: =IF(COUNTIF('畅想下单（外销合同导出）'!$B$2:$B$100,B36)>0,"有","无") -> 有
A37: 昊特赛三公司 | B37: HSC26X016 | C37: 46113 | D37: 熊环英 | E37: DM | F37: 0.0076 | G37: USD | H37: =IFERROR(SUMIFS(畅想出运数据透视!$B$4:$B$500,畅想出运数据透视!$A$4:$A$500,B37),"0") -> 844.41 | I37: =IFERROR(VLOOKUP(B37,CHOOSE({1,2},畅想出运数据透视!$A$4:$A$500,畅想出运数据透视!$D$4:$D$500),2,FALSE),"") -> 11.98% | J37: =I37*M37 -> 107.90626 | K37: =J37-N37 -> 101.06078 | L37: 900.72 | M37: =L37 -> 900.72 | N37: =M37*F37 -> 6.845472 | O37: 2026-04-16 | P37: 2026-04-16 | Q37: 2026-04-16 | R37: =MONTH(Q37) -> 4 | S37: 已通过 | T37: 加拿大925 | U37: 宁波昊特赛进出口有限公司 | V37: FOB | W37: 100% T/T At sight of B/L copy | X37: 0 | Y37: 待审核 | Z37: 已审核 | AA37: 10008 | AB37: 0 | AC37: 417 | AD37: 405.32 | AE37: 280.22 | AF37: 5.004 | AG37: 0 | AH37: 900.72 | AI37: 6.7 | AJ37: 0 | AK37: 702.33 | AL37: 20 | AM37: 50 | AN37: 0 | AO37: 874.41 | AP37: 6.31 | AQ37: 44.36 | AS37: PIMLQZ-20260407046 | AT37: 否 | AU37: 2026-04-12 | AV37: LCL | AW37: DOLLARAMA | AX37: 30.52 | AY37: False | AZ37: 否 | BA37: 客户第一组 | BB37: 外部工厂 | BC37: 0 | BD37: 0 | BE37: False | BF37: 44.32 | BG37: False | BI37: 6104.88 | BJ37: 1 | BL37: 无 | BM37: 0.0076 | BN37: 6104.88 | BP37: 无 | BQ37: 30.52 | BR37: 702.33 | BS37: 5783.7 | BT37: 44.36 | BU37: 0.0076 | BV37: 44.32 | BW37: 0.0076 | BX37: 0 | BY37: 否 | BZ37: 632.27 | CA37: False | CB37: 0.10477 | CC37: 2026-04-25 | CD37: False | CE37: 0 | CF37: 0 | CG37: 15 | CH37: 6104.88 | CJ37: 331.15 | CK37: 6104.88 | CL37: 0 | CM37: 0 | CN37: 1 | CO37: 财务经理-通过 | CP37: 已结束 | CQ37: 0 | CR37: =IF(COUNTIF('畅想下单（外销合同导出）'!$B$2:$B$100,B37)>0,"有","无") -> 有
A38: 昊特赛十公司 | B38: HSJ26R004-6 | C38: 46113 | D38: 夏煜昕 | E38: DGL-HT | F38: 0.0634 | G38: USD | H38: =IFERROR(SUMIFS(畅想出运数据透视!$B$4:$B$500,畅想出运数据透视!$A$4:$A$500,B38),"0") -> 11589.59 | I38: =IFERROR(VLOOKUP(B38,CHOOSE({1,2},畅想出运数据透视!$A$4:$A$500,畅想出运数据透视!$D$4:$D$500),2,FALSE),"") -> 8.38% | J38: =I38*M38 -> 986.4936 | K38: =J38-N38 -> 240.1488 | L38: 11772 | M38: =L38 -> 11772 | N38: =M38*F38 -> 746.3448 | O38: 2026-06-04 | P38: 2026-06-09 | Q38: 2026-06-04 | R38: =MONTH(Q38) -> 6 | S38: 已通过 | T38: 美国0830 | U38: 宁波昊特赛进出口有限公司 | V38: FOB | W38: 100% T/T Before shipment | X38: 0 | Y38: 待审核 | Z38: 已审核 | AA38: 3600 | AB38: 0 | AC38: 115 | AD38: 437 | AE38: 345 | AF38: 0.9085 | AG38: 0 | AH38: 11772 | AI38: 6.7 | AJ38: 0 | AK38: 8817.45 | AL38: 23.54 | AM38: 50 | AN38: 0 | AO38: 11666.06 | AP38: 82.4 | AQ38: 4953.97 | AS38: 合同变更流程已完成，HTBG-20260422236 | AT38: 否 | AU38: 2026-04-17 | AV38: LCL | AX38: 383.22 | AY38: False | AZ38: 否 | BA38: 办公室 | BB38: 自拼 | BC38: 0 | BD38: 0 | BE38: False | BF38: 2972.4 | BG38: True | BI38: 76644 | BJ38: 2 | BL38: / | BM38: 0.038 | BN38: 76644 | BO38: 价格条款由DDP变为FOB | BP38: LCL | BQ38: 383.22 | BR38: 8817.45 | BS38: 72825.39 | BT38: 4953.97 | BU38: 0.0634 | BV38: 2972.4 | BW38: 0.038 | BX38: 0 | BY38: 否 | BZ38: 11045.85 | CA38: True | CB38: 0.140047 | CC38: 2026-06-09 | CD38: False | CE38: 0 | CF38: 0 | CG38: 55 | CH38: 76644 | CJ38: 60.12 | CK38: 76644 | CL38: 4888.72 | CM38: 0 | CN38: 7 | CO38: 财务经理-通过 | CP38: 已结束 | CQ38: 0 | CR38: =IF(COUNTIF('畅想下单（外销合同导出）'!$B$2:$B$100,B38)>0,"有","无") -> 有
A39: 昊特赛十公司 | B39: HSJ26R004-5 | C39: 46113 | D39: 夏煜昕 | E39: DGL-HT | F39: 0.004 | G39: USD | H39: =IFERROR(SUMIFS(畅想出运数据透视!$B$4:$B$500,畅想出运数据透视!$A$4:$A$500,B39),"0") -> 4033.85 | I39: =IFERROR(VLOOKUP(B39,CHOOSE({1,2},畅想出运数据透视!$A$4:$A$500,畅想出运数据透视!$D$4:$D$500),2,FALSE),"") -> 6.13% | J39: =I39*M39 -> 252.10483 | K39: =J39-N39 -> 235.65427 | L39: 4112.64 | M39: =L39 -> 4112.64 | N39: =M39*F39 -> 16.45056 | O39: 2026-06-01 | P39: 2026-06-05 | Q39: 2026-06-01 | R39: =MONTH(Q39) -> 6 | S39: 已通过 | T39: 美国0830 | U39: 宁波昊特赛进出口有限公司 | V39: DDP | W39: 100% T/T Before shipment | X39: 0 | Y39: 待审核 | Z39: 已审核 | AA39: 1344 | AB39: 0 | AC39: 28 | AD39: 140 | AE39: 112 | AF39: 0.4956 | AG39: 0 | AH39: 4112.64 | AI39: 6.7 | AJ39: 0 | AK39: 2933.13 | AL39: 20 | AM39: 50 | AN39: 0 | AO39: 4063.85 | AP39: 28.79 | AQ39: 109.24 | AS39: PI毛利前置审批已完成，PIMLQZ-20260402043 | AT39: 否 | AU39: 2026-04-17 | AV39: LCL | AX39: 254.96 | AY39: False | AZ39: 否 | BA39: 办公室 | BB39: 自拼 | BC39: 0 | BD39: 0 | BE39: False | BF39: 65.54 | BG39: True | BI39: 25495.68 | BJ39: 1 | BL39: / | BM39: 0.0024 | BN39: 25495.68 | BP39: LCL | BQ39: 254.96 | BR39: 2933.13 | BS39: 26863.61 | BT39: 109.24 | BU39: 0.004 | BV39: 65.54 | BW39: 0.0024 | BX39: 0 | BY39: 否 | BZ39: 4992.14 | CA39: False | CB39: 0.181172 | CC39: 2026-06-05 | CD39: False | CE39: 0 | CF39: 0 | CG39: 50 | CH39: 25495.68 | CJ39: 32.8 | CK39: 25495.68 | CL39: 4218.26 | CM39: 0 | CN39: 8 | CO39: 财务经理-通过 | CP39: 已结束 | CQ39: 0 | CR39: =IF(COUNTIF('畅想下单（外销合同导出）'!$B$2:$B$100,B39)>0,"有","无") -> 有
A40: 昊特赛十公司 | B40: HSJ26R004-4 | C40: 46113 | D40: 夏煜昕 | E40: DGL-HT | F40: 0.0993 | G40: USD | H40: =IFERROR(SUMIFS(畅想出运数据透视!$B$4:$B$500,畅想出运数据透视!$A$4:$A$500,B40),"0") -> 2778.38 | I40: =IFERROR(VLOOKUP(B40,CHOOSE({1,2},畅想出运数据透视!$A$4:$A$500,畅想出运数据透视!$D$4:$D$500),2,FALSE),"") -> 2.69% | J40: =I40*M40 -> 76.619808 | K40: =J40-N40 -> -206.21837 | L40: 2848.32 | M40: =L40 -> 2848.32 | N40: =M40*F40 -> 282.83818 | O40: 2026-05-28 | P40: 2026-06-02 | Q40: 2026-05-28 | R40: =MONTH(Q40) -> 5 | S40: 已通过 | T40: 美国0830 | U40: 宁波昊特赛进出口有限公司 | V40: FOB | W40: 100% T/T Before shipment | X40: 0 | Y40: 待审核 | Z40: 已审核 | AA40: 2064 | AB40: 0 | AC40: 43 | AD40: 55.9 | AE40: 43 | AF40: 0.7955 | AG40: 0 | AH40: 2848.32 | AI40: 6.7 | AJ40: 0 | AK40: 2137.06 | AL40: 20 | AM40: 50 | AN40: 0 | AO40: 2808.38 | AP40: 19.94 | AQ40: 1867.68 | AS40: PI毛利前置审批已完成，PIMLQZ-20260402043 | AT40: 否 | AU40: 2026-04-17 | AV40: LCL | AX40: 92.88 | AY40: False | AZ40: 否 | BA40: 办公室 | BB40: 自拼 | BC40: 0 | BD40: 0 | BE40: False | BF40: 1120.6 | BG40: True | BI40: 18576 | BJ40: 1 | BL40: / | BM40: 0.0596 | BN40: 18576 | BP40: LCL | BQ40: 92.88 | BR40: 2137.06 | BS40: 16855.6 | BT40: 1867.68 | BU40: 0.0993 | BV40: 1120.6 | BW40: 0.0596 | BX40: 0 | BY40: 否 | BZ40: 2644.8 | CA40: True | CB40: 0.138589 | CC40: 2026-06-02 | CD40: False | CE40: 0 | CF40: 0 | CG40: 48 | CH40: 18576 | CJ40: 52.64 | CK40: 18576 | CL40: 314.02 | CM40: 0 | CN40: 7 | CO40: 财务经理-通过 | CP40: 已结束 | CQ40: 0 | CR40: =IF(COUNTIF('畅想下单（外销合同导出）'!$B$2:$B$100,B40)>0,"有","无") -> 有
A41: 昊特赛十公司 | B41: HSJ26R004-3 | C41: 46113 | D41: 夏煜昕 | E41: DGL-HT | F41: 0.0676 | G41: USD | H41: =IFERROR(SUMIFS(畅想出运数据透视!$B$4:$B$500,畅想出运数据透视!$A$4:$A$500,B41),"0") -> 6777.87 | I41: =IFERROR(VLOOKUP(B41,CHOOSE({1,2},畅想出运数据透视!$A$4:$A$500,畅想出运数据透视!$D$4:$D$500),2,FALSE),"") -> 5.77% | J41: =I41*M41 -> 396.7452 | K41: =J41-N41 -> -68.0724 | L41: 6876 | M41: =L41 -> 6876 | N41: =M41*F41 -> 464.8176 | O41: 2026-05-14 | P41: 2026-05-18 | Q41: 2026-05-14 | R41: =MONTH(Q41) -> 5 | S41: 已通过 | T41: 美国0830 | U41: 宁波昊特赛进出口有限公司 | V41: FOB | W41: 100% T/T Before shipment | X41: 0 | Y41: 待审核 | Z41: 已审核 | AA41: 3600 | AB41: 0 | AC41: 150 | AD41: 705 | AE41: 540 | AF41: 1.995 | AG41: 0 | AH41: 6876 | AI41: 6.7 | AJ41: 0 | AK41: 5384.07 | AL41: 20 | AM41: 50 | AN41: 0 | AO41: 6807.87 | AP41: 48.13 | AQ41: 3084.91 | AS41: PI毛利前置审批已完成，PIMLQZ-20260402043 | AT41: 是 | AU41: 2026-04-11 | AV41: LCL | AX41: 234 | AY41: False | AZ41: 否 | BA41: 办公室 | BB41: 自拼 | BC41: 0 | BD41: 0 | BE41: False | BF41: 1850.95 | BG41: False | BI41: 46800 | BJ41: 1 | BL41: / | BM41: 0.0406 | BN41: 46800 | BP41: LCL | BQ41: 234 | BR41: 5384.07 | BS41: 42293.81 | BT41: 3084.91 | BU41: 0.0676 | BV41: 1850.95 | BW41: 0.0406 | BX41: 0 | BY41: 否 | BZ41: 4653.27 | CA41: True | CB41: 0.101006 | CC41: 2026-05-18 | CD41: False | CE41: 0 | CF41: 0 | CG41: 36 | CH41: 46800 | CJ41: 132.02 | CK41: 46800 | CL41: 695.87 | CM41: 0 | CN41: 5 | CO41: 财务经理-通过 | CP41: 已结束 | CQ41: 0 | CR41: =IF(COUNTIF('畅想下单（外销合同导出）'!$B$2:$B$100,B41)>0,"有","无") -> 有
A42: 昊特赛三公司 | B42: HSC26X017 | C42: 46113 | D42: 熊环英 | E42: LPP | F42: 0.1068 | G42: USD | H42: =IFERROR(SUMIFS(畅想出运数据透视!$B$4:$B$500,畅想出运数据透视!$A$4:$A$500,B42),"0") -> 0 | I42: =IFERROR(VLOOKUP(B42,CHOOSE({1,2},畅想出运数据透视!$A$4:$A$500,畅想出运数据透视!$D$4:$D$500),2,FALSE),"") | L42: 1612.8 | M42: =L42 -> 1612.8 | N42: =M42*F42 -> 172.24704 | O42: 2026-07-10 | P42: 2026-07-20 | Q42: 2026-07-10 | R42: =MONTH(Q42) -> 7 | S42: 已通过 | T42: 波兰749 | U42: 宁波昊特赛进出口有限公司 | V42: FOB | W42: OA 90 DAYS | X42: 0 | Y42: 待审核 | Z42: 已审核 | AA42: 1536 | AB42: 0 | AC42: 32 | AD42: 232.96 | AE42: 168.96 | AF42: 1.5872 | AG42: 0 | AH42: 1612.8 | AI42: 6.7 | AJ42: 0 | AK42: 1060.25 | AL42: 20 | AM42: 50 | AN42: 0 | AO42: 1581.51 | AP42: 11.29 | AQ42: 1131.19 | AS42: PIMLQZ-20260407049 | AT42: 否 | AU42: 2026-04-23 | AV42: LCL | AW42: LPP S.A. | AX42: 46.08 | AY42: False | AZ42: 否 | BA42: 客户第一组 | BB42: 外部工厂 | BC42: 0 | BD42: 108.06 | BE42: False | BF42: 1131.19 | BG42: True | BI42: 9216 | BJ42: 1 | BL42: 无 | BM42: 0.1068 | BN42: 9216 | BP42: 无 | BQ42: 46.08 | BR42: 1060.25 | BS42: 9310.79 | BT42: 1131.19 | BU42: 0.1068 | BV42: 1131.19 | BW42: 0.1068 | BX42: 0 | BY42: 否 | BZ42: 2650.01 | CA42: False | CB42: 0.245241 | CC42: 2026-06-30 | CD42: False | CE42: 0 | CF42: 0 | CG42: 60 | CH42: 9216 | CJ42: 105.04 | CK42: 9216 | CL42: 1000 | CM42: 0 | CN42: 24 | CO42: 财务经理-通过 | CP42: 已结束 | CQ42: 0 | CR42: =IF(COUNTIF('畅想下单（外销合同导出）'!$B$2:$B$100,B42)>0,"有","无") -> 有
A43: 昊特赛十公司 | B43: HSJ26R004-2 | C43: 46113 | D43: 夏煜昕 | E43: DGL-HT | F43: 0.0369 | G43: USD | H43: =IFERROR(SUMIFS(畅想出运数据透视!$B$4:$B$500,畅想出运数据透视!$A$4:$A$500,B43),"0") -> 7293.23 | I43: =IFERROR(VLOOKUP(B43,CHOOSE({1,2},畅想出运数据透视!$A$4:$A$500,畅想出运数据透视!$D$4:$D$500),2,FALSE),"") -> 4.73% | J43: =I43*M43 -> 349.7835 | K43: =J43-N43 -> 76.908 | L43: 7395 | M43: =L43 -> 7395 | N43: =M43*F43 -> 272.8755 | O43: 2026-05-14 | P43: 2026-06-01 | Q43: 2026-05-31 | R43: =MONTH(Q43) -> 5 | S43: 已通过 | T43: 美国0830 | U43: 宁波昊特赛进出口有限公司 | V43: FOB | W43: 100% T/T Before shipment | X43: 0 | Y43: 待审核 | Z43: 已审核 | AA43: 1020 | AB43: 0 | AC43: 85 | AD43: 1207 | AE43: 1122 | AF43: 10.0045 | AG43: 0 | AH43: 7395 | AI43: 6.7 | AJ43: 0 | AK43: 5867.26 | AL43: 20 | AM43: 50 | AN43: 0 | AO43: 7323.23 | AP43: 51.77 | AQ43: 1808.26 | AS43: 销售合同变更流程已完成，流程编号HTBG-202605082400 | AT43: 否 | AU43: 2026-04-10 | AV43: LCL | AX43: 1020 | AY43: False | AZ43: 否 | BA43: 办公室 | BB43: 自拼 | BC43: 0 | BD43: 0 | BE43: False | BF43: 0 | BG43: True | BI43: 51000 | BJ43: 2 | BL43: / | BM43: 0 | BN43: 51000 | BO43: 更换供货商 | BP43: LCL | BQ43: 1020 | BR43: 5867.26 | BS43: 46237.41 | BT43: 1808.26 | BU43: 0.0369 | BV43: 0 | BW43: 0 | BX43: 0 | BY43: 否 | BZ43: 4413.76 | CA43: False | CB43: 0.089083 | CC43: 2026-06-01 | CD43: False | CE43: 0 | CF43: 0 | CG43: 20 | CH43: 51000 | CJ43: 662.06 | CK43: 51000 | CL43: 392.61 | CM43: 0 | CN43: 4 | CO43: 财务经理-通过 | CP43: 已结束 | CQ43: 0 | CR43: =IF(COUNTIF('畅想下单（外销合同导出）'!$B$2:$B$100,B43)>0,"有","无") -> 有
A44: 昊特赛三公司 | B44: HSC26H008 | C44: 46113 | D44: 黄家辉 | E44: 宁波腾峰 | F44: 0.1987 | G44: RMB | H44: =IFERROR(SUMIFS(畅想出运数据透视!$B$4:$B$500,畅想出运数据透视!$A$4:$A$500,B44),"0") -> 8900.25 | I44: =IFERROR(VLOOKUP(B44,CHOOSE({1,2},畅想出运数据透视!$A$4:$A$500,畅想出运数据透视!$D$4:$D$500),2,FALSE),"") -> 21.48% | J44: =I44*M44 -> 13164.834 | K44: =J44-N44 -> 986.74968 | L44: 61288.8 | M44: =L44 -> 61288.8 | N44: =M44*F44 -> 12178.085 | O44: 2026-05-15 | P44: 2026-05-20 | Q44: 2026-05-15 | R44: =MONTH(Q44) -> 5 | S44: 已通过 | T44: 宁波市863 | U44: 宁波昊特赛进出口有限公司 | V44: EXW | W44: OA 60DAYS | X44: 0 | Y44: 待审核 | Z44: 已审核 | AA44: 4560 | AB44: 0 | AC44: 310 | AD44: 1024.6 | AE44: 751.2 | AF44: 17.371 | AG44: 0 | AH44: 61288.8 | AI44: 1 | AJ44: 0 | AK44: 0 | AL44: 134 | AM44: 50 | AN44: 0 | AO44: 60725.78 | AP44: 429.02 | AQ44: 12065.19 | AR44: PIMLQZ-20260407048 | AT44: 否 | AU44: 2026-05-01 | AV44: LCL | AW44: 宁波腾峰进出口有限公司 | AX44: 234.6 | AY44: False | AZ44: 否 | BA44: 办公室 | BB44: 外部工厂 | BC44: 0 | BD44: 306.44 | BE44: False | BF44: 0 | BG44: False | BI44: 46920 | BJ44: 1 | BL44: 无 | BM44: 0 | BN44: 46920 | BP44: 无 | BQ44: 234.6 | BR44: 0 | BS44: 48119.55 | BT44: 12065.19 | BU44: 0.1987 | BV44: 0 | BW44: 0 | BX44: 0 | BY44: 否 | BZ44: 14368.8 | CA44: False | CB44: 0.234444 | CC44: 2026-05-20 | CD44: False | CE44: 0 | CF44: 0 | CG44: 40 | CH44: 46920 | CJ44: 1149.55 | CK44: 46920 | CL44: 0 | CM44: 0 | CN44: 3 | CO44: 财务-通过 | CP44: 已结束 | CQ44: 0 | CR44: =IF(COUNTIF('畅想下单（外销合同导出）'!$B$2:$B$100,B44)>0,"有","无") -> 有
A45: 昊特赛十公司 | B45: HSJ26R004-1 | C45: 46113 | D45: 夏煜昕 | E45: DGL-HT | F45: 0.0185 | G45: USD | H45: =IFERROR(SUMIFS(畅想出运数据透视!$B$4:$B$500,畅想出运数据透视!$A$4:$A$500,B45),"0") -> 3298.16 | I45: =IFERROR(VLOOKUP(B45,CHOOSE({1,2},畅想出运数据透视!$A$4:$A$500,畅想出运数据透视!$D$4:$D$500),2,FALSE),"") -> 0.04% | J45: =I45*M45 -> 1.348704 | K45: =J45-N45 -> -61.028856 | L45: 3371.76 | M45: =L45 -> 3371.76 | N45: =M45*F45 -> 62.37756 | O45: 2026-04-27 | P45: 2026-04-30 | Q45: 2026-04-27 | R45: =MONTH(Q45) -> 4 | S45: 已通过 | T45: 美国0830 | U45: 宁波昊特赛进出口有限公司 | V45: FOB | W45: 100% T/T Before shipment | X45: 0 | Y45: 待审核 | Z45: 已审核 | AA45: 3024 | AB45: 0 | AC45: 63 | AD45: 378 | AE45: 315 | AF45: 1.89 | AG45: 0 | AH45: 3371.76 | AI45: 6.7 | AJ45: 0 | AK45: 2783.15 | AL45: 20 | AM45: 50 | AN45: 0 | AO45: 3328.16 | AP45: 23.6 | AQ45: 413.19 | AS45: PI毛利前置审批已完成，PIMLQZ-20260402043 | AT45: 否 | AU45: 2026-04-11 | AV45: LCL | AX45: 120.96 | AY45: False | AZ45: 否 | BA45: 办公室 | BB45: 自拼 | BC45: 0 | BD45: 0 | BE45: False | BF45: 247.92 | BG45: False | BI45: 24192 | BJ45: 1 | BL45: / | BM45: 0.0111 | BN45: 24192 | BP45: LCL | BQ45: 120.96 | BR45: 2783.15 | BS45: 21764.51 | BT45: 413.19 | BU45: 0.0185 | BV45: 247.92 | BW45: 0.0111 | BX45: 0 | BY45: 否 | BZ45: 1181.94 | CA45: False | CB45: 0.05232 | CC45: 2026-05-03 | CD45: False | CE45: 0 | CF45: 0 | CG45: 23 | CH45: 24192 | CJ45: 125.07 | CK45: 24192 | CL45: 180.59 | CM45: 0 | CN45: 3 | CO45: 财务经理-通过 | CP45: 已结束 | CQ45: 0 | CR45: =IF(COUNTIF('畅想下单（外销合同导出）'!$B$2:$B$100,B45)>0,"有","无") -> 有
A46: 昊特赛三公司 | B46: HSC26X014 | C46: 46113 | D46: 熊环英 | E46: URBAN IMPORTS | F46: 0.164 | G46: USD | H46: =IFERROR(SUMIFS(畅想出运数据透视!$B$4:$B$500,畅想出运数据透视!$A$4:$A$500,B46),"0") -> 3773.74 | I46: =IFERROR(VLOOKUP(B46,CHOOSE({1,2},畅想出运数据透视!$A$4:$A$500,畅想出运数据透视!$D$4:$D$500),2,FALSE),"") -> 17.94% | J46: =I46*M46 -> 687.17376 | K46: =J46-N46 -> 58.98816 | L46: 3830.4 | M46: =L46 -> 3830.4 | N46: =M46*F46 -> 628.1856 | O46: 2026-05-05 | P46: 2026-05-20 | Q46: 2026-05-05 | R46: =MONTH(Q46) -> 5 | S46: 已通过 | T46: 美国5529 | U46: 宁波昊特赛进出口有限公司 | V46: FOB | W46: OA 60DAYS | X46: 0 | Y46: 待审核 | Z46: 已审核 | AA46: 5760 | AB46: 0 | AC46: 240 | AD46: 744 | AE46: 655.2 | AF46: 3.072 | AG46: 0 | AH46: 3830.4 | AI46: 6.7 | AJ46: 0 | AK46: 2690.38 | AL46: 20 | AM46: 50 | AN46: 0 | AO46: 3783.59 | AP46: 26.81 | AQ46: 4156.28 | AS46: PIMLQZ-20260407045 | AT46: 否 | AU46: 2026-04-23 | AV46: LCL | AX46: 116.93 | AY46: False | AZ46: 否 | BA46: 客户第一组 | BB46: 外部工厂 | BC46: 0 | BD46: 128.32 | BE46: False | BF46: 4156.3 | BG46: False | BI46: 23385.6 | BJ46: 1 | BL46: 无 | BM46: 0.164 | BN46: 23385.6 | BP46: 无 | BQ46: 116.93 | BR46: 2690.38 | BS46: 20948.51 | BT46: 4156.28 | BU46: 0.164 | BV46: 4156.3 | BW46: 0.164 | BX46: 0 | BY46: 否 | BZ46: 4968.46 | CA46: False | CB46: 0.193599 | CC46: 2026-05-10 | CD46: False | CE46: 0 | CF46: 0 | CG46: 30 | CH46: 23385.6 | CJ46: 203.29 | CK46: 23385.6 | CL46: 0 | CM46: 0 | CN46: 3 | CO46: 财务-通过 | CP46: 已结束 | CQ46: 0 | CR46: =IF(COUNTIF('畅想下单（外销合同导出）'!$B$2:$B$100,B46)>0,"有","无") -> 有
A47: 昊特赛三公司 | B47: HSC26H007-1 | C47: 46113 | D47: 黄家辉 | E47: LPP | F47: 0.0951 | G47: USD | H47: =IFERROR(SUMIFS(畅想出运数据透视!$B$4:$B$500,畅想出运数据透视!$A$4:$A$500,B47),"0") -> 15865.13 | I47: =IFERROR(VLOOKUP(B47,CHOOSE({1,2},畅想出运数据透视!$A$4:$A$500,畅想出运数据透视!$D$4:$D$500),2,FALSE),"") -> 6.31% | J47: =I47*M47 -> 2158.02 | K47: =J47-N47 -> -1094.4 | L47: 34200 | M47: =L47 -> 34200 | N47: =M47*F47 -> 3252.42 | O47: 2026-05-22 | P47: 2026-06-01 | Q47: 2026-05-22 | R47: =MONTH(Q47) -> 5 | S47: 已通过 | T47: 波兰749 | U47: 宁波昊特赛进出口有限公司 | V47: FOB | W47: OA 90 DAYS | X47: 0 | Y47: 待审核 | Z47: 已审核 | AA47: 11000 | AB47: 0 | AC47: 975 | AD47: 10092.5 | AE47: 9300 | AF47: 45.89 | AG47: 0 | AH47: 34200 | AI47: 6.7 | AJ47: 0 | AK47: 25689.38 | AL47: 68.4 | AM47: 50 | AN47: 0 | AO47: 33892.2 | AP47: 239.4 | AQ47: 21583.88 | AT47: 否 | AU47: 2026-04-30 | AV47: 40HQ | AW47: LPP S.A. | AX47: 2505 | AY47: False | AZ47: 否 | BA47: 办公室 | BB47: 自拼 | BC47: 0 | BD47: 2291.4 | BE47: False | BF47: 0 | BG47: True | BI47: 223300 | BJ47: 2 | BL47: 无 | BM47: 0 | BN47: 223300 | BO47: 装量上错 | BP47: 无 | BQ47: 2505 | BR47: 25689.38 | BS47: 200697.46 | BT47: 21583.88 | BU47: 0.0951 | BV47: 0 | BW47: 0 | BX47: 0 | BY47: 否 | BZ47: 31529.38 | CA47: False | CB47: 0.137599 | CC47: 2026-06-01 | CD47: False | CE47: 0 | CF47: 0 | CG47: 40 | CH47: 223300 | CJ47: 3036.84 | CK47: 223300 | CL47: 0 | CM47: 0 | CN47: 19 | CO47: 财务经理-通过 | CP47: 已结束 | CQ47: 0 | CR47: =IF(COUNTIF('畅想下单（外销合同导出）'!$B$2:$B$100,B47)>0,"有","无") -> 有
A48: 昊特赛三公司 | B48: HSC26X013 | C48: 46113 | D48: 熊环英 | E48: LPP | F48: 0.1941 | G48: USD | H48: =IFERROR(SUMIFS(畅想出运数据透视!$B$4:$B$500,畅想出运数据透视!$A$4:$A$500,B48),"0") -> 2471.81 | I48: =IFERROR(VLOOKUP(B48,CHOOSE({1,2},畅想出运数据透视!$A$4:$A$500,畅想出运数据透视!$D$4:$D$500),2,FALSE),"") -> 13.36% | J48: =I48*M48 -> 806.66611 | K48: =J48-N48 -> -365.29416 | L48: 6037.92 | M48: =L48 -> 6037.92 | N48: =M48*F48 -> 1171.9603 | O48: 2026-09-28 | P48: 2026-09-28 | Q48: 2026-09-28 | R48: =MONTH(Q48) -> 9 | S48: 已通过 | T48: 波兰749 | U48: 宁波昊特赛进出口有限公司 | V48: FOB | W48: 100% T/T At sight of B/L copy | X48: 0 | Y48: 待审核 | Z48: 已审核 | AA48: 5040 | AB48: 0 | AC48: 210 | AD48: 2629.2 | AE48: 2562 | AF48: 13.6626 | AG48: 0 | AH48: 6037.92 | AI48: 6.7 | AJ48: 0 | AK48: 3896.41 | AL48: 20 | AM48: 50 | AN48: 0 | AO48: 5975.65 | AP48: 42.27 | AQ48: 7771.67 | AS48: CRM-PI毛利前置审批申请（昊特赛） - 归档 PIMLQZ-20260401041 | AT48: 否 | AU48: 2026-04-30 | AV48: LCL | AW48: LPP S.A. | AX48: 338.69 | AY48: False | AZ48: 否 | BA48: 客户第一组 | BB48: 外部工厂 | BC48: 0 | BD48: 0 | BE48: False | BF48: 0 | BG48: True | BI48: 33868.8 | BJ48: 3 | BL48: 无 | BM48: 0 | BN48: 33868.8 | BO48: 系统出错 | BP48: 无 | BQ48: 338.69 | BR48: 3896.41 | BS48: 31926.53 | BT48: 7771.67 | BU48: 0.1941 | BV48: 0 | BW48: 0 | BX48: 0 | BY48: 否 | BZ48: 10481.67 | CA48: False | CB48: 0.259101 | CC48: 2026-09-02 | CD48: False | CE48: 0 | CF48: 0 | CG48: 80 | CH48: 33868.8 | CJ48: 904.14 | CK48: 33868.8 | CL48: 1000 | CM48: 0 | CN48: 73 | CO48: 财务-通过 | CP48: 已结束 | CQ48: 0 | CR48: =IF(COUNTIF('畅想下单（外销合同导出）'!$B$2:$B$100,B48)>0,"有","无") -> 有
